Workbook
Name AVAIL1: 'DATA ENTRY - JANITORIAL'!$E$2:$E$33
Name AVAIL1: 'DATA ENTRY - RECEIVED'!$E$2:$E$2
Name AVAIL1: 'DATA ENTRY - RELEASED'!$B$2:$B$630
Name AVAIL1: SUMMARY!$B$2:$B$2
Name AVAIL1: 'DATA ENTRY - REQUEST'!$E$2:$E$2
Name Excel_BuiltIn_Print_Area: 'Inventory Supply 2021'!$A$1:$J$150
Name Excel_BuiltIn_Print_Area_1: #REF!
Name Excel_BuiltIn_Print_Area_1_1: #REF!
Name Excel_BuiltIn_Print_Area_1_1_1: #REF!
Name Excel_BuiltIn_Print_Area_1_1_1_1: #REF!
Name Excel_BuiltIn_Print_Area_2: #REF!
Name Excel_BuiltIn_Print_Area_4_1: #REF!
Name REQUEST1: 'DATA ENTRY - REQUEST'!$C:$E
Name REQUEST2: 'DATA ENTRY - REQUEST'!$C:$F
Name SECTION: REFERENCE!$N$3:$N$17
Name STOCKS: 'SUPPLIES SUMMARY'!$A$2:$G$126
Name SUPPLY: REFERENCE!$B$1:$B$114
Name SUPPLY2: REFERENCE!$B$1:$E$114
Name SUPPLY3: 'SUPPLIES SUMMARY'!$A$3:$G$144
Name YEAR2023: REFERENCE!$I:$J
Name YEAR21: REFERENCE!$I$1:$J$348
Name YEAR22: REFERENCE!$I$1:$J$630

Sheet DATA ENTRY - REQUEST
A1: RIS NO | B1: COUNT (Max20) | C1: CODE | D1: REQUEST DATE (MM/DD/YYYY) | E1: DESCRIPTION | F1: QTY | G1: UNIT | H1: STOCK CODE | I1: MONTH
A2: 2023-016 | B2: 1 | C2: =CONCATENATE(A2,B2) -> 2023-0161 | D2: 45149 | E2: Bond copy paper, A4 size,70gsm 500shts/rm | F2: 60 | G2: =IFERROR(VLOOKUP(E2,SUPPLY2,3,0),"-") -> Ream | H2: =IFERROR(VLOOKUP(E2,SUPPLY2,4,0),"-") -> 2276 | I2: =IFERROR(VLOOKUP(D2,YEAR2023,2,0),"-") -> - | L2: =TODAY() -> 46223
A3: 2025-001 | B3: 1 | C3: =CONCATENATE(A3,B3) -> 2025-0011 | D3: 45664 | E3: Bond copy paper, A4 size,70gsm 500shts/rm | F3: 100 | G3: =IFERROR(VLOOKUP(E3,SUPPLY2,3,0),"-") -> Ream | H3: =IFERROR(VLOOKUP(E3,SUPPLY2,4,0),"-") -> 2276 | I3: =IFERROR(VLOOKUP(D3,YEAR2023,2,0),"-") -> 1
A4: 2025-001 | B4: 2 | C4: =CONCATENATE(A4,B4) -> 2025-0012 | D4: 45664 | E4: Bond prem,LEGAL SIZE, 216x330mm,70gsm 500shts/rm | F4: 100 | G4: =IFERROR(VLOOKUP(E4,SUPPLY2,3,0),"-") -> Ream | H4: =IFERROR(VLOOKUP(E4,SUPPLY2,4,0),"-") -> 2067 | I4: =IFERROR(VLOOKUP(D4,YEAR2023,2,0),"-") -> 1
A5: 2025-001 | B5: 3 | C5: =CONCATENATE(A5,B5) -> 2025-0013 | D5: 45664 | E5: Folder - legal size, 36mm thick (14pts) | F5: 100 | G5: =IFERROR(VLOOKUP(E5,SUPPLY2,3,0),"-") -> C | H5: =IFERROR(VLOOKUP(E5,SUPPLY2,4,0),"-") -> 330 | I5: =IFERROR(VLOOKUP(D5,YEAR2023,2,0),"-") -> 1
A6: 2025-001 | B6: 4 | C6: =CONCATENATE(A6,B6) -> 2025-0014 | D6: 45664 | E6: Envelope - document, 10 x 15 | F6: 100 | G6: =IFERROR(VLOOKUP(E6,SUPPLY2,3,0),"-") -> C | H6: =IFERROR(VLOOKUP(E6,SUPPLY2,4,0),"-") -> 46 | I6: =IFERROR(VLOOKUP(D6,YEAR2023,2,0),"-") -> 1
A7: 2025-001 | B7: 5 | C7: =CONCATENATE(A7,B7) -> 2025-0015 | D7: 45664 | E7: Tape - transparent 1 | F7: 100 | G7: =IFERROR(VLOOKUP(E7,SUPPLY2,3,0),"-") -> Roll | H7: =IFERROR(VLOOKUP(E7,SUPPLY2,4,0),"-") -> 301 | I7: =IFERROR(VLOOKUP(D7,YEAR2023,2,0),"-") -> 1
A8: 2025-002 | B8: 1 | C8: =CONCATENATE(A8,B8) -> 2025-0021 | D8: 45687 | E8: Tape - transparent 1 | F8: 100 | G8: =IFERROR(VLOOKUP(E8,SUPPLY2,3,0),"-") -> Roll | H8: =IFERROR(VLOOKUP(E8,SUPPLY2,4,0),"-") -> 301 | I8: =IFERROR(VLOOKUP(D8,YEAR2023,2,0),"-") -> 1
A9: 2025-002 | B9: 2 | C9: =CONCATENATE(A9,B9) -> 2025-0022 | D9: 45687 | E9: Bond copy paper, A4 size,70gsm 500shts/rm | F9: 100 | G9: =IFERROR(VLOOKUP(E9,SUPPLY2,3,0),"-") -> Ream | H9: =IFERROR(VLOOKUP(E9,SUPPLY2,4,0),"-") -> 2276 | I9: =IFERROR(VLOOKUP(D9,YEAR2023,2,0),"-") -> 1
A10: 2025-002 | B10: 3 | C10: =CONCATENATE(A10,B10) -> 2025-0023 | D10: 45687 | E10: Bond prem,LEGAL SIZE, 216x330mm,70gsm 500shts/rm | F10: 100 | G10: =IFERROR(VLOOKUP(E10,SUPPLY2,3,0),"-") -> Ream | H10: =IFERROR(VLOOKUP(E10,SUPPLY2,4,0),"-") -> 2067 | I10: =IFERROR(VLOOKUP(D10,YEAR2023,2,0),"-") -> 1
A11: 2025-002 | B11: 4 | C11: =CONCATENATE(A11,B11) -> 2025-0024 | D11: 45687 | E11: Paste - solid w/ waterwell and applicator | F11: 10 | G11: =IFERROR(VLOOKUP(E11,SUPPLY2,3,0),"-") -> Piece | H11: =IFERROR(VLOOKUP(E11,SUPPLY2,4,0),"-") -> 336 | I11: =IFERROR(VLOOKUP(D11,YEAR2023,2,0),"-") -> 1
A12: 2025-002 | B12: 5 | C12: =CONCATENATE(A12,B12) -> 2025-0025 | D12: 45687 | E12: Ballpoint pen | F12: 100 | G12: =IFERROR(VLOOKUP(E12,SUPPLY2,3,0),"-") -> Piece | H12: =IFERROR(VLOOKUP(E12,SUPPLY2,4,0),"-") -> 337 | I12: =IFERROR(VLOOKUP(D12,YEAR2023,2,0),"-") -> 1
A13: 2025-002 | B13: 6 | C13: =CONCATENATE(A13,B13) -> 2025-0026 | D13: 45687 | E13: Tape - masking 1 | F13: 50 | G13: =IFERROR(VLOOKUP(E13,SUPPLY2,3,0),"-") -> Roll | H13: =IFERROR(VLOOKUP(E13,SUPPLY2,4,0),"-") -> 300 | I13: =IFERROR(VLOOKUP(D13,YEAR2023,2,0),"-") -> 1
A14: 2025-002 | B14: 7 | C14: =CONCATENATE(A14,B14) -> 2025-0027 | D14: 45687 | E14: Correction tape | F14: 10 | G14: =IFERROR(VLOOKUP(E14,SUPPLY2,3,0),"-") -> Piece | H14: =IFERROR(VLOOKUP(E14,SUPPLY2,4,0),"-") -> 1960 | I14: =IFERROR(VLOOKUP(D14,YEAR2023,2,0),"-") -> 1
... A24: 2025-003 | B24: 2 | C24: =CONCATENATE(A24,B24) -> 2025-0032 | D24: 45699 | E24: Staple wire, 5000 pcs | F24: 50 | G24: =IFERROR(VLOOKUP(E24,SUPPLY2,3,0),"-") -> Box | H24: =IFERROR(VLOOKUP(E24,SUPPLY2,4,0),"-") -> 310 | I24: =IFERROR(VLOOKUP(D24,YEAR2023,2,0),"-") -> 2
A25: 2025-003 | B25: 3 | C25: =CONCATENATE(A25,B25) -> 2025-0033 | D25: 45699 | E25: Envelope - document, 10 x 15 | F25: 20 | G25: =IFERROR(VLOOKUP(E25,SUPPLY2,3,0),"-") -> C | H25: =IFERROR(VLOOKUP(E25,SUPPLY2,4,0),"-") -> 46 | I25: =IFERROR(VLOOKUP(D25,YEAR2023,2,0),"-") -> 2
A26: 2025-003 | B26: 4 | C26: =CONCATENATE(A26,B26) -> 2025-0034 | D26: 45699 | E26: Bond copy paper, A4 size,70gsm 500shts/rm | F26: 100 | G26: =IFERROR(VLOOKUP(E26,SUPPLY2,3,0),"-") -> Ream | H26: =IFERROR(VLOOKUP(E26,SUPPLY2,4,0),"-") -> 2276 | I26: =IFERROR(VLOOKUP(D26,YEAR2023,2,0),"-") -> 2
A27: 2025-003 | B27: 5 | C27: =CONCATENATE(A27,B27) -> 2025-0035 | D27: 45699 | E27: Bond prem,LEGAL SIZE, 216x330mm,70gsm 500shts/rm | F27: 100 | G27: =IFERROR(VLOOKUP(E27,SUPPLY2,3,0),"-") -> Ream | H27: =IFERROR(VLOOKUP(E27,SUPPLY2,4,0),"-") -> 2067 | I27: =IFERROR(VLOOKUP(D27,YEAR2023,2,0),"-") -> 2
A28: 2025-003 | B28: 6 | C28: =CONCATENATE(A28,B28) -> 2025-0036 | D28: 45699 | E28: Envelope - document, 10 x 15 | F28: 20 | G28: =IFERROR(VLOOKUP(E28,SUPPLY2,3,0),"-") -> C | H28: =IFERROR(VLOOKUP(E28,SUPPLY2,4,0),"-") -> 46 | I28: =IFERROR(VLOOKUP(D28,YEAR2023,2,0),"-") -> 2
A29: 2025-004 | B29: 1 | C29: =CONCATENATE(A29,B29) -> 2025-0041 | D29: 45707 | E29: Bond copy paper, A4 size,70gsm 500shts/rm | F29: 100 | G29: =IFERROR(VLOOKUP(E29,SUPPLY2,3,0),"-") -> Ream | H29: =IFERROR(VLOOKUP(E29,SUPPLY2,4,0),"-") -> 2276 | I29: =IFERROR(VLOOKUP(D29,YEAR2023,2,0),"-") -> 2
A30: 2025-004 | B30: 2 | C30: =CONCATENATE(A30,B30) -> 2025-0042 | D30: 45707 | E30: Bond prem,LEGAL SIZE, 216x330mm,70gsm 500shts/rm | F30: 100 | G30: =IFERROR(VLOOKUP(E30,SUPPLY2,3,0),"-") -> Ream | H30: =IFERROR(VLOOKUP(E30,SUPPLY2,4,0),"-") -> 2067 | I30: =IFERROR(VLOOKUP(D30,YEAR2023,2,0),"-") -> 2
A31: 2025-004 | B31: 3 | C31: =CONCATENATE(A31,B31) -> 2025-0043 | D31: 45707 | E31: MEMBER DATA CHANGE REQUEST PAGE 1&2 | F31: 100 | G31: =IFERROR(VLOOKUP(E31,SUPPLY2,3,0),"-") -> Ream | H31: =IFERROR(VLOOKUP(E31,SUPPLY2,4,0),"-") -> 0 | I31: =IFERROR(VLOOKUP(D31,YEAR2023,2,0),"-") -> 2
A32: 2025-004 | B32: 4 | C32: =CONCATENATE(A32,B32) -> 2025-0044 | D32: 45707 | E32: ACOP- SURVIVING LEGAL SPOUSE | F32: 100 | G32: =IFERROR(VLOOKUP(E32,SUPPLY2,3,0),"-") -> Ream | H32: =IFERROR(VLOOKUP(E32,SUPPLY2,4,0),"-") -> 0 | I32: =IFERROR(VLOOKUP(D32,YEAR2023,2,0),"-") -> 2
A33: 2025-004 | B33: 5 | C33: =CONCATENATE(A33,B33) -> 2025-0045 | D33: 45707 | E33: ACOP- REPRESENTATIVE PAYEE OF DEPENDENT | F33: 50 | G33: =IFERROR(VLOOKUP(E33,SUPPLY2,3,0),"-") -> Ream | H33: =IFERROR(VLOOKUP(E33,SUPPLY2,4,0),"-") -> 0 | I33: =IFERROR(VLOOKUP(D33,YEAR2023,2,0),"-") -> 2
A34: 2025-004 | B34: 6 | C34: =CONCATENATE(A34,B34) -> 2025-0046 | D34: 45707 | E34: ACOP- RETIREMENT/DISABILITY | F34: 100 | G34: =IFERROR(VLOOKUP(E34,SUPPLY2,3,0),"-") -> Ream | H34: =IFERROR(VLOOKUP(E34,SUPPLY2,4,0),"-") -> 0 | I34: =IFERROR(VLOOKUP(D34,YEAR2023,2,0),"-") -> 2
A35: 2025-004 | B35: 7 | C35: =CONCATENATE(A35,B35) -> 2025-0047 | D35: 45707 | E35: Request/Verification Form new Code | F35: 100 | G35: =IFERROR(VLOOKUP(E35,SUPPLY2,3,0),"-") -> Piece | H35: =IFERROR(VLOOKUP(E35,SUPPLY2,4,0),"-") -> 0 | I35: =IFERROR(VLOOKUP(D35,YEAR2023,2,0),"-") -> 2
A36: 2025-004 | B36: 8 | C36: =CONCATENATE(A36,B36) -> 2025-0048 | D36: 45707 | E36: PAYMENT SLIP-CONTRIBUTION 1 | F36: 100 | G36: =IFERROR(VLOOKUP(E36,SUPPLY2,3,0),"-") -> Ream | H36: =IFERROR(VLOOKUP(E36,SUPPLY2,4,0),"-") -> 2521 | I36: =IFERROR(VLOOKUP(D36,YEAR2023,2,0),"-") -> 2
A37: 2025-004 | B37: 9 | C37: =CONCATENATE(A37,B37) -> 2025-0049 | D37: 45707 | E37: PAYMENT SLIP-MEMBER LOAN | F37: 100 | G37: =IFERROR(VLOOKUP(E37,SUPPLY2,3,0),"-") -> Ream | H37: =IFERROR(VLOOKUP(E37,SUPPLY2,4,0),"-") -> 2576 | I37: =IFERROR(VLOOKUP(D37,YEAR2023,2,0),"-") -> 2
... A82: 2025-006 | B82: 17 | C82: =CONCATENATE(A82,B82) -> 2025-00617 | D82: 45730 | E82: Ballpoint pen | F82: 100 | G82: =IFERROR(VLOOKUP(E82,SUPPLY2,3,0),"-") -> Piece | H82: =IFERROR(VLOOKUP(E82,SUPPLY2,4,0),"-") -> 337 | I82: =IFERROR(VLOOKUP(D82,YEAR2023,2,0),"-") -> 3
A83: 2025-007 | B83: 1 | C83: =CONCATENATE(A83,B83) -> 2025-0071 | D83: 45741 | E83: Bond copy paper, A4 size,70gsm 500shts/rm | F83: 100 | G83: =IFERROR(VLOOKUP(E83,SUPPLY2,3,0),"-") -> Ream | I83: =IFERROR(VLOOKUP(D83,YEAR2023,2,0),"-") -> 3
A84: 2025-007 | B84: 2 | C84: =CONCATENATE(A84,B84) -> 2025-0072 | D84: 45741 | E84: Bond prem,LEGAL SIZE, 216x330mm,70gsm 500shts/rm | F84: 100 | G84: =IFERROR(VLOOKUP(E84,SUPPLY2,3,0),"-") -> Ream | H84: =IFERROR(VLOOKUP(E84,SUPPLY2,4,0),"-") -> 2067 | I84: =IFERROR(VLOOKUP(D84,YEAR2023,2,0),"-") -> 3
A85: 2025-007 | B85: 3 | C85: =CONCATENATE(A85,B85) -> 2025-0073 | D85: 45741 | E85: MEMBER DATA CHANGE REQUEST PAGE 1&2 | F85: 20 | G85: =IFERROR(VLOOKUP(E85,SUPPLY2,3,0),"-") -> Ream | H85: =IFERROR(VLOOKUP(E85,SUPPLY2,4,0),"-") -> 0 | I85: =IFERROR(VLOOKUP(D85,YEAR2023,2,0),"-") -> 3
A86: 2025-007 | B86: 4 | C86: =CONCATENATE(A86,B86) -> 2025-0074 | D86: 45741 | E86: Alcohol, ethyl, 68%-72% | F86: 30 | G86: =IFERROR(VLOOKUP(E86,SUPPLY2,3,0),"-") -> Gallon | H86: =IFERROR(VLOOKUP(E86,SUPPLY2,4,0),"-") -> 2617 | I86: =IFERROR(VLOOKUP(D86,YEAR2023,2,0),"-") -> 3
A87: 2025-007 | B87: 5 | C87: =CONCATENATE(A87,B87) -> 2025-0075 | D87: 45741 | E87: Ballpoint pen | F87: 100 | G87: =IFERROR(VLOOKUP(E87,SUPPLY2,3,0),"-") -> Piece | H87: =IFERROR(VLOOKUP(E87,SUPPLY2,4,0),"-") -> 337 | I87: =IFERROR(VLOOKUP(D87,YEAR2023,2,0),"-") -> 3
A88: 2025-007 | B88: 6 | C88: =CONCATENATE(A88,B88) -> 2025-0076 | D88: 45741 | E88: Folder - legal size, 36mm thick (14pts) | F88: 50 | G88: =IFERROR(VLOOKUP(E88,SUPPLY2,3,0),"-") -> C | H88: =IFERROR(VLOOKUP(E88,SUPPLY2,4,0),"-") -> 330 | I88: =IFERROR(VLOOKUP(D88,YEAR2023,2,0),"-") -> 3
A89: 2025-007 | B89: 7 | C89: =CONCATENATE(A89,B89) -> 2025-0077 | D89: 45741 | E89: Tape - transparent 1 | F89: 100 | G89: =IFERROR(VLOOKUP(E89,SUPPLY2,3,0),"-") -> Roll | H89: =IFERROR(VLOOKUP(E89,SUPPLY2,4,0),"-") -> 301 | I89: =IFERROR(VLOOKUP(D89,YEAR2023,2,0),"-") -> 3
A90: 2025-007 | B90: 8 | C90: =CONCATENATE(A90,B90) -> 2025-0078 | D90: 45741 | E90: Packaging tape 2” | F90: 100 | G90: =IFERROR(VLOOKUP(E90,SUPPLY2,3,0),"-") -> Roll | H90: =IFERROR(VLOOKUP(E90,SUPPLY2,4,0),"-") -> 2537 | I90: =IFERROR(VLOOKUP(D90,YEAR2023,2,0),"-") -> 3
A91: 2025-007 | B91: 9 | C91: =CONCATENATE(A91,B91) -> 2025-0079 | D91: 45741 | E91: Pencil | F91: 20 | G91: =IFERROR(VLOOKUP(E91,SUPPLY2,3,0),"-") -> Piece | H91: =IFERROR(VLOOKUP(E91,SUPPLY2,4,0),"-") -> 0 | I91: =IFERROR(VLOOKUP(D91,YEAR2023,2,0),"-") -> 3
A92: 2025-007 | B92: 10 | C92: =CONCATENATE(A92,B92) -> 2025-00710 | D92: 45741 | E92: Paste - solid w/ waterwell and applicator | F92: 10 | G92: =IFERROR(VLOOKUP(E92,SUPPLY2,3,0),"-") -> Piece | H92: =IFERROR(VLOOKUP(E92,SUPPLY2,4,0),"-") -> 336 | I92: =IFERROR(VLOOKUP(D92,YEAR2023,2,0),"-") -> 3
A93: 2025-007 | B93: 11 | C93: =CONCATENATE(A93,B93) -> 2025-00711 | D93: 45741 | E93: ACOP- SURVIVING LEGAL SPOUSE | F93: 20 | G93: =IFERROR(VLOOKUP(E93,SUPPLY2,3,0),"-") -> Ream | H93: =IFERROR(VLOOKUP(E93,SUPPLY2,4,0),"-") -> 0 | I93: =IFERROR(VLOOKUP(D93,YEAR2023,2,0),"-") -> 3
A94: 2025-007 | B94: 12 | C94: =CONCATENATE(A94,B94) -> 2025-00712 | D94: 45741 | E94: Envelope - document, 10 x 15 | F94: 50 | G94: =IFERROR(VLOOKUP(E94,SUPPLY2,3,0),"-") -> C | H94: =IFERROR(VLOOKUP(E94,SUPPLY2,4,0),"-") -> 46 | I94: =IFERROR(VLOOKUP(D94,YEAR2023,2,0),"-") -> 3
A95: 2025-007 | B95: 13 | C95: =CONCATENATE(A95,B95) -> 2025-00713 | D95: 45741 | E95: Binder clip 2” | F95: 50 | G95: =IFERROR(VLOOKUP(E95,SUPPLY2,3,0),"-") -> Box | H95: =IFERROR(VLOOKUP(E95,SUPPLY2,4,0),"-") -> 2552 | I95: =IFERROR(VLOOKUP(D95,YEAR2023,2,0),"-") -> 3
... A131: 2025-012 | B131: 16 | C131: =CONCATENATE(A131,B131) -> 2025-01216 | D131: 45779 | E131: ACOP- RETIREMENT/DISABILITY | F131: 20 | G131: =IFERROR(VLOOKUP(E131,SUPPLY2,3,0),"-") -> Ream | H131: =IFERROR(VLOOKUP(E131,SUPPLY2,4,0),"-") -> 0 | I131: =IFERROR(VLOOKUP(D131,YEAR2023,2,0),"-") -> 5
A132: 2025-013 | B132: 1 | C132: =CONCATENATE(A132,B132) -> 2025-0131 | D132: 45784 | E132: PAYMENT SLIP-CONTRIBUTION 1 | F132: 50 | H132: =IFERROR(VLOOKUP(E132,SUPPLY2,4,0),"-") -> 2521 | I132: =IFERROR(VLOOKUP(D132,YEAR2023,2,0),"-") -> 5
A133: 2025-013 | B133: 2 | C133: =CONCATENATE(A133,B133) -> 2025-0132 | D133: 45784 | E133: PAYMENT SLIP-CONTRIBUTION 2 | F133: 50 | G133: =IFERROR(VLOOKUP(E133,SUPPLY2,3,0),"-") -> PCS | H133: =IFERROR(VLOOKUP(E133,SUPPLY2,4,0),"-") -> 2521 | I133: =IFERROR(VLOOKUP(D133,YEAR2023,2,0),"-") -> 5
A134: 2025-013 | B134: 3 | C134: =CONCATENATE(A134,B134) -> 2025-0133 | D134: 45784 | E134: PAYMENT SLIP-MEMBER LOAN | F134: 50 | G134: =IFERROR(VLOOKUP(E134,SUPPLY2,3,0),"-") -> Ream | H134: =IFERROR(VLOOKUP(E134,SUPPLY2,4,0),"-") -> 2576 | I134: =IFERROR(VLOOKUP(D134,YEAR2023,2,0),"-") -> 5
A135: 2025-014 | B135: 1 | C135: =CONCATENATE(A135,B135) -> 2025-0141 | D135: 45786 | E135: Ribbon – ERC-31 for TMU-950 (epson) | F135: 100 | G135: =IFERROR(VLOOKUP(E135,SUPPLY2,3,0),"-") -> Piece | H135: =IFERROR(VLOOKUP(E135,SUPPLY2,4,0),"-") -> 137 | I135: =IFERROR(VLOOKUP(D135,YEAR2023,2,0),"-") -> 5
A136: 2025-015 | B136: 1 | C136: =CONCATENATE(A136,B136) -> 2025-0151 | D136: 45793 | E136: Bond copy paper, A4 size,70gsm 500shts/rm | F136: 50 | G136: =IFERROR(VLOOKUP(E136,SUPPLY2,3,0),"-") -> Ream | H136: =IFERROR(VLOOKUP(E136,SUPPLY2,4,0),"-") -> 2276 | I136: =IFERROR(VLOOKUP(D136,YEAR2023,2,0),"-") -> 5
A137: 2025-015 | B137: 2 | C137: =CONCATENATE(A137,B137) -> 2025-0152 | D137: 45793 | E137: Bond prem,LEGAL SIZE, 216x330mm,70gsm 500shts/rm | F137: 50 | G137: =IFERROR(VLOOKUP(E137,SUPPLY2,3,0),"-") -> Ream | H137: =IFERROR(VLOOKUP(E137,SUPPLY2,4,0),"-") -> 2067 | I137: =IFERROR(VLOOKUP(D137,YEAR2023,2,0),"-") -> 5
A138: 2025-015 | B138: 3 | C138: =CONCATENATE(A138,B138) -> 2025-0153 | D138: 45793 | E138: MEMBER DATA CHANGE REQUEST PAGE 1&2 | F138: 20 | G138: =IFERROR(VLOOKUP(E138,SUPPLY2,3,0),"-") -> Ream | H138: =IFERROR(VLOOKUP(E138,SUPPLY2,4,0),"-") -> 0 | I138: =IFERROR(VLOOKUP(D138,YEAR2023,2,0),"-") -> 5
A139: 2025-015 | B139: 4 | C139: =CONCATENATE(A139,B139) -> 2025-0154 | D139: 45793 | E139: Alcohol, ethyl, 68%-72% | F139: 50 | G139: =IFERROR(VLOOKUP(E139,SUPPLY2,3,0),"-") -> Gallon | H139: =IFERROR(VLOOKUP(E139,SUPPLY2,4,0),"-") -> 2617 | I139: =IFERROR(VLOOKUP(D139,YEAR2023,2,0),"-") -> 5
A140: 2025-015 | B140: 5 | C140: =CONCATENATE(A140,B140) -> 2025-0155 | D140: 45793 | E140: Ballpoint pen | F140: 100 | G140: =IFERROR(VLOOKUP(E140,SUPPLY2,3,0),"-") -> Piece | H140: =IFERROR(VLOOKUP(E140,SUPPLY2,4,0),"-") -> 337 | I140: =IFERROR(VLOOKUP(D140,YEAR2023,2,0),"-") -> 5
A141: 2025-015 | B141: 6 | C141: =CONCATENATE(A141,B141) -> 2025-0156 | D141: 45793 | E141: Folder - legal size, 36mm thick (14pts) | F141: 50 | G141: =IFERROR(VLOOKUP(E141,SUPPLY2,3,0),"-") -> C | H141: =IFERROR(VLOOKUP(E141,SUPPLY2,4,0),"-") -> 330 | I141: =IFERROR(VLOOKUP(D141,YEAR2023,2,0),"-") -> 5
A142: 2025-015 | B142: 7 | C142: =CONCATENATE(A142,B142) -> 2025-0157 | D142: 45793 | E142: Tape - transparent 1 | F142: 50 | G142: =IFERROR(VLOOKUP(E142,SUPPLY2,3,0),"-") -> Roll | H142: =IFERROR(VLOOKUP(E142,SUPPLY2,4,0),"-") -> 301 | I142: =IFERROR(VLOOKUP(D142,YEAR2023,2,0),"-") -> 5
A143: 2025-015 | B143: 8 | C143: =CONCATENATE(A143,B143) -> 2025-0158 | D143: 45793 | E143: Packaging tape 2” | F143: 50 | G143: =IFERROR(VLOOKUP(E143,SUPPLY2,3,0),"-") -> Roll | H143: =IFERROR(VLOOKUP(E143,SUPPLY2,4,0),"-") -> 2537 | I143: =IFERROR(VLOOKUP(D143,YEAR2023,2,0),"-") -> 5
A144: 2025-015 | B144: 9 | C144: =CONCATENATE(A144,B144) -> 2025-0159 | D144: 45793 | E144: Pencil | F144: 10 | G144: =IFERROR(VLOOKUP(E144,SUPPLY2,3,0),"-") -> Piece | H144: =IFERROR(VLOOKUP(E144,SUPPLY2,4,0),"-") -> 0 | I144: =IFERROR(VLOOKUP(D144,YEAR2023,2,0),"-") -> 5
... A213: 2025-019 | B213: 15 | C213: =CONCATENATE(A213,B213) -> 2025-01915 | D213: 45862 | E213: MEMBER'S/CLAIMANT'S PHOTO SIGNATURE CARD | F213: 10 | G213: =IFERROR(VLOOKUP(E213,SUPPLY2,3,0),"-") -> Ream | H213: =IFERROR(VLOOKUP(E213,SUPPLY2,4,0),"-") -> 1976 | I213: =IFERROR(VLOOKUP(D213,YEAR2023,2,0),"-") -> 7
A214: 2025-019 | B214: 16 | C214: =CONCATENATE(A214,B214) -> 2025-01916 | D214: 45862 | E214: Ribbon – ERC-31 for TMU-950 (epson) | F214: 20 | G214: =IFERROR(VLOOKUP(E204,SUPPLY2,3,0),"-") -> Roll | H214: =IFERROR(VLOOKUP(E204,SUPPLY2,4,0),"-") -> 300 | I214: =IFERROR(VLOOKUP(D214,YEAR2023,2,0),"-") -> 7
A215: 2025-019 | B215: 17 | C215: =CONCATENATE(A215,B215) -> 2025-01917 | D215: 45862 | E215: Folder - legal size, 36mm thick (14pts) | F215: 50 | G215: =IFERROR(VLOOKUP(E215,SUPPLY2,3,0),"-") -> C | H215: =IFERROR(VLOOKUP(E215,SUPPLY2,4,0),"-") -> 330 | I215: =IFERROR(VLOOKUP(D215,YEAR2023,2,0),"-") -> 7
A216: 2025-019 | B216: 18 | C216: =CONCATENATE(A216,B216) -> 2025-01918 | D216: 45862 | E216: Cerfificate of registration - employer | F216: 50 | G216: =IFERROR(VLOOKUP(E216,SUPPLY2,3,0),"-") -> - | H216: =IFERROR(VLOOKUP(E216,SUPPLY2,4,0),"-") -> - | I216: =IFERROR(VLOOKUP(D216,YEAR2023,2,0),"-") -> 7
A217: 2025-020 | B217: 1 | C217: =CONCATENATE(A217,B217) -> 2025-0201 | D217: 45866 | E217: Alcohol, ethyl, 68%-72% (500ml) | F217: 50 | G217: =IFERROR(VLOOKUP(E217,SUPPLY2,3,0),"-") -> Bottle | H217: =IFERROR(VLOOKUP(E217,SUPPLY2,4,0),"-") -> 2618 | I217: =IFERROR(VLOOKUP(D217,YEAR2023,2,0),"-") -> 7
A218: 2025-021 | B218: 1 | C218: =CONCATENATE(A218,B218) -> 2025-0211 | D218: 45916 | E218: Bond copy paper, A4 size,70gsm 500shts/rm | F218: 50 | G218: =IFERROR(VLOOKUP(E218,SUPPLY2,3,0),"-") -> Ream | H218: =IFERROR(VLOOKUP(E218,SUPPLY2,4,0),"-") -> 2276 | I218: =IFERROR(VLOOKUP(D218,YEAR2023,2,0),"-") -> 9
A219: 2025-021 | B219: 2 | C219: =CONCATENATE(A219,B219) -> 2025-0212 | D219: 45916 | E219: Bond prem,LEGAL SIZE, 216x330mm,70gsm 500shts/rm | F219: 50 | G219: =IFERROR(VLOOKUP(E219,SUPPLY2,3,0),"-") -> Ream | H219: =IFERROR(VLOOKUP(E219,SUPPLY2,4,0),"-") -> 2067 | I219: =IFERROR(VLOOKUP(D219,YEAR2023,2,0),"-") -> 9
A220: 2025-021 | B220: 3 | C220: =CONCATENATE(A220,B220) -> 2025-0213 | D220: 45916 | E220: Staple wire, 5000 pcs | F220: 50 | G220: =IFERROR(VLOOKUP(E220,SUPPLY2,3,0),"-") -> Box | H220: =IFERROR(VLOOKUP(E220,SUPPLY2,4,0),"-") -> 310 | I220: =IFERROR(VLOOKUP(D220,YEAR2023,2,0),"-") -> 9
A221: 2025-021 | B221: 4 | C221: =CONCATENATE(A221,B221) -> 2025-0214 | D221: 45916 | E221: Binder clip 1” | F221: 20 | G221: =IFERROR(VLOOKUP(E221,SUPPLY2,3,0),"-") -> Box | H221: =IFERROR(VLOOKUP(E221,SUPPLY2,4,0),"-") -> 2550 | I221: =IFERROR(VLOOKUP(D221,YEAR2023,2,0),"-") -> 9
A222: 2025-021 | B222: 5 | C222: =CONCATENATE(A222,B222) -> 2025-0215 | D222: 45916 | E222: Tape - transparent 1 | F222: 20 | G222: =IFERROR(VLOOKUP(E222,SUPPLY2,3,0),"-") -> Roll | H222: =IFERROR(VLOOKUP(E222,SUPPLY2,4,0),"-") -> 301 | I222: =IFERROR(VLOOKUP(D222,YEAR2023,2,0),"-") -> 9
A223: 2025-021 | B223: 6 | C223: =CONCATENATE(A223,B223) -> 2025-0216 | D223: 45916 | E223: Tape - masking 1 | F223: 20 | G223: =IFERROR(VLOOKUP(E223,SUPPLY2,3,0),"-") -> Roll | H223: =IFERROR(VLOOKUP(E223,SUPPLY2,4,0),"-") -> 300 | I223: =IFERROR(VLOOKUP(D223,YEAR2023,2,0),"-") -> 9
A224: 2025-021 | B224: 7 | C224: =CONCATENATE(A224,B224) -> 2025-0217 | D224: 45916 | E224: PAYMENT SLIP-CONTRIBUTION 1 | F224: 20 | G224: =IFERROR(VLOOKUP(E224,SUPPLY2,3,0),"-") -> Ream | H224: =IFERROR(VLOOKUP(E224,SUPPLY2,4,0),"-") -> 2521 | I224: =IFERROR(VLOOKUP(D224,YEAR2023,2,0),"-") -> 9
A225: 2025-021 | B225: 8 | C225: =CONCATENATE(A225,B225) -> 2025-0218 | D225: 45916 | E225: Paste - solid w/ waterwell and applicator | F225: 10 | G225: =IFERROR(VLOOKUP(E225,SUPPLY2,3,0),"-") -> Piece | H225: =IFERROR(VLOOKUP(E225,SUPPLY2,4,0),"-") -> 336 | I225: =IFERROR(VLOOKUP(D225,YEAR2023,2,0),"-") -> 9
A226: 2025-021 | B226: 9 | C226: =CONCATENATE(A226,B226) -> 2025-0219 | D226: 45916 | E226: ACOP- SURVIVING LEGAL SPOUSE | F226: 10 | G226: =IFERROR(VLOOKUP(E226,SUPPLY2,3,0),"-") -> Ream | H226: =IFERROR(VLOOKUP(E226,SUPPLY2,4,0),"-") -> 0 | I226: =IFERROR(VLOOKUP(D226,YEAR2023,2,0),"-") -> 9
... A424: 2026-007 | B424: 17 | C424: =CONCATENATE(A424,B424) -> 2026-00717 | D424: 46216 | E424: Packaging tape 2” | F424: 20 | G424: =IFERROR(VLOOKUP(E424,SUPPLY2,3,0),"-") -> Roll | H424: =IFERROR(VLOOKUP(E424,SUPPLY2,4,0),"-") -> 2537 | I424: =IFERROR(VLOOKUP(D424,YEAR2023,2,0),"-") -> 0
G425: =IFERROR(VLOOKUP(E425,SUPPLY2,3,0),"-") -> - | H425: =IFERROR(VLOOKUP(E425,SUPPLY2,4,0),"-") -> - | I425: =IFERROR(VLOOKUP(D425,YEAR2023,2,0),"-") -> -
G426: =IFERROR(VLOOKUP(E426,SUPPLY2,3,0),"-") -> - | H426: =IFERROR(VLOOKUP(E426,SUPPLY2,4,0),"-") -> - | I426: =IFERROR(VLOOKUP(D426,YEAR2023,2,0),"-") -> -
G427: =IFERROR(VLOOKUP(E427,SUPPLY2,3,0),"-") -> - | H427: =IFERROR(VLOOKUP(E427,SUPPLY2,4,0),"-") -> - | I427: =IFERROR(VLOOKUP(D427,YEAR2023,2,0),"-") -> -
G428: =IFERROR(VLOOKUP(E428,SUPPLY2,3,0),"-") -> - | H428: =IFERROR(VLOOKUP(E428,SUPPLY2,4,0),"-") -> - | I428: =IFERROR(VLOOKUP(D428,YEAR2023,2,0),"-") -> -

Sheet DATA ENTRY - RECEIVED
A1: RIS NO | B1: COUNT (Max10) | C1: CODE | D1: DATE RECEIVED (MM/DD/YYYY) | E1: DESCRIPTION | F1: STOCKS RECEIVED (QTY) | G1: UNIT | H1: STOCK CODE | I1: MONTH | J1: Column1 | K1: Column2
A2: ='DATA ENTRY - REQUEST'!A2 -> 2023-016 | B2: ='DATA ENTRY - REQUEST'!B2 -> 1 | C2: =Table3[[#This Row],[RIS NO]] & TEXT(Table3[[#This Row],[COUNT (Max10)]], "0;-0") -> 2023-0161 | D2: 45155 | E2: =VLOOKUP(C2,REQUEST1,3,0) -> Bond copy paper, A4 size,70gsm 500shts/rm | F2: 60 | G2: =IFERROR(VLOOKUP(E2,SUPPLY2,3,0),"-") -> Ream | H2: =IFERROR(VLOOKUP(E2,SUPPLY2,4,0),"-") -> 2276 | I2: =IFERROR(VLOOKUP(D2,YEAR2023,2,0),"-") -> -
A3: ='DATA ENTRY - REQUEST'!A3 -> 2025-001 | B3: ='DATA ENTRY - REQUEST'!B3 -> 1 | C3: =Table3[[#This Row],[RIS NO]] & TEXT(Table3[[#This Row],[COUNT (Max10)]], "0;-0") -> 2025-0011 | D3: 45674 | E3: =VLOOKUP(C3,REQUEST1,3,0) -> Bond copy paper, A4 size,70gsm 500shts/rm | F3: 20 | G3: =IFERROR(VLOOKUP(E3,SUPPLY2,3,0),"-") -> Ream | H3: =IFERROR(VLOOKUP(E3,SUPPLY2,4,0),"-") -> 2276 | I3: =IFERROR(VLOOKUP(D3,YEAR2023,2,0),"-") -> 1
A4: ='DATA ENTRY - REQUEST'!A4 -> 2025-001 | B4: ='DATA ENTRY - REQUEST'!B4 -> 2 | C4: =Table3[[#This Row],[RIS NO]] & TEXT(Table3[[#This Row],[COUNT (Max10)]], "0;-0") -> 2025-0012 | D4: 45674 | E4: =VLOOKUP(C4,REQUEST1,3,0) -> Bond prem,LEGAL SIZE, 216x330mm,70gsm 500shts/rm | F4: 20 | G4: =IFERROR(VLOOKUP(E4,SUPPLY2,3,0),"-") -> Ream | H4: =IFERROR(VLOOKUP(E4,SUPPLY2,4,0),"-") -> 2067 | I4: =IFERROR(VLOOKUP(D4,YEAR2023,2,0),"-") -> 1
A5: ='DATA ENTRY - REQUEST'!A5 -> 2025-001 | B5: ='DATA ENTRY - REQUEST'!B5 -> 3 | C5: =Table3[[#This Row],[RIS NO]] & TEXT(Table3[[#This Row],[COUNT (Max10)]], "0;-0") -> 2025-0013 | D5: 45674 | E5: =VLOOKUP(C5,REQUEST1,3,0) -> Folder - legal size, 36mm thick (14pts) | F5: 3 | G5: =IFERROR(VLOOKUP(E5,SUPPLY2,3,0),"-") -> C | H5: =IFERROR(VLOOKUP(E5,SUPPLY2,4,0),"-") -> 330 | I5: =IFERROR(VLOOKUP(D5,YEAR2023,2,0),"-") -> 1
A6: ='DATA ENTRY - REQUEST'!A6 -> 2025-001 | B6: ='DATA ENTRY - REQUEST'!B6 -> 4 | C6: =Table3[[#This Row],[RIS NO]] & TEXT(Table3[[#This Row],[COUNT (Max10)]], "0;-0") -> 2025-0014 | D6: 45699 | E6: =VLOOKUP(C6,REQUEST1,3,0) -> Envelope - document, 10 x 15 | F6: 20 | G6: =IFERROR(VLOOKUP(E6,SUPPLY2,3,0),"-") -> C | H6: =IFERROR(VLOOKUP(E6,SUPPLY2,4,0),"-") -> 46 | I6: =IFERROR(VLOOKUP(D6,YEAR2023,2,0),"-") -> 2
A7: ='DATA ENTRY - REQUEST'!A7 -> 2025-001 | B7: ='DATA ENTRY - REQUEST'!B7 -> 5 | C7: =Table3[[#This Row],[RIS NO]] & TEXT(Table3[[#This Row],[COUNT (Max10)]], "0;-0") -> 2025-0015 | D7: 45699 | E7: =VLOOKUP(C7,REQUEST1,3,0) -> Tape - transparent 1 | F7: 20 | G7: =IFERROR(VLOOKUP(E7,SUPPLY2,3,0),"-") -> Roll | H7: =IFERROR(VLOOKUP(E7,SUPPLY2,4,0),"-") -> 301 | I7: =IFERROR(VLOOKUP(D7,YEAR2023,2,0),"-") -> 2
A8: ='DATA ENTRY - REQUEST'!A8 -> 2025-002 | B8: ='DATA ENTRY - REQUEST'!B8 -> 1 | C8: =Table3[[#This Row],[RIS NO]] & TEXT(Table3[[#This Row],[COUNT (Max10)]], "0;-0") -> 2025-0021 | D8: 45699 | E8: =VLOOKUP(C8,REQUEST1,3,0) -> Tape - transparent 1 | F8: 100 | G8: =IFERROR(VLOOKUP(E8,SUPPLY2,3,0),"-") -> Roll | H8: =IFERROR(VLOOKUP(E8,SUPPLY2,4,0),"-") -> 301 | I8: =IFERROR(VLOOKUP(D8,YEAR2023,2,0),"-") -> 2
A9: ='DATA ENTRY - REQUEST'!A9 -> 2025-002 | B9: ='DATA ENTRY - REQUEST'!B9 -> 2 | C9: =Table3[[#This Row],[RIS NO]] & TEXT(Table3[[#This Row],[COUNT (Max10)]], "0;-0") -> 2025-0022 | D9: 45699 | E9: =VLOOKUP(C9,REQUEST1,3,0) -> Bond copy paper, A4 size,70gsm 500shts/rm | F9: 10 | G9: =IFERROR(VLOOKUP(E9,SUPPLY2,3,0),"-") -> Ream | H9: =IFERROR(VLOOKUP(E9,SUPPLY2,4,0),"-") -> 2276 | I9: =IFERROR(VLOOKUP(D9,YEAR2023,2,0),"-") -> 2
A10: ='DATA ENTRY - REQUEST'!A10 -> 2025-002 | B10: ='DATA ENTRY - REQUEST'!B10 -> 3 | C10: =Table3[[#This Row],[RIS NO]] & TEXT(Table3[[#This Row],[COUNT (Max10)]], "0;-0") -> 2025-0023 | D10: 45699 | E10: =VLOOKUP(C10,REQUEST1,3,0) -> Bond prem,LEGAL SIZE, 216x330mm,70gsm 500shts/rm | F10: 16 | G10: =IFERROR(VLOOKUP(E10,SUPPLY2,3,0),"-") -> Ream | H10: =IFERROR(VLOOKUP(E10,SUPPLY2,4,0),"-") -> 2067 | I10: =IFERROR(VLOOKUP(D10,YEAR2023,2,0),"-") -> 2
A11: ='DATA ENTRY - REQUEST'!A11 -> 2025-002 | B11: ='DATA ENTRY - REQUEST'!B11 -> 4 | C11: =Table3[[#This Row],[RIS NO]] & TEXT(Table3[[#This Row],[COUNT (Max10)]], "0;-0") -> 2025-0024 | D11: 45716 | E11: =VLOOKUP(C11,REQUEST1,3,0) -> Paste - solid w/ waterwell and applicator | F11: 20 | G11: =IFERROR(VLOOKUP(E11,SUPPLY2,3,0),"-") -> Piece | H11: =IFERROR(VLOOKUP(E11,SUPPLY2,4,0),"-") -> 336 | I11: =IFERROR(VLOOKUP(D11,YEAR2023,2,0),"-") -> 2
A12: ='DATA ENTRY - REQUEST'!A12 -> 2025-002 | B12: ='DATA ENTRY - REQUEST'!B12 -> 5 | C12: =Table3[[#This Row],[RIS NO]] & TEXT(Table3[[#This Row],[COUNT (Max10)]], "0;-0") -> 2025-0025 | D12: 45716 | E12: =VLOOKUP(C12,REQUEST1,3,0) -> Ballpoint pen | F12: 20 | G12: =IFERROR(VLOOKUP(E12,SUPPLY2,3,0),"-") -> Piece | H12: =IFERROR(VLOOKUP(E12,SUPPLY2,4,0),"-") -> 337 | I12: =IFERROR(VLOOKUP(D12,YEAR2023,2,0),"-") -> 2
A13: ='DATA ENTRY - REQUEST'!A13 -> 2025-002 | B13: ='DATA ENTRY - REQUEST'!B13 -> 6 | C13: =Table3[[#This Row],[RIS NO]] & TEXT(Table3[[#This Row],[COUNT (Max10)]], "0;-0") -> 2025-0026 | D13: 45716 | E13: =VLOOKUP(C13,REQUEST1,3,0) -> Tape - masking 1 | F13: 20 | G13: =IFERROR(VLOOKUP(E13,SUPPLY2,3,0),"-") -> Roll | H13: =IFERROR(VLOOKUP(E13,SUPPLY2,4,0),"-") -> 300 | I13: =IFERROR(VLOOKUP(D13,YEAR2023,2,0),"-") -> 2
... A21: ='DATA ENTRY - REQUEST'!A21 -> 2025-002 | B21: ='DATA ENTRY - REQUEST'!B21 -> 14 | C21: =Table3[[#This Row],[RIS NO]] & TEXT(Table3[[#This Row],[COUNT (Max10)]], "0;-0") -> 2025-00214 | D21: 45721 | E21: =VLOOKUP(C21,REQUEST1,3,0) -> Folder - legal size, 36mm thick (14pts) | F21: 5 | G21: =IFERROR(VLOOKUP(E21,SUPPLY2,3,0),"-") -> C | H21: =IFERROR(VLOOKUP(E21,SUPPLY2,4,0),"-") -> 330 | I21: =IFERROR(VLOOKUP(D21,YEAR2023,2,0),"-") -> 3
A22: ='DATA ENTRY - REQUEST'!A22 -> 2025-002 | B22: ='DATA ENTRY - REQUEST'!B22 -> 15 | C22: =Table3[[#This Row],[RIS NO]] & TEXT(Table3[[#This Row],[COUNT (Max10)]], "0;-0") -> 2025-00215 | D22: 45721 | E22: =VLOOKUP(C22,REQUEST1,3,0) -> Rubber band - transparent 445 grams | F22: NONE IN STOCK | G22: =IFERROR(VLOOKUP(E22,SUPPLY2,3,0),"-") -> Bag | H22: =IFERROR(VLOOKUP(E22,SUPPLY2,4,0),"-") -> 308 | I22: =IFERROR(VLOOKUP(D22,YEAR2023,2,0),"-") -> 3
A23: ='DATA ENTRY - REQUEST'!A23 -> 2025-003 | B23: ='DATA ENTRY - REQUEST'!B23 -> 1 | C23: =Table3[[#This Row],[RIS NO]] & TEXT(Table3[[#This Row],[COUNT (Max10)]], "0;-0") -> 2025-0031 | D23: 45721 | E23: =VLOOKUP(C23,REQUEST1,3,0) -> Alcohol, ethyl, 68%-72% | F23: NONE IN STOCK | G23: =IFERROR(VLOOKUP(E23,SUPPLY2,3,0),"-") -> Gallon | H23: =IFERROR(VLOOKUP(E23,SUPPLY2,4,0),"-") -> 2617 | I23: =IFERROR(VLOOKUP(D23,YEAR2023,2,0),"-") -> 3
A24: ='DATA ENTRY - REQUEST'!A24 -> 2025-003 | B24: ='DATA ENTRY - REQUEST'!B24 -> 2 | C24: =Table3[[#This Row],[RIS NO]] & TEXT(Table3[[#This Row],[COUNT (Max10)]], "0;-0") -> 2025-0032 | D24: 45721 | E24: =VLOOKUP(C24,REQUEST1,3,0) -> Staple wire, 5000 pcs | F24: NONE IN STOCK | G24: =IFERROR(VLOOKUP(E24,SUPPLY2,3,0),"-") -> Box | H24: =IFERROR(VLOOKUP(E24,SUPPLY2,4,0),"-") -> 310 | I24: =IFERROR(VLOOKUP(D24,YEAR2023,2,0),"-") -> 3
A25: ='DATA ENTRY - REQUEST'!A25 -> 2025-003 | B25: ='DATA ENTRY - REQUEST'!B25 -> 3 | C25: =Table3[[#This Row],[RIS NO]] & TEXT(Table3[[#This Row],[COUNT (Max10)]], "0;-0") -> 2025-0033 | D25: 45721 | E25: =VLOOKUP(C25,REQUEST1,3,0) -> Envelope - document, 10 x 15 | F25: NONE IN STOCK | G25: =IFERROR(VLOOKUP(E25,SUPPLY2,3,0),"-") -> C | H25: =IFERROR(VLOOKUP(E25,SUPPLY2,4,0),"-") -> 46 | I25: =IFERROR(VLOOKUP(D25,YEAR2023,2,0),"-") -> 3
A26: ='DATA ENTRY - REQUEST'!A26 -> 2025-003 | B26: ='DATA ENTRY - REQUEST'!B26 -> 4 | C26: =Table3[[#This Row],[RIS NO]] & TEXT(Table3[[#This Row],[COUNT (Max10)]], "0;-0") -> 2025-0034 | D26: 45721 | E26: =VLOOKUP(C26,REQUEST1,3,0) -> Bond copy paper, A4 size,70gsm 500shts/rm | F26: NONE IN STOCK | G26: =IFERROR(VLOOKUP(E26,SUPPLY2,3,0),"-") -> Ream | H26: =IFERROR(VLOOKUP(E26,SUPPLY2,4,0),"-") -> 2276 | I26: =IFERROR(VLOOKUP(D26,YEAR2023,2,0),"-") -> 3
A27: ='DATA ENTRY - REQUEST'!A27 -> 2025-003 | B27: ='DATA ENTRY - REQUEST'!B27 -> 5 | C27: =Table3[[#This Row],[RIS NO]] & TEXT(Table3[[#This Row],[COUNT (Max10)]], "0;-0") -> 2025-0035 | D27: 45721 | E27: =VLOOKUP(C27,REQUEST1,3,0) -> Bond prem,LEGAL SIZE, 216x330mm,70gsm 500shts/rm | F27: NONE IN STOCK | G27: =IFERROR(VLOOKUP(E27,SUPPLY2,3,0),"-") -> Ream | H27: =IFERROR(VLOOKUP(E27,SUPPLY2,4,0),"-") -> 2067 | I27: =IFERROR(VLOOKUP(D27,YEAR2023,2,0),"-") -> 3
A28: ='DATA ENTRY - REQUEST'!A28 -> 2025-003 | B28: ='DATA ENTRY - REQUEST'!B28 -> 6 | C28: =Table3[[#This Row],[RIS NO]] & TEXT(Table3[[#This Row],[COUNT (Max10)]], "0;-0") -> 2025-0036 | D28: 45721 | E28: =VLOOKUP(C28,REQUEST1,3,0) -> Envelope - document, 10 x 15 | F28: 5 | G28: =IFERROR(VLOOKUP(E28,SUPPLY2,3,0),"-") -> C | H28: =IFERROR(VLOOKUP(E28,SUPPLY2,4,0),"-") -> 46 | I28: =IFERROR(VLOOKUP(D28,YEAR2023,2,0),"-") -> 3
A29: ='DATA ENTRY - REQUEST'!A29 -> 2025-004 | B29: ='DATA ENTRY - REQUEST'!B29 -> 1 | C29: =Table3[[#This Row],[RIS NO]] & TEXT(Table3[[#This Row],[COUNT (Max10)]], "0;-0") -> 2025-0041 | D29: 45721 | E29: =VLOOKUP(C29,REQUEST1,3,0) -> Bond copy paper, A4 size,70gsm 500shts/rm | F29: 20 | G29: =IFERROR(VLOOKUP(E29,SUPPLY2,3,0),"-") -> Ream | H29: =IFERROR(VLOOKUP(E29,SUPPLY2,4,0),"-") -> 2276 | I29: =IFERROR(VLOOKUP(D29,YEAR2023,2,0),"-") -> 3
A30: ='DATA ENTRY - REQUEST'!A30 -> 2025-004 | B30: ='DATA ENTRY - REQUEST'!B30 -> 2 | C30: =Table3[[#This Row],[RIS NO]] & TEXT(Table3[[#This Row],[COUNT (Max10)]], "0;-0") -> 2025-0042 | D30: 45721 | E30: =VLOOKUP(C30,REQUEST1,3,0) -> Bond prem,LEGAL SIZE, 216x330mm,70gsm 500shts/rm | F30: NONE IN STOCK | G30: =IFERROR(VLOOKUP(E30,SUPPLY2,3,0),"-") -> Ream | H30: =IFERROR(VLOOKUP(E30,SUPPLY2,4,0),"-") -> 2067 | I30: =IFERROR(VLOOKUP(D30,YEAR2023,2,0),"-") -> 3
A31: ='DATA ENTRY - REQUEST'!A31 -> 2025-004 | B31: ='DATA ENTRY - REQUEST'!B31 -> 3 | C31: =Table3[[#This Row],[RIS NO]] & TEXT(Table3[[#This Row],[COUNT (Max10)]], "0;-0") -> 2025-0043 | D31: 45721 | E31: =VLOOKUP(C31,REQUEST1,3,0) -> MEMBER DATA CHANGE REQUEST PAGE 1&2 | F31: NONE IN STOCK | G31: =IFERROR(VLOOKUP(E31,SUPPLY2,3,0),"-") -> Ream | H31: =IFERROR(VLOOKUP(E31,SUPPLY2,4,0),"-") -> 0 | I31: =IFERROR(VLOOKUP(D31,YEAR2023,2,0),"-") -> 3
A32: ='DATA ENTRY - REQUEST'!A32 -> 2025-004 | B32: ='DATA ENTRY - REQUEST'!B32 -> 4 | C32: =Table3[[#This Row],[RIS NO]] & TEXT(Table3[[#This Row],[COUNT (Max10)]], "0;-0") -> 2025-0044 | D32: 45721 | E32: =VLOOKUP(C32,REQUEST1,3,0) -> ACOP- SURVIVING LEGAL SPOUSE | F32: NONE IN STOCK | G32: =IFERROR(VLOOKUP(E32,SUPPLY2,3,0),"-") -> Ream | H32: =IFERROR(VLOOKUP(E32,SUPPLY2,4,0),"-") -> 0 | I32: =IFERROR(VLOOKUP(D32,YEAR2023,2,0),"-") -> 3
A33: ='DATA ENTRY - REQUEST'!A33 -> 2025-004 | B33: ='DATA ENTRY - REQUEST'!B33 -> 5 | C33: =Table3[[#This Row],[RIS NO]] & TEXT(Table3[[#This Row],[COUNT (Max10)]], "0;-0") -> 2025-0045 | D33: 45721 | E33: =VLOOKUP(C33,REQUEST1,3,0) -> ACOP- REPRESENTATIVE PAYEE OF DEPENDENT | F33: NONE IN STOCK | G33: =IFERROR(VLOOKUP(E33,SUPPLY2,3,0),"-") -> Ream | H33: =IFERROR(VLOOKUP(E33,SUPPLY2,4,0),"-") -> 0 | I33: =IFERROR(VLOOKUP(D33,YEAR2023,2,0),"-") -> 3
A34: ='DATA ENTRY - REQUEST'!A34 -> 2025-004 | B34: ='DATA ENTRY - REQUEST'!B34 -> 6 | C34: =Table3[[#This Row],[RIS NO]] & TEXT(Table3[[#This Row],[COUNT (Max10)]], "0;-0") -> 2025-0046 | D34: 45721 | E34: =VLOOKUP(C34,REQUEST1,3,0) -> ACOP- RETIREMENT/DISABILITY | F34: NONE IN STOCK | G34: =IFERROR(VLOOKUP(E34,SUPPLY2,3,0),"-") -> Ream | H34: =IFERROR(VLOOKUP(E34,SUPPLY2,4,0),"-") -> 0 | I34: =IFERROR(VLOOKUP(D34,YEAR2023,2,0),"-") -> 3
A35: ='DATA ENTRY - REQUEST'!A35 -> 2025-004 | B35: ='DATA ENTRY - REQUEST'!B35 -> 7 | C35: =Table3[[#This Row],[RIS NO]] & TEXT(Table3[[#This Row],[COUNT (Max10)]], "0;-0") -> 2025-0047 | D35: 45721 | E35: =VLOOKUP(C35,REQUEST1,3,0) -> Request/Verification Form new Code | F35: 20 | G35: =IFERROR(VLOOKUP(E35,SUPPLY2,3,0),"-") -> Piece | H35: =IFERROR(VLOOKUP(E35,SUPPLY2,4,0),"-") -> 0 | I35: =IFERROR(VLOOKUP(D35,YEAR2023,2,0),"-") -> 3
A36: ='DATA ENTRY - REQUEST'!A36 -> 2025-004 | B36: ='DATA ENTRY - REQUEST'!B36 -> 8 | C36: =Table3[[#This Row],[RIS NO]] & TEXT(Table3[[#This Row],[COUNT (Max10)]], "0;-0") -> 2025-0048 | D36: 45721 | E36: =VLOOKUP(C36,REQUEST1,3,0) -> PAYMENT SLIP-CONTRIBUTION 1 | F36: 3 | G36: =IFERROR(VLOOKUP(E36,SUPPLY2,3,0),"-") -> Ream | H36: =IFERROR(VLOOKUP(E36,SUPPLY2,4,0),"-") -> 2521 | I36: =IFERROR(VLOOKUP(D36,YEAR2023,2,0),"-") -> 3
A37: ='DATA ENTRY - REQUEST'!A37 -> 2025-004 | B37: ='DATA ENTRY - REQUEST'!B37 -> 9 | C37: =Table3[[#This Row],[RIS NO]] & TEXT(Table3[[#This Row],[COUNT (Max10)]], "0;-0") -> 2025-0049 | D37: 45730 | E37: =VLOOKUP(C37,REQUEST1,3,0) -> PAYMENT SLIP-MEMBER LOAN | F37: 3 | G37: =IFERROR(VLOOKUP(E37,SUPPLY2,3,0),"-") -> Ream | H37: =IFERROR(VLOOKUP(E37,SUPPLY2,4,0),"-") -> 2576 | I37: =IFERROR(VLOOKUP(D37,YEAR2023,2,0),"-") -> 3
A38: ='DATA ENTRY - REQUEST'!A38 -> 2025-004 | B38: ='DATA ENTRY - REQUEST'!B38 -> 10 | C38: =Table3[[#This Row],[RIS NO]] & TEXT(Table3[[#This Row],[COUNT (Max10)]], "0;-0") -> 2025-00410 | D38: 45730 | E38: =VLOOKUP(C38,REQUEST1,3,0) -> Tape - transparent 1 | F38: 20 | G38: =IFERROR(VLOOKUP(E38,SUPPLY2,3,0),"-") -> Roll | H38: =IFERROR(VLOOKUP(E38,SUPPLY2,4,0),"-") -> 301 | I38: =IFERROR(VLOOKUP(D38,YEAR2023,2,0),"-") -> 3
A39: ='DATA ENTRY - REQUEST'!A39 -> 2025-004 | B39: ='DATA ENTRY - REQUEST'!B39 -> 11 | C39: =Table3[[#This Row],[RIS NO]] & TEXT(Table3[[#This Row],[COUNT (Max10)]], "0;-0") -> 2025-00411 | D39: 45730 | E39: =VLOOKUP(C39,REQUEST1,3,0) -> Correction tape | F39: 2 | G39: =IFERROR(VLOOKUP(E39,SUPPLY2,3,0),"-") -> Piece | H39: =IFERROR(VLOOKUP(E39,SUPPLY2,4,0),"-") -> 1960 | I39: =IFERROR(VLOOKUP(D39,YEAR2023,2,0),"-") -> 3
A40: ='DATA ENTRY - REQUEST'!A40 -> 2025-004 | B40: ='DATA ENTRY - REQUEST'!B40 -> 12 | C40: =Table3[[#This Row],[RIS NO]] & TEXT(Table3[[#This Row],[COUNT (Max10)]], "0;-0") -> 2025-00412 | D40: 45730 | E40: =VLOOKUP(C40,REQUEST1,3,0) -> Envelope - document, 10 x 15 | F40: 2 | G40: =IFERROR(VLOOKUP(E40,SUPPLY2,3,0),"-") -> C | H40: =IFERROR(VLOOKUP(E40,SUPPLY2,4,0),"-") -> 46 | I40: =IFERROR(VLOOKUP(D40,YEAR2023,2,0),"-") -> 3
A41: ='DATA ENTRY - REQUEST'!A41 -> 2025-004 | B41: ='DATA ENTRY - REQUEST'!B41 -> 13 | C41: =Table3[[#This Row],[RIS NO]] & TEXT(Table3[[#This Row],[COUNT (Max10)]], "0;-0") -> 2025-00413 | D41: 45730 | E41: =VLOOKUP(C41,REQUEST1,3,0) -> Folder - legal size, 36mm thick (14pts) | F41: 3 | G41: =IFERROR(VLOOKUP(E41,SUPPLY2,3,0),"-") -> C | H41: =IFERROR(VLOOKUP(E41,SUPPLY2,4,0),"-") -> 330 | I41: =IFERROR(VLOOKUP(D41,YEAR2023,2,0),"-") -> 3
A42: ='DATA ENTRY - REQUEST'!A42 -> 2025-004 | B42: ='DATA ENTRY - REQUEST'!B42 -> 14 | C42: =Table3[[#This Row],[RIS NO]] & TEXT(Table3[[#This Row],[COUNT (Max10)]], "0;-0") -> 2025-00414 | D42: 45730 | E42: =VLOOKUP(C42,REQUEST1,3,0) -> Paper – tissue | F42: 20 | G42: =IFERROR(VLOOKUP(E42,SUPPLY2,3,0),"-") -> Roll | H42: =IFERROR(VLOOKUP(E42,SUPPLY2,4,0),"-") -> 281 | I42: =IFERROR(VLOOKUP(D42,YEAR2023,2,0),"-") -> 3
A43: ='DATA ENTRY - REQUEST'!A43 -> 2025-004 | B43: ='DATA ENTRY - REQUEST'!B43 -> 15 | C43: =Table3[[#This Row],[RIS NO]] & TEXT(Table3[[#This Row],[COUNT (Max10)]], "0;-0") -> 2025-00415 | D43: 45730 | E43: =VLOOKUP(C43,REQUEST1,3,0) -> Rubber band - multicolor, 450 grams | F43: 0 | G43: =IFERROR(VLOOKUP(E43,SUPPLY2,3,0),"-") -> Box | H43: =IFERROR(VLOOKUP(E43,SUPPLY2,4,0),"-") -> 307 | I43: =IFERROR(VLOOKUP(D43,YEAR2023,2,0),"-") -> 3
A44: ='DATA ENTRY - REQUEST'!A44 -> 2025-004 | B44: ='DATA ENTRY - REQUEST'!B44 -> 16 | C44: =Table3[[#This Row],[RIS NO]] & TEXT(Table3[[#This Row],[COUNT (Max10)]], "0;-0") -> 2025-00416 | D44: 45730 | E44: =VLOOKUP(C44,REQUEST1,3,0) -> Rubber band - transparent 445 grams | F44: 0 | G44: =IFERROR(VLOOKUP(E44,SUPPLY2,3,0),"-") -> Bag | H44: =IFERROR(VLOOKUP(E44,SUPPLY2,4,0),"-") -> 308 | I44: =IFERROR(VLOOKUP(D44,YEAR2023,2,0),"-") -> 3
A45: ='DATA ENTRY - REQUEST'!A45 -> 2025-004 | B45: ='DATA ENTRY - REQUEST'!B45 -> 17 | C45: =Table3[[#This Row],[RIS NO]] & TEXT(Table3[[#This Row],[COUNT (Max10)]], "0;-0") -> 2025-00417 | D45: 45730 | E45: =VLOOKUP(C45,REQUEST1,3,0) -> Staple wire, 5000 pcs | F45: 3 | G45: =IFERROR(VLOOKUP(E45,SUPPLY2,3,0),"-") -> Box | H45: =IFERROR(VLOOKUP(E45,SUPPLY2,4,0),"-") -> 310 | I45: =IFERROR(VLOOKUP(D45,YEAR2023,2,0),"-") -> 3
A46: ='DATA ENTRY - REQUEST'!A46 -> 2025-004 | B46: ='DATA ENTRY - REQUEST'!B46 -> 18 | C46: =Table3[[#This Row],[RIS NO]] & TEXT(Table3[[#This Row],[COUNT (Max10)]], "0;-0") -> 2025-00418 | D46: 45730 | E46: =VLOOKUP(C46,REQUEST1,3,0) -> Paste - solid w/ waterwell and applicator | F46: 20 | G46: =IFERROR(VLOOKUP(E46,SUPPLY2,3,0),"-") -> Piece | H46: =IFERROR(VLOOKUP(E46,SUPPLY2,4,0),"-") -> 336 | I46: =IFERROR(VLOOKUP(D46,YEAR2023,2,0),"-") -> 3
... A48: ='DATA ENTRY - REQUEST'!A48 -> 2025-004 | B48: ='DATA ENTRY - REQUEST'!B48 -> 20 | C48: =Table3[[#This Row],[RIS NO]] & TEXT(Table3[[#This Row],[COUNT (Max10)]], "0;-0") -> 2025-00420 | D48: 45730 | E48: =VLOOKUP(C48,REQUEST1,3,0) -> Alcohol, ethyl, 68%-72% | F48: 5 | G48: =IFERROR(VLOOKUP(E48,SUPPLY2,3,0),"-") -> Gallon | H48: =IFERROR(VLOOKUP(E48,SUPPLY2,4,0),"-") -> 2617 | I48: =IFERROR(VLOOKUP(D48,YEAR2023,2,0),"-") -> 3
A49: ='DATA ENTRY - REQUEST'!A49 -> 2025-004 | B49: ='DATA ENTRY - REQUEST'!B49 -> 21 | C49: =Table3[[#This Row],[RIS NO]] & TEXT(Table3[[#This Row],[COUNT (Max10)]], "0;-0") -> 2025-00421 | D49: 45730 | E49: =VLOOKUP(C49,REQUEST1,3,0) -> Packaging tape 2” | F49: NONE IN STOCK | G49: =IFERROR(VLOOKUP(E49,SUPPLY2,3,0),"-") -> Roll | H49: =IFERROR(VLOOKUP(E49,SUPPLY2,4,0),"-") -> 2537 | I49: =IFERROR(VLOOKUP(D49,YEAR2023,2,0),"-") -> 3
A50: ='DATA ENTRY - REQUEST'!A50 -> 2025-004 | B50: ='DATA ENTRY - REQUEST'!B50 -> 22 | C50: =Table3[[#This Row],[RIS NO]] & TEXT(Table3[[#This Row],[COUNT (Max10)]], "0;-0") -> 2025-00422 | D50: 45737 | E50: =VLOOKUP(C50,REQUEST1,3,0) -> Marking pen | F50: 20 | G50: =IFERROR(VLOOKUP(E50,SUPPLY2,3,0),"-") -> Piece | H50: =IFERROR(VLOOKUP(E50,SUPPLY2,4,0),"-") -> 338 | I50: =IFERROR(VLOOKUP(D50,YEAR2023,2,0),"-") -> 3
A51: ='DATA ENTRY - REQUEST'!A51 -> 2025-004 | B51: ='DATA ENTRY - REQUEST'!B51 -> 23 | C51: =Table3[[#This Row],[RIS NO]] & TEXT(Table3[[#This Row],[COUNT (Max10)]], "0;-0") -> 2025-00423 | D51: 45737 | E51: =VLOOKUP(C51,REQUEST1,3,0) -> Bond prem,LEGAL SIZE, 216x330mm,70gsm 500shts/rm | F51: 20 | G51: =IFERROR(VLOOKUP(E51,SUPPLY2,3,0),"-") -> Ream | H51: =IFERROR(VLOOKUP(E51,SUPPLY2,4,0),"-") -> 2067 | I51: =IFERROR(VLOOKUP(D51,YEAR2023,2,0),"-") -> 3
A52: ='DATA ENTRY - REQUEST'!A52 -> 2025-004 | B52: ='DATA ENTRY - REQUEST'!B52 -> 24 | C52: =Table3[[#This Row],[RIS NO]] & TEXT(Table3[[#This Row],[COUNT (Max10)]], "0;-0") -> 2025-00424 | D52: 45737 | E52: =VLOOKUP(C52,REQUEST1,3,0) -> MEMBER DATA CHANGE REQUEST PAGE 1&2 | F52: NONE IN STOCK | G52: =IFERROR(VLOOKUP(E52,SUPPLY2,3,0),"-") -> Ream | H52: =IFERROR(VLOOKUP(E52,SUPPLY2,4,0),"-") -> 0 | I52: =IFERROR(VLOOKUP(D52,YEAR2023,2,0),"-") -> 3
A53: ='DATA ENTRY - REQUEST'!A53 -> 2025-005 | B53: ='DATA ENTRY - REQUEST'!B53 -> 1 | C53: =Table3[[#This Row],[RIS NO]] & TEXT(Table3[[#This Row],[COUNT (Max10)]], "0;-0") -> 2025-0051 | D53: 45737 | E53: =VLOOKUP(C53,REQUEST1,3,0) -> Bond prem,LEGAL SIZE, 216x330mm,70gsm 500shts/rm | F53: NONE IN STOCK | G53: =IFERROR(VLOOKUP(E53,SUPPLY2,3,0),"-") -> Ream | H53: =IFERROR(VLOOKUP(E53,SUPPLY2,4,0),"-") -> 2067 | I53: =IFERROR(VLOOKUP(D53,YEAR2023,2,0),"-") -> 3
A54: ='DATA ENTRY - REQUEST'!A54 -> 2025-005 | B54: ='DATA ENTRY - REQUEST'!B54 -> 2 | C54: =Table3[[#This Row],[RIS NO]] & TEXT(Table3[[#This Row],[COUNT (Max10)]], "0;-0") -> 2025-0052 | D54: 45737 | E54: =VLOOKUP(C54,REQUEST1,3,0) -> Bond copy paper, A4 size,70gsm 500shts/rm | F54: 3 | G54: =IFERROR(VLOOKUP(E54,SUPPLY2,3,0),"-") -> Ream | H54: =IFERROR(VLOOKUP(E54,SUPPLY2,4,0),"-") -> 2276 | I54: =IFERROR(VLOOKUP(D54,YEAR2023,2,0),"-") -> 3
A55: ='DATA ENTRY - REQUEST'!A55 -> 2025-005 | B55: ='DATA ENTRY - REQUEST'!B55 -> 3 | C55: =Table3[[#This Row],[RIS NO]] & TEXT(Table3[[#This Row],[COUNT (Max10)]], "0;-0") -> 2025-0053 | D55: 45737 | E55: =VLOOKUP(C55,REQUEST1,3,0) -> Alcohol, ethyl, 68%-72% | F55: NONE IN STOCK | G55: =IFERROR(VLOOKUP(E55,SUPPLY2,3,0),"-") -> Gallon | H55: =IFERROR(VLOOKUP(E55,SUPPLY2,4,0),"-") -> 2617 | I55: =IFERROR(VLOOKUP(D55,YEAR2023,2,0),"-") -> 3
A56: ='DATA ENTRY - REQUEST'!A56 -> 2025-005 | B56: ='DATA ENTRY - REQUEST'!B56 -> 4 | C56: =Table3[[#This Row],[RIS NO]] & TEXT(Table3[[#This Row],[COUNT (Max10)]], "0;-0") -> 2025-0054 | D56: 45737 | E56: =VLOOKUP(C56,REQUEST1,3,0) -> Paper – tissue | F56: 5 | G56: =IFERROR(VLOOKUP(E56,SUPPLY2,3,0),"-") -> Roll | H56: =IFERROR(VLOOKUP(E56,SUPPLY2,4,0),"-") -> 281 | I56: =IFERROR(VLOOKUP(D56,YEAR2023,2,0),"-") -> 3
A57: ='DATA ENTRY - REQUEST'!A57 -> 2025-005 | B57: ='DATA ENTRY - REQUEST'!B57 -> 5 | C57: =Table3[[#This Row],[RIS NO]] & TEXT(Table3[[#This Row],[COUNT (Max10)]], "0;-0") -> 2025-0055 | D57: 45737 | E57: =VLOOKUP(C57,REQUEST1,3,0) -> Envelope - document, 10 x 15 | F57: 5 | G57: =IFERROR(VLOOKUP(E57,SUPPLY2,3,0),"-") -> C | H57: =IFERROR(VLOOKUP(E57,SUPPLY2,4,0),"-") -> 46 | I57: =IFERROR(VLOOKUP(D57,YEAR2023,2,0),"-") -> 3
A58: ='DATA ENTRY - REQUEST'!A58 -> 2025-005 | B58: ='DATA ENTRY - REQUEST'!B58 -> 6 | C58: =Table3[[#This Row],[RIS NO]] & TEXT(Table3[[#This Row],[COUNT (Max10)]], "0;-0") -> 2025-0056 | D58: 45737 | E58: =VLOOKUP(C58,REQUEST1,3,0) -> Tape - transparent 1 | F58: NONE IN STOCK | G58: =IFERROR(VLOOKUP(E58,SUPPLY2,3,0),"-") -> Roll | H58: =IFERROR(VLOOKUP(E58,SUPPLY2,4,0),"-") -> 301 | I58: =IFERROR(VLOOKUP(D58,YEAR2023,2,0),"-") -> 3
A59: ='DATA ENTRY - REQUEST'!A59 -> 2025-005 | B59: ='DATA ENTRY - REQUEST'!B59 -> 7 | C59: =Table3[[#This Row],[RIS NO]] & TEXT(Table3[[#This Row],[COUNT (Max10)]], "0;-0") -> 2025-0057 | D59: 45737 | E59: =VLOOKUP(C59,REQUEST1,3,0) -> MEMBER DATA CHANGE REQUEST PAGE 1&2 | F59: NONE IN STOCK | G59: =IFERROR(VLOOKUP(E59,SUPPLY2,3,0),"-") -> Ream | H59: =IFERROR(VLOOKUP(E59,SUPPLY2,4,0),"-") -> 0 | I59: =IFERROR(VLOOKUP(D59,YEAR2023,2,0),"-") -> 3
A60: ='DATA ENTRY - REQUEST'!A60 -> 2025-005 | B60: ='DATA ENTRY - REQUEST'!B60 -> 8 | C60: =Table3[[#This Row],[RIS NO]] & TEXT(Table3[[#This Row],[COUNT (Max10)]], "0;-0") -> 2025-0058 | D60: 45737 | E60: =VLOOKUP(C60,REQUEST1,3,0) -> ACOP- SURVIVING LEGAL SPOUSE | F60: 3 | G60: =IFERROR(VLOOKUP(E60,SUPPLY2,3,0),"-") -> Ream | H60: =IFERROR(VLOOKUP(E60,SUPPLY2,4,0),"-") -> 0 | I60: =IFERROR(VLOOKUP(D60,YEAR2023,2,0),"-") -> 3
A61: ='DATA ENTRY - REQUEST'!A61 -> 2025-005 | B61: ='DATA ENTRY - REQUEST'!B61 -> 9 | C61: =Table3[[#This Row],[RIS NO]] & TEXT(Table3[[#This Row],[COUNT (Max10)]], "0;-0") -> 2025-0059 | D61: 45737 | E61: =VLOOKUP(C61,REQUEST1,3,0) -> ACOP- RETIREMENT/DISABILITY | F61: 3 | G61: =IFERROR(VLOOKUP(E61,SUPPLY2,3,0),"-") -> Ream | H61: =IFERROR(VLOOKUP(E61,SUPPLY2,4,0),"-") -> 0 | I61: =IFERROR(VLOOKUP(D61,YEAR2023,2,0),"-") -> 3
A62: ='DATA ENTRY - REQUEST'!A62 -> 2025-005 | B62: ='DATA ENTRY - REQUEST'!B62 -> 10 | C62: =Table3[[#This Row],[RIS NO]] & TEXT(Table3[[#This Row],[COUNT (Max10)]], "0;-0") -> 2025-00510 | D62: 45737 | E62: =VLOOKUP(C62,REQUEST1,3,0) -> Request/Verification Form new Code | F62: NONE IN STOCK | G62: =IFERROR(VLOOKUP(E62,SUPPLY2,3,0),"-") -> Piece | H62: =IFERROR(VLOOKUP(E62,SUPPLY2,4,0),"-") -> 0 | I62: =IFERROR(VLOOKUP(D62,YEAR2023,2,0),"-") -> 3
A63: ='DATA ENTRY - REQUEST'!A63 -> 2025-005 | B63: ='DATA ENTRY - REQUEST'!B63 -> 11 | C63: =Table3[[#This Row],[RIS NO]] & TEXT(Table3[[#This Row],[COUNT (Max10)]], "0;-0") -> 2025-00511 | D63: 45737 | E63: =VLOOKUP(C63,REQUEST1,3,0) -> PAYMENT SLIP-CONTRIBUTION 1 | F63: 10 | G63: =IFERROR(VLOOKUP(E63,SUPPLY2,3,0),"-") -> Ream | H63: =IFERROR(VLOOKUP(E63,SUPPLY2,4,0),"-") -> 2521 | I63: =IFERROR(VLOOKUP(D63,YEAR2023,2,0),"-") -> 3
A64: ='DATA ENTRY - REQUEST'!A64 -> 2025-005 | B64: ='DATA ENTRY - REQUEST'!B64 -> 12 | C64: =Table3[[#This Row],[RIS NO]] & TEXT(Table3[[#This Row],[COUNT (Max10)]], "0;-0") -> 2025-00512 | D64: 45737 | E64: =VLOOKUP(C64,REQUEST1,3,0) -> PAYMENT SLIP-MEMBER LOAN | F64: NONE IN STOCK | G64: =IFERROR(VLOOKUP(E64,SUPPLY2,3,0),"-") -> Ream | H64: =IFERROR(VLOOKUP(E64,SUPPLY2,4,0),"-") -> 2576 | I64: =IFERROR(VLOOKUP(D64,YEAR2023,2,0),"-") -> 3
A65: ='DATA ENTRY - REQUEST'!A65 -> 2025-005 | B65: ='DATA ENTRY - REQUEST'!B65 -> 13 | C65: =Table3[[#This Row],[RIS NO]] & TEXT(Table3[[#This Row],[COUNT (Max10)]], "0;-0") -> 2025-00513 | D65: 45737 | E65: =VLOOKUP(C65,REQUEST1,3,0) -> Folder - legal size, 36mm thick (14pts) | F65: NONE IN STOCK | G65: =IFERROR(VLOOKUP(E65,SUPPLY2,3,0),"-") -> C | H65: =IFERROR(VLOOKUP(E65,SUPPLY2,4,0),"-") -> 330 | I65: =IFERROR(VLOOKUP(D65,YEAR2023,2,0),"-") -> 3
A66: ='DATA ENTRY - REQUEST'!A66 -> 2025-006 | B66: ='DATA ENTRY - REQUEST'!B66 -> 1 | C66: =Table3[[#This Row],[RIS NO]] & TEXT(Table3[[#This Row],[COUNT (Max10)]], "0;-0") -> 2025-0061 | D66: 45737 | E66: =VLOOKUP(C66,REQUEST1,3,0) -> Bond prem,LEGAL SIZE, 216x330mm,70gsm 500shts/rm | F66: NONE IN STOCK | G66: =IFERROR(VLOOKUP(E66,SUPPLY2,3,0),"-") -> Ream | H66: =IFERROR(VLOOKUP(E66,SUPPLY2,4,0),"-") -> 2067 | I66: =IFERROR(VLOOKUP(D66,YEAR2023,2,0),"-") -> 3
A67: ='DATA ENTRY - REQUEST'!A67 -> 2025-006 | B67: ='DATA ENTRY - REQUEST'!B67 -> 2 | C67: =Table3[[#This Row],[RIS NO]] & TEXT(Table3[[#This Row],[COUNT (Max10)]], "0;-0") -> 2025-0062 | D67: 45754 | E67: =VLOOKUP(C67,REQUEST1,3,0) -> Bond copy paper, A4 size,70gsm 500shts/rm | F67: 20 | G67: =IFERROR(VLOOKUP(E67,SUPPLY2,3,0),"-") -> Ream | H67: =IFERROR(VLOOKUP(E67,SUPPLY2,4,0),"-") -> 2276 | I67: =IFERROR(VLOOKUP(D67,YEAR2023,2,0),"-") -> 4
A68: ='DATA ENTRY - REQUEST'!A68 -> 2025-006 | B68: ='DATA ENTRY - REQUEST'!B68 -> 3 | C68: =Table3[[#This Row],[RIS NO]] & TEXT(Table3[[#This Row],[COUNT (Max10)]], "0;-0") -> 2025-0063 | D68: 45754 | E68: =VLOOKUP(C68,REQUEST1,3,0) -> Alcohol, ethyl, 68%-72% | F68: 20 | G68: =IFERROR(VLOOKUP(E68,SUPPLY2,3,0),"-") -> Gallon | H68: =IFERROR(VLOOKUP(E68,SUPPLY2,4,0),"-") -> 2617 | I68: =IFERROR(VLOOKUP(D68,YEAR2023,2,0),"-") -> 4
A69: ='DATA ENTRY - REQUEST'!A69 -> 2025-006 | B69: ='DATA ENTRY - REQUEST'!B69 -> 4 | C69: =Table3[[#This Row],[RIS NO]] & TEXT(Table3[[#This Row],[COUNT (Max10)]], "0;-0") -> 2025-0064 | D69: 45754 | E69: =VLOOKUP(C69,REQUEST1,3,0) -> Envelope - document, 10 x 15 | F69: NONE IN STOCK | G69: =IFERROR(VLOOKUP(E69,SUPPLY2,3,0),"-") -> C | H69: =IFERROR(VLOOKUP(E69,SUPPLY2,4,0),"-") -> 46 | I69: =IFERROR(VLOOKUP(D69,YEAR2023,2,0),"-") -> 4
A70: ='DATA ENTRY - REQUEST'!A70 -> 2025-006 | B70: ='DATA ENTRY - REQUEST'!B70 -> 5 | C70: =Table3[[#This Row],[RIS NO]] & TEXT(Table3[[#This Row],[COUNT (Max10)]], "0;-0") -> 2025-0065 | D70: 45754 | E70: =VLOOKUP(C70,REQUEST1,3,0) -> ACOP- SURVIVING LEGAL SPOUSE | F70: NONE IN STOCK | G70: =IFERROR(VLOOKUP(E70,SUPPLY2,3,0),"-") -> Ream | H70: =IFERROR(VLOOKUP(E70,SUPPLY2,4,0),"-") -> 0 | I70: =IFERROR(VLOOKUP(D70,YEAR2023,2,0),"-") -> 4
A71: ='DATA ENTRY - REQUEST'!A71 -> 2025-006 | B71: ='DATA ENTRY - REQUEST'!B71 -> 6 | C71: =Table3[[#This Row],[RIS NO]] & TEXT(Table3[[#This Row],[COUNT (Max10)]], "0;-0") -> 2025-0066 | D71: 45754 | E71: =VLOOKUP(C71,REQUEST1,3,0) -> ACOP- RETIREMENT/DISABILITY | F71: NONE IN STOCK | G71: =IFERROR(VLOOKUP(E71,SUPPLY2,3,0),"-") -> Ream | H71: =IFERROR(VLOOKUP(E71,SUPPLY2,4,0),"-") -> 0 | I71: =IFERROR(VLOOKUP(D71,YEAR2023,2,0),"-") -> 4
A72: ='DATA ENTRY - REQUEST'!A72 -> 2025-006 | B72: ='DATA ENTRY - REQUEST'!B72 -> 7 | C72: =Table3[[#This Row],[RIS NO]] & TEXT(Table3[[#This Row],[COUNT (Max10)]], "0;-0") -> 2025-0067 | D72: 45754 | E72: =VLOOKUP(C72,REQUEST1,3,0) -> PAYMENT SLIP-CONTRIBUTION 1 | F72: NONE IN STOCK | G72: =IFERROR(VLOOKUP(E72,SUPPLY2,3,0),"-") -> Ream | H72: =IFERROR(VLOOKUP(E72,SUPPLY2,4,0),"-") -> 2521 | I72: =IFERROR(VLOOKUP(D72,YEAR2023,2,0),"-") -> 4
A73: ='DATA ENTRY - REQUEST'!A73 -> 2025-006 | B73: ='DATA ENTRY - REQUEST'!B73 -> 8 | C73: =Table3[[#This Row],[RIS NO]] & TEXT(Table3[[#This Row],[COUNT (Max10)]], "0;-0") -> 2025-0068 | D73: 45754 | E73: =VLOOKUP(C73,REQUEST1,3,0) -> PAYMENT SLIP-MEMBER LOAN | F73: NONE IN STOCK | G73: =IFERROR(VLOOKUP(E73,SUPPLY2,3,0),"-") -> Ream | H73: =IFERROR(VLOOKUP(E73,SUPPLY2,4,0),"-") -> 2576 | I73: =IFERROR(VLOOKUP(D73,YEAR2023,2,0),"-") -> 4
A74: ='DATA ENTRY - REQUEST'!A74 -> 2025-006 | B74: ='DATA ENTRY - REQUEST'!B74 -> 9 | C74: =Table3[[#This Row],[RIS NO]] & TEXT(Table3[[#This Row],[COUNT (Max10)]], "0;-0") -> 2025-0069 | D74: 45754 | E74: =VLOOKUP(C74,REQUEST1,3,0) -> Folder - legal size, 36mm thick (14pts) | F74: NONE IN STOCK | G74: =IFERROR(VLOOKUP(E74,SUPPLY2,3,0),"-") -> C | H74: =IFERROR(VLOOKUP(E74,SUPPLY2,4,0),"-") -> 330 | I74: =IFERROR(VLOOKUP(D74,YEAR2023,2,0),"-") -> 4
A75: ='DATA ENTRY - REQUEST'!A75 -> 2025-006 | B75: ='DATA ENTRY - REQUEST'!B75 -> 10 | C75: =Table3[[#This Row],[RIS NO]] & TEXT(Table3[[#This Row],[COUNT (Max10)]], "0;-0") -> 2025-00610 | D75: 45754 | E75: =VLOOKUP(C75,REQUEST1,3,0) -> Packaging tape 2” | F75: NONE IN STOCK | G75: =IFERROR(VLOOKUP(E75,SUPPLY2,3,0),"-") -> Roll | H75: =IFERROR(VLOOKUP(E75,SUPPLY2,4,0),"-") -> 2537 | I75: =IFERROR(VLOOKUP(D75,YEAR2023,2,0),"-") -> 4
A76: ='DATA ENTRY - REQUEST'!A76 -> 2025-006 | B76: ='DATA ENTRY - REQUEST'!B76 -> 11 | C76: =Table3[[#This Row],[RIS NO]] & TEXT(Table3[[#This Row],[COUNT (Max10)]], "0;-0") -> 2025-00611 | D76: 45754 | E76: =VLOOKUP(C76,REQUEST1,3,0) -> MEMBER DATA CHANGE REQUEST PAGE 1&2 | F76: NONE IN STOCK | G76: =IFERROR(VLOOKUP(E76,SUPPLY2,3,0),"-") -> Ream | H76: =IFERROR(VLOOKUP(E76,SUPPLY2,4,0),"-") -> 0 | I76: =IFERROR(VLOOKUP(D76,YEAR2023,2,0),"-") -> 4
A77: ='DATA ENTRY - REQUEST'!A77 -> 2025-006 | B77: ='DATA ENTRY - REQUEST'!B77 -> 12 | C77: =Table3[[#This Row],[RIS NO]] & TEXT(Table3[[#This Row],[COUNT (Max10)]], "0;-0") -> 2025-00612 | D77: 45389 | E77: =VLOOKUP(C77,REQUEST1,3,0) -> Request/Verification Form new Code | F77: 2 | G77: =IFERROR(VLOOKUP(E77,SUPPLY2,3,0),"-") -> Piece | H77: =IFERROR(VLOOKUP(E77,SUPPLY2,4,0),"-") -> 0 | I77: =IFERROR(VLOOKUP(D77,YEAR2023,2,0),"-") -> -
A78: ='DATA ENTRY - REQUEST'!A78 -> 2025-006 | B78: ='DATA ENTRY - REQUEST'!B78 -> 13 | C78: =Table3[[#This Row],[RIS NO]] & TEXT(Table3[[#This Row],[COUNT (Max10)]], "0;-0") -> 2025-00613 | D78: 45754 | E78: =VLOOKUP(C78,REQUEST1,3,0) -> Rubber band - multicolor, 450 grams | F78: NONE IN STOCK | G78: =IFERROR(VLOOKUP(E78,SUPPLY2,3,0),"-") -> Box | H78: =IFERROR(VLOOKUP(E78,SUPPLY2,4,0),"-") -> 307 | I78: =IFERROR(VLOOKUP(D78,YEAR2023,2,0),"-") -> 4
A79: ='DATA ENTRY - REQUEST'!A79 -> 2025-006 | B79: ='DATA ENTRY - REQUEST'!B79 -> 14 | C79: =Table3[[#This Row],[RIS NO]] & TEXT(Table3[[#This Row],[COUNT (Max10)]], "0;-0") -> 2025-00614 | D79: 45754 | E79: =VLOOKUP(C79,REQUEST1,3,0) -> Tape - masking 1 | F79: NONE IN STOCK | G79: =IFERROR(VLOOKUP(E79,SUPPLY2,3,0),"-") -> Roll | H79: =IFERROR(VLOOKUP(E79,SUPPLY2,4,0),"-") -> 300 | I79: =IFERROR(VLOOKUP(D79,YEAR2023,2,0),"-") -> 4
A80: ='DATA ENTRY - REQUEST'!A80 -> 2025-006 | B80: ='DATA ENTRY - REQUEST'!B80 -> 15 | C80: =Table3[[#This Row],[RIS NO]] & TEXT(Table3[[#This Row],[COUNT (Max10)]], "0;-0") -> 2025-00615 | D80: 45754 | E80: =VLOOKUP(C80,REQUEST1,3,0) -> Pencil | F80: NONE IN STOCK | G80: =IFERROR(VLOOKUP(E80,SUPPLY2,3,0),"-") -> Piece | H80: =IFERROR(VLOOKUP(E80,SUPPLY2,4,0),"-") -> 0 | I80: =IFERROR(VLOOKUP(D80,YEAR2023,2,0),"-") -> 4
A81: ='DATA ENTRY - REQUEST'!A81 -> 2025-006 | B81: ='DATA ENTRY - REQUEST'!B81 -> 16 | C81: =Table3[[#This Row],[RIS NO]] & TEXT(Table3[[#This Row],[COUNT (Max10)]], "0;-0") -> 2025-00616 | D81: 45777 | E81: =VLOOKUP(C81,REQUEST1,3,0) -> Paste - solid w/ waterwell and applicator | F81: 20 | G81: =IFERROR(VLOOKUP(E81,SUPPLY2,3,0),"-") -> Piece | H81: =IFERROR(VLOOKUP(E81,SUPPLY2,4,0),"-") -> 336 | I81: =IFERROR(VLOOKUP(D81,YEAR2023,2,0),"-") -> 4
A82: ='DATA ENTRY - REQUEST'!A82 -> 2025-006 | B82: ='DATA ENTRY - REQUEST'!B82 -> 17 | C82: =Table3[[#This Row],[RIS NO]] & TEXT(Table3[[#This Row],[COUNT (Max10)]], "0;-0") -> 2025-00617 | D82: 45777 | E82: =VLOOKUP(C82,REQUEST1,3,0) -> Ballpoint pen | F82: 20 | G82: =IFERROR(VLOOKUP(E82,SUPPLY2,3,0),"-") -> Piece | H82: =IFERROR(VLOOKUP(E82,SUPPLY2,4,0),"-") -> 337 | I82: =IFERROR(VLOOKUP(D82,YEAR2023,2,0),"-") -> 4
A83: ='DATA ENTRY - REQUEST'!A83 -> 2025-007 | B83: ='DATA ENTRY - REQUEST'!B83 -> 1 | C83: =Table3[[#This Row],[RIS NO]] & TEXT(Table3[[#This Row],[COUNT (Max10)]], "0;-0") -> 2025-0071 | D83: 45777 | E83: =VLOOKUP(C83,REQUEST1,3,0) -> Bond copy paper, A4 size,70gsm 500shts/rm | F83: 2 | G83: =IFERROR(VLOOKUP(E83,SUPPLY2,3,0),"-") -> Ream | H83: =IFERROR(VLOOKUP(E83,SUPPLY2,4,0),"-") -> 2276 | I83: =IFERROR(VLOOKUP(D83,YEAR2023,2,0),"-") -> 4
A84: ='DATA ENTRY - REQUEST'!A84 -> 2025-007 | B84: ='DATA ENTRY - REQUEST'!B84 -> 2 | C84: =Table3[[#This Row],[RIS NO]] & TEXT(Table3[[#This Row],[COUNT (Max10)]], "0;-0") -> 2025-0072 | D84: 45777 | E84: =VLOOKUP(C84,REQUEST1,3,0) -> Bond prem,LEGAL SIZE, 216x330mm,70gsm 500shts/rm | F84: NOT FOR SHIPMENT | G84: =IFERROR(VLOOKUP(E84,SUPPLY2,3,0),"-") -> Ream | H84: =IFERROR(VLOOKUP(E84,SUPPLY2,4,0),"-") -> 2067 | I84: =IFERROR(VLOOKUP(D84,YEAR2023,2,0),"-") -> 4
A85: ='DATA ENTRY - REQUEST'!A85 -> 2025-007 | B85: ='DATA ENTRY - REQUEST'!B85 -> 3 | C85: =Table3[[#This Row],[RIS NO]] & TEXT(Table3[[#This Row],[COUNT (Max10)]], "0;-0") -> 2025-0073 | D85: 45777 | E85: =VLOOKUP(C85,REQUEST1,3,0) -> MEMBER DATA CHANGE REQUEST PAGE 1&2 | F85: NONE IN STOCK | G85: =IFERROR(VLOOKUP(E85,SUPPLY2,3,0),"-") -> Ream | H85: =IFERROR(VLOOKUP(E85,SUPPLY2,4,0),"-") -> 0 | I85: =IFERROR(VLOOKUP(D85,YEAR2023,2,0),"-") -> 4
A86: ='DATA ENTRY - REQUEST'!A86 -> 2025-007 | B86: ='DATA ENTRY - REQUEST'!B86 -> 4 | C86: =Table3[[#This Row],[RIS NO]] & TEXT(Table3[[#This Row],[COUNT (Max10)]], "0;-0") -> 2025-0074 | D86: 45777 | E86: =VLOOKUP(C86,REQUEST1,3,0) -> Alcohol, ethyl, 68%-72% | F86: NONE IN STOCK | G86: =IFERROR(VLOOKUP(E86,SUPPLY2,3,0),"-") -> Gallon | H86: =IFERROR(VLOOKUP(E86,SUPPLY2,4,0),"-") -> 2617 | I86: =IFERROR(VLOOKUP(D86,YEAR2023,2,0),"-") -> 4
A87: ='DATA ENTRY - REQUEST'!A87 -> 2025-007 | B87: ='DATA ENTRY - REQUEST'!B87 -> 5 | C87: =Table3[[#This Row],[RIS NO]] & TEXT(Table3[[#This Row],[COUNT (Max10)]], "0;-0") -> 2025-0075 | D87: 45777 | E87: =VLOOKUP(C87,REQUEST1,3,0) -> Ballpoint pen | F87: NONE IN STOCK | G87: =IFERROR(VLOOKUP(E87,SUPPLY2,3,0),"-") -> Piece | H87: =IFERROR(VLOOKUP(E87,SUPPLY2,4,0),"-") -> 337 | I87: =IFERROR(VLOOKUP(D87,YEAR2023,2,0),"-") -> 4
A88: ='DATA ENTRY - REQUEST'!A88 -> 2025-007 | B88: ='DATA ENTRY - REQUEST'!B88 -> 6 | C88: =Table3[[#This Row],[RIS NO]] & TEXT(Table3[[#This Row],[COUNT (Max10)]], "0;-0") -> 2025-0076 | D88: 45777 | E88: =VLOOKUP(C88,REQUEST1,3,0) -> Folder - legal size, 36mm thick (14pts) | F88: NONE IN STOCK | G88: =IFERROR(VLOOKUP(E88,SUPPLY2,3,0),"-") -> C | H88: =IFERROR(VLOOKUP(E88,SUPPLY2,4,0),"-") -> 330 | I88: =IFERROR(VLOOKUP(D88,YEAR2023,2,0),"-") -> 4
A89: ='DATA ENTRY - REQUEST'!A89 -> 2025-007 | B89: ='DATA ENTRY - REQUEST'!B89 -> 7 | C89: =Table3[[#This Row],[RIS NO]] & TEXT(Table3[[#This Row],[COUNT (Max10)]], "0;-0") -> 2025-0077 | D89: 45777 | E89: =VLOOKUP(C89,REQUEST1,3,0) -> Tape - transparent 1 | F89: NONE IN STOCK | G89: =IFERROR(VLOOKUP(E89,SUPPLY2,3,0),"-") -> Roll | H89: =IFERROR(VLOOKUP(E89,SUPPLY2,4,0),"-") -> 301 | I89: =IFERROR(VLOOKUP(D89,YEAR2023,2,0),"-") -> 4
A90: ='DATA ENTRY - REQUEST'!A90 -> 2025-007 | B90: ='DATA ENTRY - REQUEST'!B90 -> 8 | C90: =Table3[[#This Row],[RIS NO]] & TEXT(Table3[[#This Row],[COUNT (Max10)]], "0;-0") -> 2025-0078 | D90: 45777 | E90: =VLOOKUP(C90,REQUEST1,3,0) -> Packaging tape 2” | F90: NONE IN STOCK | G90: =IFERROR(VLOOKUP(E90,SUPPLY2,3,0),"-") -> Roll | H90: =IFERROR(VLOOKUP(E90,SUPPLY2,4,0),"-") -> 2537 | I90: =IFERROR(VLOOKUP(D90,YEAR2023,2,0),"-") -> 4
A91: ='DATA ENTRY - REQUEST'!A91 -> 2025-007 | B91: ='DATA ENTRY - REQUEST'!B91 -> 9 | C91: =Table3[[#This Row],[RIS NO]] & TEXT(Table3[[#This Row],[COUNT (Max10)]], "0;-0") -> 2025-0079 | D91: 45777 | E91: =VLOOKUP(C91,REQUEST1,3,0) -> Pencil | F91: 2 | G91: =IFERROR(VLOOKUP(E91,SUPPLY2,3,0),"-") -> Piece | H91: =IFERROR(VLOOKUP(E91,SUPPLY2,4,0),"-") -> 0 | I91: =IFERROR(VLOOKUP(D91,YEAR2023,2,0),"-") -> 4
A92: ='DATA ENTRY - REQUEST'!A92 -> 2025-007 | B92: ='DATA ENTRY - REQUEST'!B92 -> 10 | C92: =Table3[[#This Row],[RIS NO]] & TEXT(Table3[[#This Row],[COUNT (Max10)]], "0;-0") -> 2025-00710 | D92: 45777 | E92: =VLOOKUP(C92,REQUEST1,3,0) -> Paste - solid w/ waterwell and applicator | F92: NONE IN STOCK | G92: =IFERROR(VLOOKUP(E92,SUPPLY2,3,0),"-") -> Piece | H92: =IFERROR(VLOOKUP(E92,SUPPLY2,4,0),"-") -> 336 | I92: =IFERROR(VLOOKUP(D92,YEAR2023,2,0),"-") -> 4
A93: ='DATA ENTRY - REQUEST'!A93 -> 2025-007 | B93: ='DATA ENTRY - REQUEST'!B93 -> 11 | C93: =Table3[[#This Row],[RIS NO]] & TEXT(Table3[[#This Row],[COUNT (Max10)]], "0;-0") -> 2025-00711 | D93: 45777 | E93: =VLOOKUP(C93,REQUEST1,3,0) -> ACOP- SURVIVING LEGAL SPOUSE | F93: NONE IN STOCK | G93: =IFERROR(VLOOKUP(E93,SUPPLY2,3,0),"-") -> Ream | H93: =IFERROR(VLOOKUP(E93,SUPPLY2,4,0),"-") -> 0 | I93: =IFERROR(VLOOKUP(D93,YEAR2023,2,0),"-") -> 4
A94: ='DATA ENTRY - REQUEST'!A94 -> 2025-007 | B94: ='DATA ENTRY - REQUEST'!B94 -> 12 | C94: =Table3[[#This Row],[RIS NO]] & TEXT(Table3[[#This Row],[COUNT (Max10)]], "0;-0") -> 2025-00712 | D94: 45777 | E94: =VLOOKUP(C94,REQUEST1,3,0) -> Envelope - document, 10 x 15 | F94: NONE IN STOCK | G94: =IFERROR(VLOOKUP(E94,SUPPLY2,3,0),"-") -> C | H94: =IFERROR(VLOOKUP(E94,SUPPLY2,4,0),"-") -> 46 | I94: =IFERROR(VLOOKUP(D94,YEAR2023,2,0),"-") -> 4
A95: ='DATA ENTRY - REQUEST'!A95 -> 2025-007 | B95: ='DATA ENTRY - REQUEST'!B95 -> 13 | C95: =Table3[[#This Row],[RIS NO]] & TEXT(Table3[[#This Row],[COUNT (Max10)]], "0;-0") -> 2025-00713 | D95: 45777 | E95: =VLOOKUP(C95,REQUEST1,3,0) -> Binder clip 2” | F95: 2 | G95: =IFERROR(VLOOKUP(E95,SUPPLY2,3,0),"-") -> Box | H95: =IFERROR(VLOOKUP(E95,SUPPLY2,4,0),"-") -> 2552 | I95: =IFERROR(VLOOKUP(D95,YEAR2023,2,0),"-") -> 4
A96: ='DATA ENTRY - REQUEST'!A96 -> 2025-007 | B96: ='DATA ENTRY - REQUEST'!B96 -> 14 | C96: =Table3[[#This Row],[RIS NO]] & TEXT(Table3[[#This Row],[COUNT (Max10)]], "0;-0") -> 2025-00714 | D96: 45777 | E96: =VLOOKUP(C96,REQUEST1,3,0) -> Binder clip 1” | F96: 2 | G96: =IFERROR(VLOOKUP(E96,SUPPLY2,3,0),"-") -> Box | H96: =IFERROR(VLOOKUP(E96,SUPPLY2,4,0),"-") -> 2550 | I96: =IFERROR(VLOOKUP(D96,YEAR2023,2,0),"-") -> 4
A97: ='DATA ENTRY - REQUEST'!A97 -> 2025-008 | B97: ='DATA ENTRY - REQUEST'!B97 -> 1 | C97: =Table3[[#This Row],[RIS NO]] & TEXT(Table3[[#This Row],[COUNT (Max10)]], "0;-0") -> 2025-0081 | D97: 45793 | E97: =VLOOKUP(C97,REQUEST1,3,0) -> PROPERTY STICKER/TAG | F97: 20 | G97: =IFERROR(VLOOKUP(E97,SUPPLY2,3,0),"-") -> - | H97: =IFERROR(VLOOKUP(E97,SUPPLY2,4,0),"-") -> - | I97: =IFERROR(VLOOKUP(D97,YEAR2023,2,0),"-") -> 5
A98: ='DATA ENTRY - REQUEST'!A98 -> 2025-009 | B98: ='DATA ENTRY - REQUEST'!B98 -> 1 | C98: =Table3[[#This Row],[RIS NO]] & TEXT(Table3[[#This Row],[COUNT (Max10)]], "0;-0") -> 2025-0091 | D98: 45793 | E98: =VLOOKUP(C98,REQUEST1,3,0) -> Bond copy paper, A4 size,70gsm 500shts/rm | F98: 20 | G98: =IFERROR(VLOOKUP(E98,SUPPLY2,3,0),"-") -> Ream | H98: =IFERROR(VLOOKUP(E98,SUPPLY2,4,0),"-") -> 2276 | I98: =IFERROR(VLOOKUP(D98,YEAR2023,2,0),"-") -> 5
A99: ='DATA ENTRY - REQUEST'!A99 -> 2025-009 | B99: ='DATA ENTRY - REQUEST'!B99 -> 2 | C99: =Table3[[#This Row],[RIS NO]] & TEXT(Table3[[#This Row],[COUNT (Max10)]], "0;-0") -> 2025-0092 | D99: 45793 | E99: =VLOOKUP(C99,REQUEST1,3,0) -> Bond prem,LEGAL SIZE, 216x330mm,70gsm 500shts/rm | F99: 2 | G99: =IFERROR(VLOOKUP(E99,SUPPLY2,3,0),"-") -> Ream | H99: =IFERROR(VLOOKUP(E99,SUPPLY2,4,0),"-") -> 2067 | I99: =IFERROR(VLOOKUP(D99,YEAR2023,2,0),"-") -> 5
A100: ='DATA ENTRY - REQUEST'!A100 -> 2025-009 | B100: ='DATA ENTRY - REQUEST'!B100 -> 3 | C100: =Table3[[#This Row],[RIS NO]] & TEXT(Table3[[#This Row],[COUNT (Max10)]], "0;-0") -> 2025-0093 | D100: 45793 | E100: =VLOOKUP(C100,REQUEST1,3,0) -> MEMBER DATA CHANGE REQUEST PAGE 1&2 | F100: NONE IN STOCK | G100: =IFERROR(VLOOKUP(E100,SUPPLY2,3,0),"-") -> Ream | H100: =IFERROR(VLOOKUP(E100,SUPPLY2,4,0),"-") -> 0 | I100: =IFERROR(VLOOKUP(D100,YEAR2023,2,0),"-") -> 5
A101: ='DATA ENTRY - REQUEST'!A101 -> 2025-009 | B101: ='DATA ENTRY - REQUEST'!B101 -> 4 | C101: =Table3[[#This Row],[RIS NO]] & TEXT(Table3[[#This Row],[COUNT (Max10)]], "0;-0") -> 2025-0094 | D101: 45793 | E101: =VLOOKUP(C101,REQUEST1,3,0) -> Alcohol, ethyl, 68%-72% | F101: NONE IN STOCK | G101: =IFERROR(VLOOKUP(E101,SUPPLY2,3,0),"-") -> Gallon | H101: =IFERROR(VLOOKUP(E101,SUPPLY2,4,0),"-") -> 2617 | I101: =IFERROR(VLOOKUP(D101,YEAR2023,2,0),"-") -> 5
A102: ='DATA ENTRY - REQUEST'!A102 -> 2025-009 | B102: ='DATA ENTRY - REQUEST'!B102 -> 5 | C102: =Table3[[#This Row],[RIS NO]] & TEXT(Table3[[#This Row],[COUNT (Max10)]], "0;-0") -> 2025-0095 | D102: 45793 | E102: =VLOOKUP(C102,REQUEST1,3,0) -> Ballpoint pen | F102: NONE IN STOCK | G102: =IFERROR(VLOOKUP(E102,SUPPLY2,3,0),"-") -> Piece | H102: =IFERROR(VLOOKUP(E102,SUPPLY2,4,0),"-") -> 337 | I102: =IFERROR(VLOOKUP(D102,YEAR2023,2,0),"-") -> 5
A103: ='DATA ENTRY - REQUEST'!A103 -> 2025-009 | B103: ='DATA ENTRY - REQUEST'!B103 -> 6 | C103: =Table3[[#This Row],[RIS NO]] & TEXT(Table3[[#This Row],[COUNT (Max10)]], "0;-0") -> 2025-0096 | D103: 45793 | E103: =VLOOKUP(C103,REQUEST1,3,0) -> Folder - legal size, 36mm thick (14pts) | F103: 5 | G103: =IFERROR(VLOOKUP(E103,SUPPLY2,3,0),"-") -> C | H103: =IFERROR(VLOOKUP(E103,SUPPLY2,4,0),"-") -> 330 | I103: =IFERROR(VLOOKUP(D103,YEAR2023,2,0),"-") -> 5
A104: ='DATA ENTRY - REQUEST'!A104 -> 2025-009 | B104: ='DATA ENTRY - REQUEST'!B104 -> 7 | C104: =Table3[[#This Row],[RIS NO]] & TEXT(Table3[[#This Row],[COUNT (Max10)]], "0;-0") -> 2025-0097 | D104: 45793 | E104: =VLOOKUP(C104,REQUEST1,3,0) -> Tape - transparent 1 | F104: 3 | G104: =IFERROR(VLOOKUP(E104,SUPPLY2,3,0),"-") -> Roll | H104: =IFERROR(VLOOKUP(E104,SUPPLY2,4,0),"-") -> 301 | I104: =IFERROR(VLOOKUP(D104,YEAR2023,2,0),"-") -> 5
A105: ='DATA ENTRY - REQUEST'!A105 -> 2025-009 | B105: ='DATA ENTRY - REQUEST'!B105 -> 8 | C105: =Table3[[#This Row],[RIS NO]] & TEXT(Table3[[#This Row],[COUNT (Max10)]], "0;-0") -> 2025-0098 | D105: 45793 | E105: =VLOOKUP(C105,REQUEST1,3,0) -> Packaging tape 2” | F105: 5 | G105: =IFERROR(VLOOKUP(E105,SUPPLY2,3,0),"-") -> Roll | H105: =IFERROR(VLOOKUP(E105,SUPPLY2,4,0),"-") -> 2537 | I105: =IFERROR(VLOOKUP(D105,YEAR2023,2,0),"-") -> 5
A106: ='DATA ENTRY - REQUEST'!A106 -> 2025-009 | B106: ='DATA ENTRY - REQUEST'!B106 -> 9 | C106: =Table3[[#This Row],[RIS NO]] & TEXT(Table3[[#This Row],[COUNT (Max10)]], "0;-0") -> 2025-0099 | D106: 45793 | E106: =VLOOKUP(C106,REQUEST1,3,0) -> Pencil | F106: NONE IN STOCK | H106: =IFERROR(VLOOKUP(E106,SUPPLY2,4,0),"-") -> 0 | I106: =IFERROR(VLOOKUP(D106,YEAR2023,2,0),"-") -> 5
A107: ='DATA ENTRY - REQUEST'!A107 -> 2025-009 | B107: ='DATA ENTRY - REQUEST'!B107 -> 10 | C107: =Table3[[#This Row],[RIS NO]] & TEXT(Table3[[#This Row],[COUNT (Max10)]], "0;-0") -> 2025-00910 | D107: 45793 | E107: =VLOOKUP(C107,REQUEST1,3,0) -> Paste - solid w/ waterwell and applicator | F107: 2 | G107: =IFERROR(VLOOKUP(E107,SUPPLY2,3,0),"-") -> Piece | H107: =IFERROR(VLOOKUP(E107,SUPPLY2,4,0),"-") -> 336 | I107: =IFERROR(VLOOKUP(D107,YEAR2023,2,0),"-") -> 5
A108: ='DATA ENTRY - REQUEST'!A108 -> 2025-009 | B108: ='DATA ENTRY - REQUEST'!B108 -> 11 | C108: =Table3[[#This Row],[RIS NO]] & TEXT(Table3[[#This Row],[COUNT (Max10)]], "0;-0") -> 2025-00911 | D108: 45793 | E108: =VLOOKUP(C108,REQUEST1,3,0) -> ACOP- SURVIVING LEGAL SPOUSE | F108: NONE IN STOCK | G108: =IFERROR(VLOOKUP(E108,SUPPLY2,3,0),"-") -> Ream | H108: =IFERROR(VLOOKUP(E108,SUPPLY2,4,0),"-") -> 0 | I108: =IFERROR(VLOOKUP(D108,YEAR2023,2,0),"-") -> 5
...

Sheet DATA ENTRY - JANITORIAL
A1: RIS NO | B1: NO (Max10) | C1: REF | D1: REQUEST DATE (MM/DD/YYYY) | E1: DESCRIPTION | F1: QTY | G1: UNIT | H1: STOCK CODE | I1: BALANCE AVAILABLE STOCKS | J1: REQUESTED BY | K1: EMAILED DATE | L1: RECEIPT DATE | M1: NO OF STOCKS (IN) | N1: RELEASING DATE | O1: NO OF STOCKS (OUT) | P1: MONTH
A2: 2022-001 | D2: OLD | E2: SCRUB SPONGE | G2: =IFERROR(VLOOKUP(E2,SUPPLY2,3,0),"-") -> - | H2: =IFERROR(VLOOKUP(E2,SUPPLY2,4,0),"-") -> - | M2: 20 | P2: =IFERROR(VLOOKUP(D2,YEAR21,2,0),"-") -> -
A3: 2022-001 | D3: OLD | E3: BAYGON MULTI INSECT SPRAY | G3: =IFERROR(VLOOKUP(E3,SUPPLY2,3,0),"-") -> - | H3: =IFERROR(VLOOKUP(E3,SUPPLY2,4,0),"-") -> - | M3: 2 | P3: =IFERROR(VLOOKUP(D3,YEAR21,2,0),"-") -> -
A4: 2022-001 | D4: OLD | E4: MULTI PURP CLEANER LIQUID PUREBASICS | G4: =IFERROR(VLOOKUP(E4,SUPPLY2,3,0),"-") -> - | H4: =IFERROR(VLOOKUP(E4,SUPPLY2,4,0),"-") -> - | M4: 4 | P4: =IFERROR(VLOOKUP(D4,YEAR21,2,0),"-") -> -
A5: 2022-001 | D5: OLD | E5: SURF POWDER DETERGENT | G5: =IFERROR(VLOOKUP(E5,SUPPLY2,3,0),"-") -> - | H5: =IFERROR(VLOOKUP(E5,SUPPLY2,4,0),"-") -> - | M5: 12 | P5: =IFERROR(VLOOKUP(D5,YEAR21,2,0),"-") -> -
A6: 2022-001 | D6: OLD | E6: LYSOL TIOLET CLEANER | G6: =IFERROR(VLOOKUP(E6,SUPPLY2,3,0),"-") -> - | H6: =IFERROR(VLOOKUP(E6,SUPPLY2,4,0),"-") -> - | M6: 11 | P6: =IFERROR(VLOOKUP(D6,YEAR21,2,0),"-") -> -
A7: 2022-001 | D7: OLD | E7: HAND LIQUID SOAP (BOT) | G7: =IFERROR(VLOOKUP(E7,SUPPLY2,3,0),"-") -> - | H7: =IFERROR(VLOOKUP(E7,SUPPLY2,4,0),"-") -> - | M7: 4 | P7: =IFERROR(VLOOKUP(D7,YEAR21,2,0),"-") -> -
A8: 2022-001 | D8: OLD | E8: MURIATIC ACID (L) | G8: =IFERROR(VLOOKUP(E8,SUPPLY2,3,0),"-") -> - | H8: =IFERROR(VLOOKUP(E8,SUPPLY2,4,0),"-") -> - | M8: 2 | P8: =IFERROR(VLOOKUP(D8,YEAR21,2,0),"-") -> -
A9: 2022-001 | D9: OLD | E9: MULTI PURP CLEANER LIQUID DOMEX | G9: =IFERROR(VLOOKUP(E9,SUPPLY2,3,0),"-") -> - | H9: =IFERROR(VLOOKUP(E9,SUPPLY2,4,0),"-") -> - | M9: 5 | P9: =IFERROR(VLOOKUP(D9,YEAR21,2,0),"-") -> -
A10: 2022-001 | D10: OLD | E10: ZONROX (GAL) | G10: =IFERROR(VLOOKUP(E10,SUPPLY2,3,0),"-") -> - | H10: =IFERROR(VLOOKUP(E10,SUPPLY2,4,0),"-") -> - | M10: 1 | P10: =IFERROR(VLOOKUP(D10,YEAR21,2,0),"-") -> -
A11: 2022-001 | D11: OLD | E11: MOP HEAD | G11: =IFERROR(VLOOKUP(E11,SUPPLY2,3,0),"-") -> - | H11: =IFERROR(VLOOKUP(E11,SUPPLY2,4,0),"-") -> - | M11: 5 | P11: =IFERROR(VLOOKUP(D11,YEAR21,2,0),"-") -> -
D12: OLD | E12: TRASH BAG XL-XXL | G12: =IFERROR(VLOOKUP(E12,SUPPLY2,3,0),"-") -> - | H12: =IFERROR(VLOOKUP(E12,SUPPLY2,4,0),"-") -> - | M12: 170
D13: OLD | E13: DEODORANT CAKE | G13: =IFERROR(VLOOKUP(E13,SUPPLY2,3,0),"-") -> - | H13: =IFERROR(VLOOKUP(E13,SUPPLY2,4,0),"-") -> - | M13: 30
D14: OLD | E14: MOUSE BAIT | G14: =IFERROR(VLOOKUP(E14,SUPPLY2,3,0),"-") -> - | H14: =IFERROR(VLOOKUP(E14,SUPPLY2,4,0),"-") -> - | M14: 5
D15: 44678 | E15: DEODORANT CAKE | G15: =IFERROR(VLOOKUP(E15,SUPPLY2,3,0),"-") -> - | H15: =IFERROR(VLOOKUP(E15,SUPPLY2,4,0),"-") -> - | M15: 24
D16: 44678 | E16: BAYGON MULTI INSECT SPRAY | G16: =IFERROR(VLOOKUP(E16,SUPPLY2,3,0),"-") -> - | H16: =IFERROR(VLOOKUP(E16,SUPPLY2,4,0),"-") -> - | M16: 6
D17: 44678 | E17: TOILET BOWL CLEANER DOMEX (L) | G17: =IFERROR(VLOOKUP(E17,SUPPLY2,3,0),"-") -> - | H17: =IFERROR(VLOOKUP(E17,SUPPLY2,4,0),"-") -> - | M17: 6
D18: 44678 | E18: AIR FRESHENER (GEL) | G18: =IFERROR(VLOOKUP(E18,SUPPLY2,3,0),"-") -> - | H18: =IFERROR(VLOOKUP(E18,SUPPLY2,4,0),"-") -> - | M18: 12
D19: 44678 | E19: TISSUE (PAPER TOWEL) | G19: =IFERROR(VLOOKUP(E19,SUPPLY2,3,0),"-") -> - | H19: =IFERROR(VLOOKUP(E19,SUPPLY2,4,0),"-") -> - | M19: 6
D20: 44678 | E20: HAND LIQUID SOAP (BOT) | G20: =IFERROR(VLOOKUP(E20,SUPPLY2,3,0),"-") -> - | H20: =IFERROR(VLOOKUP(E20,SUPPLY2,4,0),"-") -> - | M20: 6
D21: 44678 | E21: LYSOL DISINFECTANT SPRAY & AIR FRESHENER/DEODORIZER | G21: =IFERROR(VLOOKUP(E21,SUPPLY2,3,0),"-") -> - | H21: =IFERROR(VLOOKUP(E21,SUPPLY2,4,0),"-") -> - | M21: 6
D22: 44678 | E22: SCRUB SPONGE | G22: =IFERROR(VLOOKUP(E22,SUPPLY2,3,0),"-") -> - | H22: =IFERROR(VLOOKUP(E22,SUPPLY2,4,0),"-") -> - | M22: 6
D23: 44678 | E23: CAR FRESHENER | G23: =IFERROR(VLOOKUP(E23,SUPPLY2,3,0),"-") -> - | H23: =IFERROR(VLOOKUP(E23,SUPPLY2,4,0),"-") -> - | M23: 4
D24: 44678 | E24: DISHWASHING LIQUID (L) | G24: =IFERROR(VLOOKUP(E24,SUPPLY2,3,0),"-") -> - | H24: =IFERROR(VLOOKUP(E24,SUPPLY2,4,0),"-") -> - | M24: 3
D25: 44678 | E25: ZONROX (GAL) | G25: =IFERROR(VLOOKUP(E25,SUPPLY2,3,0),"-") -> - | H25: =IFERROR(VLOOKUP(E25,SUPPLY2,4,0),"-") -> - | M25: 4
D26: 44678 | E26: RUG | G26: =IFERROR(VLOOKUP(E26,SUPPLY2,3,0),"-") -> - | H26: =IFERROR(VLOOKUP(E26,SUPPLY2,4,0),"-") -> - | M26: 9
D27: 44678 | E27: SOFT BROOM | G27: =IFERROR(VLOOKUP(E27,SUPPLY2,3,0),"-") -> - | H27: =IFERROR(VLOOKUP(E27,SUPPLY2,4,0),"-") -> - | M27: 2
D28: OLD | E28: DISINFECTANT & CLEANING SOLUTION (GAL) | G28: =IFERROR(VLOOKUP(E28,SUPPLY2,3,0),"-") -> - | H28: =IFERROR(VLOOKUP(E28,SUPPLY2,4,0),"-") -> - | M28: 10
D29: OLD | E29: HAND SANITIZER (GAL) | G29: =IFERROR(VLOOKUP(E29,SUPPLY2,3,0),"-") -> - | H29: =IFERROR(VLOOKUP(E29,SUPPLY2,4,0),"-") -> - | M29: 4
D30: OLD | E30: ALCOHOL ETHYL (GAL) | G30: =IFERROR(VLOOKUP(E30,SUPPLY2,3,0),"-") -> - | H30: =IFERROR(VLOOKUP(E30,SUPPLY2,4,0),"-") -> - | M30: 6
G31: =IFERROR(VLOOKUP(E31,SUPPLY2,3,0),"-") -> - | H31: =IFERROR(VLOOKUP(E31,SUPPLY2,4,0),"-") -> -
G32: =IFERROR(VLOOKUP(E32,SUPPLY2,3,0),"-") -> - | H32: =IFERROR(VLOOKUP(E32,SUPPLY2,4,0),"-") -> -
G33: =IFERROR(VLOOKUP(E33,SUPPLY2,3,0),"-") -> - | H33: =IFERROR(VLOOKUP(E33,SUPPLY2,4,0),"-") -> -
G34: =IFERROR(VLOOKUP(E34,SUPPLY2,3,0),"-") -> - | H34: =IFERROR(VLOOKUP(E34,SUPPLY2,4,0),"-") -> - | P34: =IFERROR(VLOOKUP(D34,YEAR21,2,0),"-") -> -
G35: =IFERROR(VLOOKUP(E35,SUPPLY2,3,0),"-") -> - | H35: =IFERROR(VLOOKUP(E35,SUPPLY2,4,0),"-") -> - | P35: =IFERROR(VLOOKUP(D35,YEAR21,2,0),"-") -> -
G36: =IFERROR(VLOOKUP(E36,SUPPLY2,3,0),"-") -> - | H36: =IFERROR(VLOOKUP(E36,SUPPLY2,4,0),"-") -> - | P36: =IFERROR(VLOOKUP(D36,YEAR21,2,0),"-") -> -
G37: =IFERROR(VLOOKUP(E37,SUPPLY2,3,0),"-") -> - | H37: =IFERROR(VLOOKUP(E37,SUPPLY2,4,0),"-") -> - | P37: =IFERROR(VLOOKUP(D37,YEAR21,2,0),"-") -> -
D38: 44678 | E38: TISSUE (PAPER TOWEL) | F38: 1 | G38: =IFERROR(VLOOKUP(E38,SUPPLY2,3,0),"-") -> - | H38: =IFERROR(VLOOKUP(E38,SUPPLY2,4,0),"-") -> - | I38: =IFERROR(VLOOKUP(H38,'SUPPLIES SUMMARY'!A$147:G$180,7,0),"-") -> - | J38: RHODA | N38: 44678 | O38: =F38 -> 1 | P38: =IFERROR(VLOOKUP(D38,YEAR21,2,0),"-") -> -
D39: 44679 | E39: CAR FRESHENER | F39: 1 | G39: =IFERROR(VLOOKUP(E39,SUPPLY2,3,0),"-") -> - | H39: =IFERROR(VLOOKUP(E39,SUPPLY2,4,0),"-") -> - | I39: =IFERROR(VLOOKUP(H39,'SUPPLIES SUMMARY'!A$147:G$180,7,0),"-") -> - | J39: MARTIN | N39: 44679 | O39: =F39 -> 1 | P39: =IFERROR(VLOOKUP(D39,YEAR21,2,0),"-") -> -
D40: 44679 | E40: AIR FRESHENER (GEL) | F40: 2 | G40: =IFERROR(VLOOKUP(E40,SUPPLY2,3,0),"-") -> - | H40: =IFERROR(VLOOKUP(E40,SUPPLY2,4,0),"-") -> - | I40: =IFERROR(VLOOKUP(H40,'SUPPLIES SUMMARY'!A$147:G$180,7,0),"-") -> - | J40: RHODA | N40: 44679 | O40: =F40 -> 2 | P40: =IFERROR(VLOOKUP(D40,YEAR21,2,0),"-") -> -
D41: 44679 | E41: HAND SANITIZER (GAL) | F41: 1 | G41: =IFERROR(VLOOKUP(E41,SUPPLY2,3,0),"-") -> - | H41: =IFERROR(VLOOKUP(E41,SUPPLY2,4,0),"-") -> - | I41: =IFERROR(VLOOKUP(H41,'SUPPLIES SUMMARY'!A$147:G$180,7,0),"-") -> - | J41: RHODA | N41: 44679 | O41: =F41 -> 1 | P41: =IFERROR(VLOOKUP(D41,YEAR21,2,0),"-") -> -
D42: 44679 | E42: DEODORANT CAKE | F42: 6 | G42: =IFERROR(VLOOKUP(E42,SUPPLY2,3,0),"-") -> - | H42: =IFERROR(VLOOKUP(E42,SUPPLY2,4,0),"-") -> - | I42: =IFERROR(VLOOKUP(H42,'SUPPLIES SUMMARY'!A$147:G$180,7,0),"-") -> - | J42: RHODA | N42: 44679 | O42: =F42 -> 6 | P42: =IFERROR(VLOOKUP(D42,YEAR21,2,0),"-") -> -
D43: 44679 | E43: LYSOL TIOLET CLEANER | F43: 1 | G43: =IFERROR(VLOOKUP(E43,SUPPLY2,3,0),"-") -> - | H43: =IFERROR(VLOOKUP(E43,SUPPLY2,4,0),"-") -> - | I43: =IFERROR(VLOOKUP(H43,'SUPPLIES SUMMARY'!A$147:G$180,7,0),"-") -> - | J43: RHODA | N43: 44679 | O43: =F43 -> 1 | P43: =IFERROR(VLOOKUP(D43,YEAR21,2,0),"-") -> -
D44: 44679 | E44: MOP HEAD | F44: 1 | G44: =IFERROR(VLOOKUP(E44,SUPPLY2,3,0),"-") -> - | H44: =IFERROR(VLOOKUP(E44,SUPPLY2,4,0),"-") -> - | I44: =IFERROR(VLOOKUP(H44,'SUPPLIES SUMMARY'!A$147:G$180,7,0),"-") -> - | J44: RHODA | N44: 44679 | O44: =F44 -> 1 | P44: =IFERROR(VLOOKUP(D44,YEAR21,2,0),"-") -> -
D45: 44679 | E45: DISHWASHING LIQUID (L) | F45: 1 | G45: =IFERROR(VLOOKUP(E45,SUPPLY2,3,0),"-") -> - | H45: =IFERROR(VLOOKUP(E45,SUPPLY2,4,0),"-") -> - | I45: =IFERROR(VLOOKUP(H45,'SUPPLIES SUMMARY'!A$147:G$180,7,0),"-") -> - | J45: RHODA | N45: 44679 | O45: =F45 -> 1 | P45: =IFERROR(VLOOKUP(D45,YEAR21,2,0),"-") -> -
D46: 44679 | E46: AIR FRESHENER (GEL) | F46: 1 | G46: =IFERROR(VLOOKUP(E46,SUPPLY2,3,0),"-") -> - | H46: =IFERROR(VLOOKUP(E46,SUPPLY2,4,0),"-") -> - | I46: =IFERROR(VLOOKUP(H46,'SUPPLIES SUMMARY'!A$147:G$180,7,0),"-") -> - | J46: ADMIN | N46: 44679 | O46: =F46 -> 1 | P46: =IFERROR(VLOOKUP(D46,YEAR21,2,0),"-") -> -
D47: 44679 | E47: AIR FRESHENER (GEL) | F47: 1 | G47: =IFERROR(VLOOKUP(E47,SUPPLY2,3,0),"-") -> - | H47: =IFERROR(VLOOKUP(E47,SUPPLY2,4,0),"-") -> - | I47: =IFERROR(VLOOKUP(H47,'SUPPLIES SUMMARY'!A$147:G$180,7,0),"-") -> - | J47: MSS | N47: 44679 | O47: =F47 -> 1 | P47: =IFERROR(VLOOKUP(D47,YEAR21,2,0),"-") -> -
D48: 44680 | E48: BAYGON MULTI INSECT SPRAY | F48: 1 | G48: =IFERROR(VLOOKUP(E48,SUPPLY2,3,0),"-") -> - | H48: =IFERROR(VLOOKUP(E48,SUPPLY2,4,0),"-") -> - | I48: =IFERROR(VLOOKUP(H48,'SUPPLIES SUMMARY'!A$147:G$180,7,0),"-") -> - | J48: REY | N48: 44680 | O48: =F48 -> 1 | P48: =IFERROR(VLOOKUP(D48,YEAR21,2,0),"-") -> -
D49: 44680 | E49: MULTI PURP CLEANER LIQUID PUREBASICS | F49: 1 | G49: =IFERROR(VLOOKUP(E49,SUPPLY2,3,0),"-") -> - | H49: =IFERROR(VLOOKUP(E49,SUPPLY2,4,0),"-") -> - | I49: =IFERROR(VLOOKUP(H49,'SUPPLIES SUMMARY'!A$147:G$180,7,0),"-") -> - | J49: REY | N49: 44680 | O49: =F49 -> 1 | P49: =IFERROR(VLOOKUP(D49,YEAR21,2,0),"-") -> -
... D60: 44687 | E60: BAYGON MULTI INSECT SPRAY | F60: 1 | G60: =IFERROR(VLOOKUP(E60,SUPPLY2,3,0),"-") -> - | H60: =IFERROR(VLOOKUP(E60,SUPPLY2,4,0),"-") -> - | I60: =IFERROR(VLOOKUP(H60,'SUPPLIES SUMMARY'!A$147:G$180,7,0),"-") -> - | J60: KAPATAGAN SO | N60: 44687 | O60: =F60 -> 1 | P60: =IFERROR(VLOOKUP(D60,YEAR21,2,0),"-") -> -
D61: 44691 | E61: DEODORANT CAKE | F61: 2 | G61: =IFERROR(VLOOKUP(E61,SUPPLY2,3,0),"-") -> - | H61: =IFERROR(VLOOKUP(E61,SUPPLY2,4,0),"-") -> - | I61: =IFERROR(VLOOKUP(H61,'SUPPLIES SUMMARY'!A$147:G$180,7,0),"-") -> - | J61: RHODA | N61: 44691 | O61: =F62 -> 4 | P61: =IFERROR(VLOOKUP(D62,YEAR21,2,0),"-") -> - | R61: N
D62: 44694 | E62: DEODORANT CAKE | F62: 4 | G62: =IFERROR(VLOOKUP(E62,SUPPLY2,3,0),"-") -> - | H62: =IFERROR(VLOOKUP(E62,SUPPLY2,4,0),"-") -> - | I62: =IFERROR(VLOOKUP(H62,'SUPPLIES SUMMARY'!A$147:G$180,7,0),"-") -> - | J62: REY | N62: 44694 | O62: =F63 -> 1 | P62: =IFERROR(VLOOKUP(D63,YEAR21,2,0),"-") -> -
D63: 44694 | E63: MULTI PURP CLEANER LIQUID DOMEX | F63: 1 | G63: =IFERROR(VLOOKUP(E63,SUPPLY2,3,0),"-") -> - | H63: =IFERROR(VLOOKUP(E63,SUPPLY2,4,0),"-") -> - | I63: =IFERROR(VLOOKUP(H63,'SUPPLIES SUMMARY'!A$147:G$180,7,0),"-") -> - | J63: REY | N63: 44694 | O63: =F64 -> 1
D64: 44694 | E64: HAND LIQUID SOAP (BOT) | F64: 1 | G64: =IFERROR(VLOOKUP(E64,SUPPLY2,3,0),"-") -> - | H64: =IFERROR(VLOOKUP(E64,SUPPLY2,4,0),"-") -> - | I64: =IFERROR(VLOOKUP(H64,'SUPPLIES SUMMARY'!A$147:G$180,7,0),"-") -> - | J64: REY | N64: 44694 | O64: =F65 -> 1 | P64: =IFERROR(VLOOKUP(#REF!,YEAR21,2,0),"-") -> -
D65: 44699 | E65: DISINFECTANT & CLEANING SOLUTION (GAL) | F65: 1 | G65: =IFERROR(VLOOKUP(E65,SUPPLY2,3,0),"-") -> - | H65: =IFERROR(VLOOKUP(E65,SUPPLY2,4,0),"-") -> - | I65: =IFERROR(VLOOKUP(H65,'SUPPLIES SUMMARY'!A$147:G$180,7,0),"-") -> - | J65: RHODA | N65: 44699 | O65: =F66 -> 1
D66: 44706 | E66: ALCOHOL ETHYL (GAL) | F66: 1 | G66: =IFERROR(VLOOKUP(E66,SUPPLY2,3,0),"-") -> - | H66: =IFERROR(VLOOKUP(E66,SUPPLY2,4,0),"-") -> - | I66: =IFERROR(VLOOKUP(H66,'SUPPLIES SUMMARY'!A$147:G$180,7,0),"-") -> - | J66: REY | N66: 44706 | O66: =F67 -> 1 | P66: =IFERROR(VLOOKUP(D66,YEAR21,2,0),"-") -> -
D67: 44709 | E67: LYSOL TIOLET CLEANER | F67: 1 | G67: =IFERROR(VLOOKUP(E67,SUPPLY2,3,0),"-") -> - | H67: =IFERROR(VLOOKUP(E67,SUPPLY2,4,0),"-") -> - | I67: =IFERROR(VLOOKUP(H67,'SUPPLIES SUMMARY'!A$147:G$180,7,0),"-") -> - | J67: RHODA | N67: 44709 | O67: =F68 -> 1 | P67: =IFERROR(VLOOKUP(D67,YEAR21,2,0),"-") -> -
D68: 44709 | E68: HAND SANITIZER (GAL) | F68: 1 | G68: =IFERROR(VLOOKUP(E68,SUPPLY2,3,0),"-") -> - | H68: =IFERROR(VLOOKUP(E68,SUPPLY2,4,0),"-") -> - | I68: =IFERROR(VLOOKUP(H68,'SUPPLIES SUMMARY'!A$147:G$180,7,0),"-") -> - | J68: RHODA | N68: 44711 | O68: =F69 -> 1 | P68: =IFERROR(VLOOKUP(D68,YEAR21,2,0),"-") -> -
D69: 44711 | E69: SCRUB SPONGE | F69: 1 | G69: =IFERROR(VLOOKUP(E69,SUPPLY2,3,0),"-") -> - | H69: =IFERROR(VLOOKUP(E69,SUPPLY2,4,0),"-") -> - | I69: =IFERROR(VLOOKUP(H69,'SUPPLIES SUMMARY'!A$147:G$180,7,0),"-") -> - | J69: RHODA | N69: 44711 | O69: =F70 -> 1 | P69: =IFERROR(VLOOKUP(D69,YEAR21,2,0),"-") -> -
D70: 44715 | E70: ALCOHOL ETHYL (GAL) | F70: 1 | G70: =IFERROR(VLOOKUP(E70,SUPPLY2,3,0),"-") -> - | H70: =IFERROR(VLOOKUP(E70,SUPPLY2,4,0),"-") -> - | I70: =IFERROR(VLOOKUP(H70,'SUPPLIES SUMMARY'!A$147:G$180,7,0),"-") -> - | J70: REY | N70: 44715 | O70: =F70 -> 1 | P70: =IFERROR(VLOOKUP(D70,YEAR21,2,0),"-") -> -
D71: 44730 | E71: DEODORANT CAKE | F71: 2 | G71: =IFERROR(VLOOKUP(E71,SUPPLY2,3,0),"-") -> - | H71: =IFERROR(VLOOKUP(E71,SUPPLY2,4,0),"-") -> - | I71: =IFERROR(VLOOKUP(H71,'SUPPLIES SUMMARY'!A$147:G$180,7,0),"-") -> - | J71: REY | N71: 44730 | O71: =F71 -> 2 | P71: =IFERROR(VLOOKUP(D71,YEAR21,2,0),"-") -> -
D72: 44730 | E72: BAYGON MULTI INSECT SPRAY | F72: 1 | G72: =IFERROR(VLOOKUP(E72,SUPPLY2,3,0),"-") -> - | H72: =IFERROR(VLOOKUP(E72,SUPPLY2,4,0),"-") -> - | I72: =IFERROR(VLOOKUP(H72,'SUPPLIES SUMMARY'!A$147:G$180,7,0),"-") -> - | J72: REY | N72: 44730 | O72: =E72 -> BAYGON MULTI INSECT SPRAY | P72: =IFERROR(VLOOKUP(D72,YEAR21,2,0),"-") -> -
D73: 44730 | E73: LYSOL DISINFECTANT SPRAY & AIR FRESHENER/DEODORIZER | F73: 1 | G73: =IFERROR(VLOOKUP(E73,SUPPLY2,3,0),"-") -> - | H73: =IFERROR(VLOOKUP(E73,SUPPLY2,4,0),"-") -> - | I73: =IFERROR(VLOOKUP(H73,'SUPPLIES SUMMARY'!A$147:G$180,7,0),"-") -> - | J73: REY | N73: 44730 | O73: =F73 -> 1 | P73: =IFERROR(VLOOKUP(D73,YEAR21,2,0),"-") -> -
D74: 44730 | E74: ALCOHOL ETHYL (GAL) | F74: 1 | G74: =IFERROR(VLOOKUP(E74,SUPPLY2,3,0),"-") -> - | H74: =IFERROR(VLOOKUP(E74,SUPPLY2,4,0),"-") -> - | I74: =IFERROR(VLOOKUP(H74,'SUPPLIES SUMMARY'!A$147:G$180,7,0),"-") -> - | J74: REY | N74: 44730 | O74: =F74 -> 1 | P74: =IFERROR(VLOOKUP(D74,YEAR21,2,0),"-") -> -
D75: 44730 | E75: AIR FRESHENER (GEL) | F75: 1 | G75: =IFERROR(VLOOKUP(E75,SUPPLY2,3,0),"-") -> - | H75: =IFERROR(VLOOKUP(E75,SUPPLY2,4,0),"-") -> - | I75: =IFERROR(VLOOKUP(H75,'SUPPLIES SUMMARY'!A$147:G$180,7,0),"-") -> - | J75: REY | N75: 44730 | O75: =F75 -> 1 | P75: =IFERROR(VLOOKUP(D75,YEAR21,2,0),"-") -> -
D76: 44734 | E76: HAND LIQUID SOAP (BOT) | F76: 1 | G76: =IFERROR(VLOOKUP(E76,SUPPLY2,3,0),"-") -> - | H76: =IFERROR(VLOOKUP(E76,SUPPLY2,4,0),"-") -> - | I76: =IFERROR(VLOOKUP(H76,'SUPPLIES SUMMARY'!A$147:G$180,7,0),"-") -> - | J76: REY | N76: 44734 | O76: =F76 -> 1 | P76: =IFERROR(VLOOKUP(D76,YEAR21,2,0),"-") -> -
D77: 44744 | E77: AIR FRESHENER (GEL) | F77: 1 | G77: =IFERROR(VLOOKUP(E77,SUPPLY2,3,0),"-") -> - | H77: =IFERROR(VLOOKUP(E77,SUPPLY2,4,0),"-") -> - | I77: =IFERROR(VLOOKUP(H77,'SUPPLIES SUMMARY'!A$147:G$180,7,0),"-") -> - | J77: REY | N77: 44744 | O77: =F77 -> 1 | P77: =IFERROR(VLOOKUP(D77,YEAR21,2,0),"-") -> -
D78: 44744 | E78: LYSOL DISINFECTANT SPRAY & AIR FRESHENER/DEODORIZER | F78: 1 | G78: =IFERROR(VLOOKUP(E78,SUPPLY2,3,0),"-") -> - | H78: =IFERROR(VLOOKUP(E78,SUPPLY2,4,0),"-") -> - | I78: =IFERROR(VLOOKUP(H78,'SUPPLIES SUMMARY'!A$147:G$180,7,0),"-") -> - | J78: REY | N78: 44744 | O78: =F78 -> 1 | P78: =IFERROR(VLOOKUP(D78,YEAR21,2,0),"-") -> -
D79: 44744 | E79: DEODORANT CAKE | F79: 4 | G79: =IFERROR(VLOOKUP(E79,SUPPLY2,3,0),"-") -> - | H79: =IFERROR(VLOOKUP(E79,SUPPLY2,4,0),"-") -> - | I79: =IFERROR(VLOOKUP(H79,'SUPPLIES SUMMARY'!A$147:G$180,7,0),"-") -> - | J79: REY | N79: 44744 | O79: =F79 -> 4 | P79: =IFERROR(VLOOKUP(D79,YEAR21,2,0),"-") -> -
D80: 44744 | E80: MOP | F80: 1 | G80: =IFERROR(VLOOKUP(E80,SUPPLY2,3,0),"-") -> - | H80: =IFERROR(VLOOKUP(E80,SUPPLY2,4,0),"-") -> - | I80: =IFERROR(VLOOKUP(H80,'SUPPLIES SUMMARY'!A$147:G$180,7,0),"-") -> - | J80: REY | N80: 44744 | O80: =F80 -> 1 | P80: =IFERROR(VLOOKUP(D80,YEAR21,2,0),"-") -> -
D81: 44746 | E81: ALCOHOL ETHYL (GAL) | F81: 1 | G81: =IFERROR(VLOOKUP(E81,SUPPLY2,3,0),"-") -> - | H81: =IFERROR(VLOOKUP(E81,SUPPLY2,4,0),"-") -> - | I81: =IFERROR(VLOOKUP(H81,'SUPPLIES SUMMARY'!A$147:G$180,7,0),"-") -> - | J81: REY | N81: 44746 | O81: =F81 -> 1 | P81: =IFERROR(VLOOKUP(D81,YEAR21,2,0),"-") -> -
D82: 44746 | E82: ALCOHOL ETHYL (GAL) | F82: 2 | G82: =IFERROR(VLOOKUP(E82,SUPPLY2,3,0),"-") -> - | H82: =IFERROR(VLOOKUP(E82,SUPPLY2,4,0),"-") -> - | I82: =IFERROR(VLOOKUP(H82,'SUPPLIES SUMMARY'!A$147:G$180,7,0),"-") -> - | J82: RHODA | N82: 44746 | O82: =F82 -> 2 | P82: =IFERROR(VLOOKUP(D82,YEAR21,2,0),"-") -> -
D83: 44749 | E83: LYSOL DISINFECTANT SPRAY & AIR FRESHENER/DEODORIZER | F83: 1 | G83: =IFERROR(VLOOKUP(E83,SUPPLY2,3,0),"-") -> - | H83: =IFERROR(VLOOKUP(E83,SUPPLY2,4,0),"-") -> - | I83: =IFERROR(VLOOKUP(H83,'SUPPLIES SUMMARY'!A$147:G$180,7,0),"-") -> - | J83: REY | N83: 44749 | O83: =F83 -> 1 | P83: =IFERROR(VLOOKUP(D83,YEAR21,2,0),"-") -> -
D84: 44752 | E84: AIR FRESHENER (GEL) | F84: 2 | G84: =IFERROR(VLOOKUP(E84,SUPPLY2,3,0),"-") -> - | H84: =IFERROR(VLOOKUP(E84,SUPPLY2,4,0),"-") -> - | I84: =IFERROR(VLOOKUP(H84,'SUPPLIES SUMMARY'!A$147:G$180,7,0),"-") -> - | J84: RHODA | N84: 44752 | O84: =F84 -> 2 | P84: =IFERROR(VLOOKUP(D84,YEAR21,2,0),"-") -> -
... D96: 44784 | E96: BAYGON MULTI INSECT SPRAY | F96: 1 | G96: =IFERROR(VLOOKUP(E96,SUPPLY2,3,0),"-") -> - | H96: =IFERROR(VLOOKUP(E96,SUPPLY2,4,0),"-") -> - | I96: =IFERROR(VLOOKUP(H96,'SUPPLIES SUMMARY'!A$147:G$180,7,0),"-") -> - | J96: KAPATAGAN SO | N96: 44796 | O96: =F96 -> 1 | P96: =IFERROR(VLOOKUP(D96,YEAR21,2,0),"-") -> -
D97: 44784 | E97: AIR FRESHENER (GEL) | F97: 1 | G97: =IFERROR(VLOOKUP(E97,SUPPLY2,3,0),"-") -> - | H97: =IFERROR(VLOOKUP(E97,SUPPLY2,4,0),"-") -> - | I97: =IFERROR(VLOOKUP(H97,'SUPPLIES SUMMARY'!A$147:G$180,7,0),"-") -> - | J97: KAPATAGAN SO | N97: NS | O97: =F97 -> 1 | P97: =IFERROR(VLOOKUP(D97,YEAR21,2,0),"-") -> -
D98: 44784 | E98: HAND LIQUID SOAP (BOT) | F98: 2 | G98: =IFERROR(VLOOKUP(E98,SUPPLY2,3,0),"-") -> - | H98: =IFERROR(VLOOKUP(E98,SUPPLY2,4,0),"-") -> - | I98: =IFERROR(VLOOKUP(H98,'SUPPLIES SUMMARY'!A$147:G$180,7,0),"-") -> - | J98: KAPATAGAN SO | N98: 44796 | O98: =F98 -> 2 | P98: =IFERROR(VLOOKUP(D98,YEAR21,2,0),"-") -> -
D99: 44784 | E99: LYSOL DISINFECTANT SPRAY & AIR FRESHENER/DEODORIZER | F99: 1 | G99: =IFERROR(VLOOKUP(E99,SUPPLY2,3,0),"-") -> - | H99: =IFERROR(VLOOKUP(E99,SUPPLY2,4,0),"-") -> - | I99: =IFERROR(VLOOKUP(H99,'SUPPLIES SUMMARY'!A$147:G$180,7,0),"-") -> - | J99: KAPATAGAN SO | N99: NS | O99: =F99 -> 1 | P99: =IFERROR(VLOOKUP(D99,YEAR21,2,0),"-") -> -
D100: 44784 | E100: LYSOL TIOLET CLEANER | F100: 1 | G100: =IFERROR(VLOOKUP(E100,SUPPLY2,3,0),"-") -> - | H100: =IFERROR(VLOOKUP(E100,SUPPLY2,4,0),"-") -> - | I100: =IFERROR(VLOOKUP(H100,'SUPPLIES SUMMARY'!A$147:G$180,7,0),"-") -> - | J100: KAPATAGAN SO | N100: NS | O100: =F100 -> 1 | P100: =IFERROR(VLOOKUP(D100,YEAR21,2,0),"-") -> -
D101: 44784 | E101: RUG | F101: 3 | G101: =IFERROR(VLOOKUP(E101,SUPPLY2,3,0),"-") -> - | H101: =IFERROR(VLOOKUP(E101,SUPPLY2,4,0),"-") -> - | I101: =IFERROR(VLOOKUP(H101,'SUPPLIES SUMMARY'!A$147:G$180,7,0),"-") -> - | J101: KAPATAGAN SO | N101: NS | O101: =F101 -> 3 | P101: =IFERROR(VLOOKUP(D101,YEAR21,2,0),"-") -> -
D102: 44784 | E102: SOFT BROOM | F102: 1 | G102: =IFERROR(VLOOKUP(E102,SUPPLY2,3,0),"-") -> - | H102: =IFERROR(VLOOKUP(E102,SUPPLY2,4,0),"-") -> - | I102: =IFERROR(VLOOKUP(H102,'SUPPLIES SUMMARY'!A$147:G$180,7,0),"-") -> - | J102: KAPATAGAN SO | N102: NS | O102: =F102 -> 1 | P102: =IFERROR(VLOOKUP(D102,YEAR21,2,0),"-") -> -
D103: 44784 | E103: TOILET BOWL CLEANER DOMEX (L) | F103: 2 | G103: =IFERROR(VLOOKUP(E103,SUPPLY2,3,0),"-") -> - | H103: =IFERROR(VLOOKUP(E103,SUPPLY2,4,0),"-") -> - | I103: =IFERROR(VLOOKUP(H103,'SUPPLIES SUMMARY'!A$147:G$180,7,0),"-") -> - | J103: KAPATAGAN SO | N103: 44796 | O103: =F103 -> 2 | P103: =IFERROR(VLOOKUP(D103,YEAR21,2,0),"-") -> -
D104: 44784 | E104: DISINFECTANT & CLEANING SOLUTION (GAL) | F104: 1 | G104: =IFERROR(VLOOKUP(E104,SUPPLY2,3,0),"-") -> - | H104: =IFERROR(VLOOKUP(E104,SUPPLY2,4,0),"-") -> - | I104: =IFERROR(VLOOKUP(H104,'SUPPLIES SUMMARY'!A$147:G$180,7,0),"-") -> - | J104: KAPATAGAN SO | N104: 44796 | O104: =F104 -> 1 | P104: =IFERROR(VLOOKUP(D104,YEAR21,2,0),"-") -> -
D105: 44796 | E105: ALCOHOL ETHYL (GAL) | F105: 1 | G105: =IFERROR(VLOOKUP(E105,SUPPLY2,3,0),"-") -> - | H105: =IFERROR(VLOOKUP(E105,SUPPLY2,4,0),"-") -> - | I105: =IFERROR(VLOOKUP(H105,'SUPPLIES SUMMARY'!A$147:G$180,7,0),"-") -> - | J105: REY | N105: 44796 | O105: =F105 -> 1 | P105: =IFERROR(VLOOKUP(D105,YEAR21,2,0),"-") -> -
D106: 44804 | E106: HAND LIQUID SOAP (BOT) | F106: 1 | G106: =IFERROR(VLOOKUP(E106,SUPPLY2,3,0),"-") -> - | H106: =IFERROR(VLOOKUP(E106,SUPPLY2,4,0),"-") -> - | I106: =IFERROR(VLOOKUP(H106,'SUPPLIES SUMMARY'!A$147:G$180,7,0),"-") -> - | J106: RHODA | N106: 44804 | O106: =F106 -> 1 | P106: =IFERROR(VLOOKUP(D106,YEAR21,2,0),"-") -> -
D107: 44809 | E107: TRASH BAG XL-XXL | F107: 2 | G107: =IFERROR(VLOOKUP(E107,SUPPLY2,3,0),"-") -> - | H107: =IFERROR(VLOOKUP(E107,SUPPLY2,4,0),"-") -> - | I107: =IFERROR(VLOOKUP(H107,'SUPPLIES SUMMARY'!A$147:G$180,7,0),"-") -> - | J107: REY | N107: 44809 | O107: =F107 -> 2 | P107: =IFERROR(VLOOKUP(D107,YEAR21,2,0),"-") -> -
D108: 44809 | E108: ALCOHOL ETHYL (GAL) | F108: 1 | G108: =IFERROR(VLOOKUP(E108,SUPPLY2,3,0),"-") -> - | H108: =IFERROR(VLOOKUP(E108,SUPPLY2,4,0),"-") -> - | I108: =IFERROR(VLOOKUP(H108,'SUPPLIES SUMMARY'!A$147:G$180,7,0),"-") -> - | J108: REY | N108: 44809 | O108: =F108 -> 1 | P108: =IFERROR(VLOOKUP(D108,YEAR21,2,0),"-") -> -
D109: 44827 | E109: ZONROX (GAL) | F109: 1 | G109: =IFERROR(VLOOKUP(E109,SUPPLY2,3,0),"-") -> - | H109: =IFERROR(VLOOKUP(E109,SUPPLY2,4,0),"-") -> - | I109: =IFERROR(VLOOKUP(H109,'SUPPLIES SUMMARY'!A$147:G$180,7,0),"-") -> - | J109: REY | N109: 44827 | O109: =F109 -> 1 | P109: =IFERROR(VLOOKUP(D109,YEAR21,2,0),"-") -> -
D110: 44820 | E110: DEODORANT CAKE | F110: 2 | G110: =IFERROR(VLOOKUP(E110,SUPPLY2,3,0),"-") -> - | H110: =IFERROR(VLOOKUP(E110,SUPPLY2,4,0),"-") -> - | I110: =IFERROR(VLOOKUP(H110,'SUPPLIES SUMMARY'!A$147:G$180,7,0),"-") -> - | J110: REY | N110: 44820 | O110: =F110 -> 2 | P110: =IFERROR(VLOOKUP(D110,YEAR21,2,0),"-") -> -
D111: 44820 | E111: SCRUB SPONGE | F111: 1 | G111: =IFERROR(VLOOKUP(E111,SUPPLY2,3,0),"-") -> - | H111: =IFERROR(VLOOKUP(E111,SUPPLY2,4,0),"-") -> - | I111: =IFERROR(VLOOKUP(H111,'SUPPLIES SUMMARY'!A$147:G$180,7,0),"-") -> - | J111: REY | N111: 44820 | O111: =F111 -> 1 | P111: =IFERROR(VLOOKUP(D111,YEAR21,2,0),"-") -> -
D112: 44820 | E112: MULTI PURP CLEANER LIQUID DOMEX | F112: 1 | G112: =IFERROR(VLOOKUP(E112,SUPPLY2,3,0),"-") -> - | H112: =IFERROR(VLOOKUP(E112,SUPPLY2,4,0),"-") -> - | I112: =IFERROR(VLOOKUP(H112,'SUPPLIES SUMMARY'!A$147:G$180,7,0),"-") -> - | J112: REY | N112: 44820 | O112: =F112 -> 1 | P112: =IFERROR(VLOOKUP(D112,YEAR21,2,0),"-") -> -
D113: 44851 | E113: ALCOHOL ETHYL (GAL) | F113: 1 | G113: =IFERROR(VLOOKUP(E113,SUPPLY2,3,0),"-") -> - | H113: =IFERROR(VLOOKUP(E113,SUPPLY2,4,0),"-") -> - | I113: =IFERROR(VLOOKUP(H113,'SUPPLIES SUMMARY'!A$147:G$180,7,0),"-") -> - | J113: RHODA | N113: 44821 | O113: =F113 -> 1 | P113: =IFERROR(VLOOKUP(D113,YEAR21,2,0),"-") -> -
D114: 44852 | E114: DEODORANT CAKE | F114: 3 | G114: =IFERROR(VLOOKUP(E114,SUPPLY2,3,0),"-") -> - | H114: =IFERROR(VLOOKUP(E114,SUPPLY2,4,0),"-") -> - | I114: =IFERROR(VLOOKUP(H114,'SUPPLIES SUMMARY'!A$147:G$180,7,0),"-") -> - | J114: REY | N114: 44852 | O114: =F114 -> 3 | P114: =IFERROR(VLOOKUP(D114,YEAR21,2,0),"-") -> - | Q114: DDD
D115: 44853 | E115: DISINFECTANT & CLEANING SOLUTION (GAL) | F115: 1 | G115: =IFERROR(VLOOKUP(E115,SUPPLY2,3,0),"-") -> - | H115: =IFERROR(VLOOKUP(E115,SUPPLY2,4,0),"-") -> - | I115: =IFERROR(VLOOKUP(H115,'SUPPLIES SUMMARY'!A$147:G$180,7,0),"-") -> - | J115: REY | N115: 44853 | O115: =F115 -> 1 | P115: =IFERROR(VLOOKUP(D115,YEAR21,2,0),"-") -> -
D116: 44855 | E116: ALCOHOL ETHYL (GAL) | F116: 1 | G116: =IFERROR(VLOOKUP(E116,SUPPLY2,3,0),"-") -> - | H116: =IFERROR(VLOOKUP(E116,SUPPLY2,4,0),"-") -> - | I116: =IFERROR(VLOOKUP(H116,'SUPPLIES SUMMARY'!A$147:G$180,7,0),"-") -> - | J116: REY | N116: 44855 | O116: =F116 -> 1 | P116: =IFERROR(VLOOKUP(D116,YEAR21,2,0),"-") -> -
D117: 44855 | E117: TOILET BOWL CLEANER DOMEX (L) | F117: 1 | G117: =IFERROR(VLOOKUP(E117,SUPPLY2,3,0),"-") -> - | H117: =IFERROR(VLOOKUP(E117,SUPPLY2,4,0),"-") -> - | I117: =IFERROR(VLOOKUP(H117,'SUPPLIES SUMMARY'!A$147:G$180,7,0),"-") -> - | J117: REY | N117: 44855 | O117: =F117 -> 1 | P117: =IFERROR(VLOOKUP(D117,YEAR21,2,0),"-") -> -
D118: 44855 | E118: TRASH BAG XL-XXL | F118: 2 | G118: =IFERROR(VLOOKUP(E118,SUPPLY2,3,0),"-") -> - | H118: =IFERROR(VLOOKUP(E118,SUPPLY2,4,0),"-") -> - | I118: =IFERROR(VLOOKUP(H118,'SUPPLIES SUMMARY'!A$147:G$180,7,0),"-") -> - | J118: REY | N118: 44855 | O118: =F118 -> 2 | P118: =IFERROR(VLOOKUP(D118,YEAR21,2,0),"-") -> -
G119: =IFERROR(VLOOKUP(E119,SUPPLY2,3,0),"-") -> - | H119: =IFERROR(VLOOKUP(E119,SUPPLY2,4,0),"-") -> - | I119: =IFERROR(VLOOKUP(H119,'SUPPLIES SUMMARY'!A$147:G$180,7,0),"-") -> - | O119: =F119 -> 0 | P119: =IFERROR(VLOOKUP(D119,YEAR21,2,0),"-") -> -
G120: =IFERROR(VLOOKUP(E120,SUPPLY2,3,0),"-") -> - | H120: =IFERROR(VLOOKUP(E120,SUPPLY2,4,0),"-") -> - | I120: =IFERROR(VLOOKUP(H120,'SUPPLIES SUMMARY'!A$147:G$180,7,0),"-") -> - | O120: =F120 -> 0 | P120: =IFERROR(VLOOKUP(D120,YEAR21,2,0),"-") -> -
G121: =IFERROR(VLOOKUP(E121,SUPPLY2,3,0),"-") -> - | H121: =IFERROR(VLOOKUP(E121,SUPPLY2,4,0),"-") -> - | I121: =IFERROR(VLOOKUP(H121,'SUPPLIES SUMMARY'!A$147:G$180,7,0),"-") -> - | O121: =F121 -> 0 | P121: =IFERROR(VLOOKUP(D121,YEAR21,2,0),"-") -> -
...

Sheet Sheet1
C1: AIR FRESHENER (GEL)
C2: BAYGON MULTI INSECT SPRAY
C3: BROOM BRUSH
C4: BROOM NYLON
C5: BRUSH
C6: CAR FRESHENER
C7: DECLOGGER
C8: DEODORANT CAKE
C9: DISHWASHING LIQUID (L)
C10: DISINFECTANT MAT
C11: DUST PAN
C12: HAND LIQUID SOAP (BOT)
... C46: TELLERING

Sheet DATA ENTRY - RELEASED
A1: DATE RELEASED (MM/DD/YYYY) | B1: DESCRIPTION | C1: STOCKS RELEASED (QTY) | D1: UNIT | E1: STOCK CODE | F1: REQUESTED BY medical | G1: MONTH | H1: Column1
A2: 45660 | B2: Bond copy paper, A4 size,70gsm 500shts/rm | C2: 3 | D2: =IFERROR(VLOOKUP(B2,SUPPLY2,3,0),"-") -> Ream | E2: =IFERROR(VLOOKUP(B2,SUPPLY2,4,0),"-") -> 2276 | F2: ADMIN | G2: =IFERROR(VLOOKUP(A2,YEAR2023,2,0),"-") -> 1
A3: 45660 | B3: Bond prem,LEGAL SIZE, 216x330mm,70gsm 500shts/rm | C3: 3 | D3: =IFERROR(VLOOKUP(B3,SUPPLY2,3,0),"-") -> Ream | E3: =IFERROR(VLOOKUP(B3,SUPPLY2,4,0),"-") -> 2067 | F3: ADMIN | G3: =IFERROR(VLOOKUP(A3,YEAR2023,2,0),"-") -> 1
A4: 45692 | B4: Bond copy paper, A4 size,70gsm 500shts/rm | C4: 1 | D4: =IFERROR(VLOOKUP(B4,SUPPLY2,3,0),"-") -> Ream | E4: =IFERROR(VLOOKUP(B4,SUPPLY2,4,0),"-") -> 2276 | F4: TELLERING | G4: =IFERROR(VLOOKUP(A4,YEAR2023,2,0),"-") -> 2
A5: 45692 | B5: Bond prem,LEGAL SIZE, 216x330mm,70gsm 500shts/rm | C5: 1 | D5: =IFERROR(VLOOKUP(B5,SUPPLY2,3,0),"-") -> Ream | E5: =IFERROR(VLOOKUP(B5,SUPPLY2,4,0),"-") -> 2067 | F5: ADMIN | G5: =IFERROR(VLOOKUP(A5,YEAR2023,2,0),"-") -> 2
A6: 45695 | B6: Bond copy paper, A4 size,70gsm 500shts/rm | C6: 1 | D6: =IFERROR(VLOOKUP(B6,SUPPLY2,3,0),"-") -> Ream | E6: =IFERROR(VLOOKUP(B6,SUPPLY2,4,0),"-") -> 2276 | F6: MSS-ECS | G6: =IFERROR(VLOOKUP(A6,YEAR2023,2,0),"-") -> 2
A7: 45695 | B7: Bond prem,LEGAL SIZE, 216x330mm,70gsm 500shts/rm | C7: 1 | D7: =IFERROR(VLOOKUP(B7,SUPPLY2,3,0),"-") -> Ream | E7: =IFERROR(VLOOKUP(B7,SUPPLY2,4,0),"-") -> 2067 | F7: MSS-ECS | G7: =IFERROR(VLOOKUP(A7,YEAR2023,2,0),"-") -> 2
A8: 45695 | B8: Bond copy paper, A4 size,70gsm 500shts/rm | C8: 2 | D8: =IFERROR(VLOOKUP(B8,SUPPLY2,3,0),"-") -> Ream | E8: =IFERROR(VLOOKUP(B8,SUPPLY2,4,0),"-") -> 2276 | F8: ADMIN | G8: =IFERROR(VLOOKUP(A8,YEAR2023,2,0),"-") -> 2
A9: 45695 | B9: Bond prem,LEGAL SIZE, 216x330mm,70gsm 500shts/rm | C9: 2 | D9: =IFERROR(VLOOKUP(B9,SUPPLY2,3,0),"-") -> Ream | E9: =IFERROR(VLOOKUP(B9,SUPPLY2,4,0),"-") -> 2067 | F9: ADMIN | G9: =IFERROR(VLOOKUP(A9,YEAR2023,2,0),"-") -> 2
A10: 45701 | B10: Bond prem,LEGAL SIZE, 216x330mm,70gsm 500shts/rm | C10: 2 | D10: =IFERROR(VLOOKUP(B10,SUPPLY2,3,0),"-") -> Ream | E10: =IFERROR(VLOOKUP(B10,SUPPLY2,4,0),"-") -> 2067 | F10: MSS | G10: =IFERROR(VLOOKUP(A10,YEAR2023,2,0),"-") -> 2
A11: 45701 | B11: Bond copy paper, A4 size,70gsm 500shts/rm | C11: 2 | D11: =IFERROR(VLOOKUP(B11,SUPPLY2,3,0),"-") -> Ream | E11: =IFERROR(VLOOKUP(B11,SUPPLY2,4,0),"-") -> 2276 | F11: MSS | G11: =IFERROR(VLOOKUP(A11,YEAR2023,2,0),"-") -> 2
A12: 45706 | B12: Bond copy paper, A4 size,70gsm 500shts/rm | C12: 2 | D12: =IFERROR(VLOOKUP(B12,SUPPLY2,3,0),"-") -> Ream | E12: =IFERROR(VLOOKUP(B12,SUPPLY2,4,0),"-") -> 2276 | F12: ADMIN | G12: =IFERROR(VLOOKUP(A12,YEAR2023,2,0),"-") -> 2
A13: 45706 | B13: Bond prem,LEGAL SIZE, 216x330mm,70gsm 500shts/rm | C13: 2 | D13: =IFERROR(VLOOKUP(B13,SUPPLY2,3,0),"-") -> Ream | E13: =IFERROR(VLOOKUP(B13,SUPPLY2,4,0),"-") -> 2067 | F13: ADMIN | G13: =IFERROR(VLOOKUP(A13,YEAR2023,2,0),"-") -> 2
... A38: 45784 | B38: Tape - masking 1 | C38: 15 | D38: =IFERROR(VLOOKUP(B38,SUPPLY2,3,0),"-") -> Roll | E38: =IFERROR(VLOOKUP(B38,SUPPLY2,4,0),"-") -> 300 | F38: ADMIN | G38: =IFERROR(VLOOKUP(A38,YEAR2023,2,0),"-") -> 5
A39: 45785 | B39: Staple wire, 5000 pcs | C39: 298 | D39: =IFERROR(VLOOKUP(B39,SUPPLY2,3,0),"-") -> Box | E39: =IFERROR(VLOOKUP(B40,SUPPLY2,4,0),"-") -> 281 | F39: ADMIN | G39: =IFERROR(VLOOKUP(A39,YEAR2023,2,0),"-") -> 5
A40: 45796 | B40: Paper – tissue | C40: 132 | D40: =IFERROR(VLOOKUP(B40,SUPPLY2,3,0),"-") -> Roll | E40: =IFERROR(VLOOKUP(B40,SUPPLY2,4,0),"-") -> 281 | F40: ADMIN | G40: =IFERROR(VLOOKUP(A40,YEAR2023,2,0),"-") -> 5
A41: 45799 | B41: Packaging tape 2” | C41: 31 | D41: =IFERROR(VLOOKUP(B41,SUPPLY2,3,0),"-") -> Roll | E41: =IFERROR(VLOOKUP(B41,SUPPLY2,4,0),"-") -> 2537 | F41: ADMIN | G41: =IFERROR(VLOOKUP(A41,YEAR2023,2,0),"-") -> 5
A42: 45814 | B42: Ballpoint pen | C42: 50 | D42: =IFERROR(VLOOKUP(B42,SUPPLY2,3,0),"-") -> Piece | E42: =IFERROR(VLOOKUP(B42,SUPPLY2,4,0),"-") -> 337 | F42: ADMIN | G42: =IFERROR(VLOOKUP(A42,YEAR2023,2,0),"-") -> 6
A43: 45828 | B43: Alcohol, ethyl, 68%-72% | C43: 40 | D43: =IFERROR(VLOOKUP(B43,SUPPLY2,3,0),"-") -> Gallon | E43: =IFERROR(VLOOKUP(B43,SUPPLY2,4,0),"-") -> 2617 | F43: ADMIN | G43: =IFERROR(VLOOKUP(A43,YEAR2023,2,0),"-") -> 6
A44: 45828 | B44: Bond prem,LEGAL SIZE, 216x330mm,70gsm 500shts/rm | C44: 3 | D44: =IFERROR(VLOOKUP(B44,SUPPLY2,3,0),"-") -> Ream | E44: =IFERROR(VLOOKUP(B44,SUPPLY2,4,0),"-") -> 2067 | F44: MSS | G44: =IFERROR(VLOOKUP(A44,YEAR2023,2,0),"-") -> 6
A45: 45834 | B45: Bond copy paper, A4 size,70gsm 500shts/rm | C45: 4 | D45: =IFERROR(VLOOKUP(B45,SUPPLY2,3,0),"-") -> Ream | E45: =IFERROR(VLOOKUP(B45,SUPPLY2,4,0),"-") -> 2276 | F45: KAPATAGAN SO | G45: =IFERROR(VLOOKUP(A45,YEAR2023,2,0),"-") -> 6
A46: 45847 | B46: Tape - masking 1 | C46: 3 | D46: =IFERROR(VLOOKUP(B46,SUPPLY2,3,0),"-") -> Roll | E46: =IFERROR(VLOOKUP(B46,SUPPLY2,4,0),"-") -> 300 | F46: MSS | G46: =IFERROR(VLOOKUP(A46,YEAR2023,2,0),"-") -> 7
A47: 45849 | B47: Folder - legal size, 36mm thick (14pts) | C47: 29 | D47: =IFERROR(VLOOKUP(B47,SUPPLY2,3,0),"-") -> C | E47: =IFERROR(VLOOKUP(B47,SUPPLY2,4,0),"-") -> 330 | F47: MSS | G47: =IFERROR(VLOOKUP(A47,YEAR2023,2,0),"-") -> 7
A48: 45849 | B48: Paper – tissue | C48: 4 | D48: =IFERROR(VLOOKUP(B48,SUPPLY2,3,0),"-") -> Roll | E48: =IFERROR(VLOOKUP(B48,SUPPLY2,4,0),"-") -> 281 | F48: ADMIN | G48: =IFERROR(VLOOKUP(A48,YEAR2023,2,0),"-") -> 7
A49: 45849 | B49: Request/Verification Form new Code | C49: 100 | D49: =IFERROR(VLOOKUP(B49,SUPPLY2,3,0),"-") -> Piece | E49: =IFERROR(VLOOKUP(B49,SUPPLY2,4,0),"-") -> 0 | F49: MSS | G49: =IFERROR(VLOOKUP(A49,YEAR2023,2,0),"-") -> 7
A50: 45849 | B50: Alcohol, ethyl, 68%-72% (500ml) | C50: 8 | D50: =IFERROR(VLOOKUP(B50,SUPPLY2,3,0),"-") -> Bottle | E50: =IFERROR(VLOOKUP(B50,SUPPLY2,4,0),"-") -> 2618 | F50: MSS | G50: =IFERROR(VLOOKUP(A50,YEAR2023,2,0),"-") -> 7
A51: 45849 | B51: Envelope - document, 10 x 15 | C51: 10 | D51: =IFERROR(VLOOKUP(B51,SUPPLY2,3,0),"-") -> C | E51: =IFERROR(VLOOKUP(B51,SUPPLY2,4,0),"-") -> 46 | F51: MSS | G51: =IFERROR(VLOOKUP(A51,YEAR2023,2,0),"-") -> 7
... A112: 45964 | B112: E4-PAGE 1-MEMBER DATA CHANGE PAGE 1 | C112: 10 | D112: =IFERROR(VLOOKUP(B112,SUPPLY2,3,0),"-") -> - | E112: =IFERROR(VLOOKUP(B112,SUPPLY2,4,0),"-") -> - | F112: MSS | G112: =IFERROR(VLOOKUP(A112,YEAR2023,2,0),"-") -> 11
A113: 45966 | B113: E4-PAGE 1-MEMBER DATA CHANGE PAGE 1 | C113: 100 | D113: pieces | E113: =IFERROR(VLOOKUP(B113,SUPPLY2,4,0),"-") -> - | F113: MSS | G113: =IFERROR(VLOOKUP(A113,YEAR2023,2,0),"-") -> 11
A114: 45966 | B114: Bond copy paper, A4 size,70gsm 500shts/rm | C114: 2 | D114: =IFERROR(VLOOKUP(B114,SUPPLY2,3,0),"-") -> Ream | E114: =IFERROR(VLOOKUP(B114,SUPPLY2,4,0),"-") -> 2276 | F114: ADMIN | G114: =IFERROR(VLOOKUP(A114,YEAR2023,2,0),"-") -> 11
A115: 45968 | B115: Thermal paper for set 80 x 30mm | C115: 4 | D115: =IFERROR(VLOOKUP(B115,SUPPLY2,3,0),"-") -> Roll | E115: =IFERROR(VLOOKUP(B115,SUPPLY2,4,0),"-") -> 2629 | F115: MSS | G115: =IFERROR(VLOOKUP(A115,YEAR2023,2,0),"-") -> 11
A116: 45971 | B116: Bond copy paper, A4 size,70gsm 500shts/rm | C116: 2 | D116: =IFERROR(VLOOKUP(B116,SUPPLY2,3,0),"-") -> Ream | E116: =IFERROR(VLOOKUP(B116,SUPPLY2,4,0),"-") -> 2276 | F116: ADMIN | G116: =IFERROR(VLOOKUP(A116,YEAR2023,2,0),"-") -> 11
A117: 45971 | B117: MEMBER DATA CHANGE REQUEST PAGE 1&2 | C117: 100 | D117: =IFERROR(VLOOKUP(B117,SUPPLY2,3,0),"-") -> Ream | E117: =IFERROR(VLOOKUP(B117,SUPPLY2,4,0),"-") -> 0 | F117: MSS | G117: =IFERROR(VLOOKUP(A117,YEAR2023,2,0),"-") -> 11
A118: 45971 | B118: Pencil | C118: 1 | D118: =IFERROR(VLOOKUP(B118,SUPPLY2,3,0),"-") -> Piece | E118: =IFERROR(VLOOKUP(B118,SUPPLY2,4,0),"-") -> 0 | F118: MSS-JGT | G118: =IFERROR(VLOOKUP(A118,YEAR2023,2,0),"-") -> 11
A119: 45971 | B119: Folder - legal size, 36mm thick (14pts) | C119: 10 | D119: =IFERROR(VLOOKUP(B119,SUPPLY2,3,0),"-") -> C | E119: =IFERROR(VLOOKUP(B119,SUPPLY2,4,0),"-") -> 330 | F119: AMS | G119: =IFERROR(VLOOKUP(A119,YEAR2023,2,0),"-") -> 11
A120: 45971 | B120: Request/Verification Form new Code, E4 form | C120: 100 | D120: =IFERROR(VLOOKUP(B120,SUPPLY2,3,0),"-") -> - | E120: =IFERROR(VLOOKUP(B120,SUPPLY2,4,0),"-") -> - | F120: mss | G120: =IFERROR(VLOOKUP(A120,YEAR2023,2,0),"-") -> 11
A121: 45971 | B121: PAYMENT SLIP-CONTRIBUTION 1 | C121: 100 | D121: pieces | E121: =IFERROR(VLOOKUP(B121,SUPPLY2,4,0),"-") -> 2521 | F121: MSS | G121: =IFERROR(VLOOKUP(A121,YEAR2023,2,0),"-") -> 11
A122: 45971 | B122: ACOP- SURVIVING LEGAL SPOUSE | C122: 100 | D122: pieces | E122: =IFERROR(VLOOKUP(B122,SUPPLY2,4,0),"-") -> 0 | F122: MSS | G122: =IFERROR(VLOOKUP(A122,YEAR2023,2,0),"-") -> 11
A123: 45972 | B123: paper cup | C123: 1 | D123: pack | E123: =IFERROR(VLOOKUP(B123,SUPPLY2,4,0),"-") -> - | F123: ADMIN | G123: =IFERROR(VLOOKUP(A123,YEAR2023,2,0),"-") -> 11
A124: 45972 | B124: Alcohol, ethyl, 68%-72% (500ml) | C124: 2 | D124: =IFERROR(VLOOKUP(B124,SUPPLY2,3,0),"-") -> Bottle | E124: =IFERROR(VLOOKUP(B124,SUPPLY2,4,0),"-") -> 2618 | F124: ADMIN | G124: =IFERROR(VLOOKUP(A124,YEAR2023,2,0),"-") -> 11
A125: 45972 | B125: Pensioner Dara changes request | C125: 100 | D125: piece | E125: =IFERROR(VLOOKUP(B125,SUPPLY2,4,0),"-") -> - | F125: MSS | G125: =IFERROR(VLOOKUP(A125,YEAR2023,2,0),"-") -> 11
A126: 45972 | B126: E4 form page 1&2, data privacy | C126: 100 | D126: piece | E126: =IFERROR(VLOOKUP(B126,SUPPLY2,4,0),"-") -> - | F126: MSS | G126: =IFERROR(VLOOKUP(A126,YEAR2023,2,0),"-") -> 11
A127: 45972 | B127: Paper – tissue | C127: 1 | D127: piece | E127: =IFERROR(VLOOKUP(B127,SUPPLY2,4,0),"-") -> 281 | F127: ADMIN | G127: =IFERROR(VLOOKUP(A127,YEAR2023,2,0),"-") -> 11
A128: 45973 | B128: Envelope - document, 10 x 15 | C128: 1 | D128: =IFERROR(VLOOKUP(B128,SUPPLY2,3,0),"-") -> C | E128: =IFERROR(VLOOKUP(B128,SUPPLY2,4,0),"-") -> 46 | F128: MSS-ECS | G128: =IFERROR(VLOOKUP(A128,YEAR2023,2,0),"-") -> 11
A129: 45973 | B129: Bond copy paper, A4 size,70gsm 500shts/rm | C129: 2 | D129: =IFERROR(VLOOKUP(B129,SUPPLY2,3,0),"-") -> Ream | E129: =IFERROR(VLOOKUP(B129,SUPPLY2,4,0),"-") -> 2276 | F129: ADMIN | G129: =IFERROR(VLOOKUP(A129,YEAR2023,2,0),"-") -> 11
A130: 45974 | B130: E4 form , data privacy | C130: 100 | D130: PIECE | E130: =IFERROR(VLOOKUP(B130,SUPPLY2,4,0),"-") -> - | F130: MSS | G130: =IFERROR(VLOOKUP(A130,YEAR2023,2,0),"-") -> 11
A131: 45974 | B131: Envelope - document, 10 x 15 | C131: 10 | D131: piece | E131: =IFERROR(VLOOKUP(B131,SUPPLY2,4,0),"-") -> 46 | F131: MSS | G131: =IFERROR(VLOOKUP(A131,YEAR2023,2,0),"-") -> 11
A132: 45975 | B132: Bond copy paper, A4 size,70gsm 500shts/rm | C132: 2 | D132: ream | E132: =IFERROR(VLOOKUP(B132,SUPPLY2,4,0),"-") -> 2276 | F132: admin | G132: =IFERROR(VLOOKUP(A132,YEAR2023,2,0),"-") -> 11
A133: 45975 | B133: Alcohol, ethyl, 68%-72% (500ml) | C133: 1 | D133: =IFERROR(VLOOKUP(B133,SUPPLY2,3,0),"-") -> Bottle | E133: =IFERROR(VLOOKUP(B133,SUPPLY2,4,0),"-") -> 2618 | F133: admin | G133: =IFERROR(VLOOKUP(A133,YEAR2023,2,0),"-") -> 11
A134: 45975 | B134: paper cups | C134: 1 | D134: pack | E134: =IFERROR(VLOOKUP(B134,SUPPLY2,4,0),"-") -> - | F134: admin | G134: =IFERROR(VLOOKUP(A134,YEAR2023,2,0),"-") -> 11
A135: 45975 | B135: Bond prem,LEGAL SIZE, 216x330mm,70gsm 500shts/rm | C135: 1 | D135: ream | E135: =IFERROR(VLOOKUP(B135,SUPPLY2,4,0),"-") -> 2067 | F135: admin | G135: =IFERROR(VLOOKUP(A135,YEAR2023,2,0),"-") -> 11
A136: 45975 | B136: Corrugated box | C136: 1 | D136: piece | E136: =IFERROR(VLOOKUP(B136,SUPPLY2,4,0),"-") -> 313 | F136: tellering | G136: =IFERROR(VLOOKUP(A136,YEAR2023,2,0),"-") -> 11
A137: 45975 | B137: MEMBER DATA CHANGE REQUEST PAGE 1&2 | C137: 100 | D137: piece | E137: =IFERROR(VLOOKUP(B137,SUPPLY2,4,0),"-") -> 0 | F137: MSS | G137: =IFERROR(VLOOKUP(A137,YEAR2023,2,0),"-") -> 11
A138: 45975 | B138: Alcohol, ethyl, 68%-72% (500ml) | C138: 1 | D138: piece | E138: =IFERROR(VLOOKUP(B138,SUPPLY2,4,0),"-") -> 2618 | F138: MSS | G138: =IFERROR(VLOOKUP(A138,YEAR2023,2,0),"-") -> 11
A139: 45975 | B139: ACOP- SURVIVING LEGAL SPOUSE | C139: 100 | D139: piece | E139: =IFERROR(VLOOKUP(B139,SUPPLY2,4,0),"-") -> 0 | F139: MSS | G139: =IFERROR(VLOOKUP(A139,YEAR2023,2,0),"-") -> 11
A140: 45975 | B140: ball pen | C140: 2 | D140: piece | E140: =IFERROR(VLOOKUP(B140,SUPPLY2,4,0),"-") -> - | F140: MSS | G140: =IFERROR(VLOOKUP(A140,YEAR2023,2,0),"-") -> 11
A141: 45975 | B141: Staple wire, 5000 pcs | C141: 1 | D141: piece | E141: =IFERROR(VLOOKUP(B141,SUPPLY2,4,0),"-") -> 310 | F141: MSS | G141: =IFERROR(VLOOKUP(A141,YEAR2023,2,0),"-") -> 11
A142: 45975 | B142: Paper – tissue | C142: 1 | D142: ROLL | E142: =IFERROR(VLOOKUP(B142,SUPPLY2,4,0),"-") -> 281 | F142: MSS | G142: =IFERROR(VLOOKUP(A142,YEAR2023,2,0),"-") -> 11
A143: 45975 | B143: DEATH CLAIM APPLICATION 1 | C143: 10 | D143: =IFERROR(VLOOKUP(B143,SUPPLY2,3,0),"-") -> Ream | E143: =IFERROR(VLOOKUP(B143,SUPPLY2,4,0),"-") -> 1938 | F143: MSS | G143: =IFERROR(VLOOKUP(A143,YEAR2023,2,0),"-") -> 11
A144: 45975 | B144: RETIREMENT P.1 | C144: 10 | D144: =IFERROR(VLOOKUP(B144,SUPPLY2,3,0),"-") -> Ream | E144: =IFERROR(VLOOKUP(B144,SUPPLY2,4,0),"-") -> 1939 | F144: MSS | G144: =IFERROR(VLOOKUP(A144,YEAR2023,2,0),"-") -> 11
A145: 45978 | B145: MEMBER DATA CHANGE REQUEST PAGE 1&2 | C145: 100 | D145: =IFERROR(VLOOKUP(B145,SUPPLY2,3,0),"-") -> Ream | E145: =IFERROR(VLOOKUP(B145,SUPPLY2,4,0),"-") -> 0 | F145: MSS | G145: =IFERROR(VLOOKUP(A145,YEAR2023,2,0),"-") -> 11
A146: 45978 | B146: Staple wire, 5000 pcs | C146: 1 | D146: =IFERROR(VLOOKUP(B146,SUPPLY2,3,0),"-") -> Box | E146: =IFERROR(VLOOKUP(B146,SUPPLY2,4,0),"-") -> 310 | F146: MSS-CTD | G146: =IFERROR(VLOOKUP(A146,YEAR2023,2,0),"-") -> 11
A147: 45978 | B147: Thermal paper for set 80 x 30mm | C147: 4 | D147: =IFERROR(VLOOKUP(B147,SUPPLY2,3,0),"-") -> Roll | E147: =IFERROR(VLOOKUP(B147,SUPPLY2,4,0),"-") -> 2629 | F147: ADMIN | G147: =IFERROR(VLOOKUP(A147,YEAR2023,2,0),"-") -> 11
A148: 45978 | B148: Bond copy paper, A4 size,70gsm 500shts/rm | C148: 1 | D148: =IFERROR(VLOOKUP(B148,SUPPLY2,3,0),"-") -> Ream | E148: =IFERROR(VLOOKUP(B148,SUPPLY2,4,0),"-") -> 2276 | F148: ADMIN | G148: =IFERROR(VLOOKUP(A148,YEAR2023,2,0),"-") -> 11
A149: 45978 | B149: Alcohol, ethyl, 68%-72% (500ml) | C149: 1 | D149: =IFERROR(VLOOKUP(B149,SUPPLY2,3,0),"-") -> Bottle | E149: =IFERROR(VLOOKUP(B149,SUPPLY2,4,0),"-") -> 2618 | F149: AMS | G149: =IFERROR(VLOOKUP(A149,YEAR2023,2,0),"-") -> 11
A150: 45978 | B150: E4-PAGE 1-MEMBER DATA CHANGE page 1&2 | C150: 100 | D150: piece | E150: =IFERROR(VLOOKUP(B150,SUPPLY2,4,0),"-") -> - | F150: MSS | G150: =IFERROR(VLOOKUP(A150,YEAR2023,2,0),"-") -> 11
A151: 45978 | B151: Bond prem,LEGAL SIZE, 216x330mm,70gsm 500shts/rm | C151: 1 | D151: =IFERROR(VLOOKUP(B151,SUPPLY2,3,0),"-") -> Ream | E151: =IFERROR(VLOOKUP(B151,SUPPLY2,4,0),"-") -> 2067 | F151: ADMIN | G151: =IFERROR(VLOOKUP(A151,YEAR2023,2,0),"-") -> 11
A152: 45978 | B152: Bond copy paper, A4 size,70gsm 500shts/rm | C152: 1 | D152: =IFERROR(VLOOKUP(B152,SUPPLY2,3,0),"-") -> Ream | E152: =IFERROR(VLOOKUP(B152,SUPPLY2,4,0),"-") -> 2276 | F152: ADMIN | G152: =IFERROR(VLOOKUP(A152,YEAR2023,2,0),"-") -> 11
A153: 45978 | B153: DEATH CLAIM APPLICATION 1 | C153: 50 | D153: piece | E153: =IFERROR(VLOOKUP(B153,SUPPLY2,4,0),"-") -> 1938 | F153: MSS | G153: =IFERROR(VLOOKUP(A153,YEAR2023,2,0),"-") -> 11
A154: 45979 | B154: Bond prem,LEGAL SIZE, 216x330mm,70gsm 500shts/rm | C154: 1 | D154: ream | E154: =IFERROR(VLOOKUP(B154,SUPPLY2,4,0),"-") -> 2067 | F154: ADMIN | G154: =IFERROR(VLOOKUP(A154,YEAR2023,2,0),"-") -> 11
A155: 45979 | B155: Bond copy paper, A4 size,70gsm 500shts/rm | C155: 2 | D155: =IFERROR(VLOOKUP(B155,SUPPLY2,3,0),"-") -> Ream | E155: =IFERROR(VLOOKUP(B155,SUPPLY2,4,0),"-") -> 2276 | F155: ADMIN | G155: =IFERROR(VLOOKUP(A155,YEAR2023,2,0),"-") -> 11
A156: 45979 | B156: MEMBER DATA CHANGE REQUEST PAGE 1&2 | C156: 100 | D156: piece | E156: =IFERROR(VLOOKUP(B156,SUPPLY2,4,0),"-") -> 0 | G156: =IFERROR(VLOOKUP(A156,YEAR2023,2,0),"-") -> 11
A157: 45980 | B157: MEMBER DATA CHANGE REQUEST PAGE 1&2 | C157: 100 | D157: PIECE | E157: =IFERROR(VLOOKUP(B157,SUPPLY2,4,0),"-") -> 0 | G157: =IFERROR(VLOOKUP(A157,YEAR2023,2,0),"-") -> 11
A158: 45980 | B158: Bond copy paper, A4 size,70gsm 500shts/rm | C158: 1 | D158: =IFERROR(VLOOKUP(B158,SUPPLY2,3,0),"-") -> Ream | E158: =IFERROR(VLOOKUP(B158,SUPPLY2,4,0),"-") -> 2276 | F158: TELLERING | G158: =IFERROR(VLOOKUP(A158,YEAR2023,2,0),"-") -> 11
A159: 45980 | B159: Folder - legal size, 36mm thick (14pts) | C159: 1 | D159: piece | E159: =IFERROR(VLOOKUP(B159,SUPPLY2,4,0),"-") -> 330 | G159: =IFERROR(VLOOKUP(A159,YEAR2023,2,0),"-") -> 11
A160: 45981 | B160: Paper – tissue | C160: 4 | D160: =IFERROR(VLOOKUP(B160,SUPPLY2,3,0),"-") -> Roll | E160: =IFERROR(VLOOKUP(B160,SUPPLY2,4,0),"-") -> 281 | G160: =IFERROR(VLOOKUP(A160,YEAR2023,2,0),"-") -> 11
A161: 45981 | B161: MEMBER DATA CHANGE REQUEST PAGE 1&2 | C161: 100 | D161: piece | E161: =IFERROR(VLOOKUP(B161,SUPPLY2,4,0),"-") -> 0 | G161: =IFERROR(VLOOKUP(A161,YEAR2023,2,0),"-") -> 11
A162: 45981 | B162: Request/Verification Form new Code | C162: 100 | D162: =IFERROR(VLOOKUP(B162,SUPPLY2,3,0),"-") -> Piece | E162: =IFERROR(VLOOKUP(B162,SUPPLY2,4,0),"-") -> 0 | G162: =IFERROR(VLOOKUP(A162,YEAR2023,2,0),"-") -> 11
A163: 45981 | B163: PAYMENT SLIP-CONTRIBUTION 1 | C163: 200 | D163: =IFERROR(VLOOKUP(B163,SUPPLY2,3,0),"-") -> Ream | E163: =IFERROR(VLOOKUP(B163,SUPPLY2,4,0),"-") -> 2521 | G163: =IFERROR(VLOOKUP(A163,YEAR2023,2,0),"-") -> 11
A164: 45981 | B164: PAYMENT SLIP-MEMBER LOAN | C164: 100 | D164: =IFERROR(VLOOKUP(B164,SUPPLY2,3,0),"-") -> Ream | E164: =IFERROR(VLOOKUP(B164,SUPPLY2,4,0),"-") -> 2576 | G164: =IFERROR(VLOOKUP(A164,YEAR2023,2,0),"-") -> 11
A165: 45981 | B165: ACOP- SURVIVING LEGAL SPOUSE | C165: 100 | D165: =IFERROR(VLOOKUP(B165,SUPPLY2,3,0),"-") -> Ream | E165: =IFERROR(VLOOKUP(B165,SUPPLY2,4,0),"-") -> 0 | G165: =IFERROR(VLOOKUP(A165,YEAR2023,2,0),"-") -> 11
A166: 45981 | B166: ACOP- RETIREMENT/DISABILITY | C166: 100 | D166: =IFERROR(VLOOKUP(B166,SUPPLY2,3,0),"-") -> Ream | E166: =IFERROR(VLOOKUP(B166,SUPPLY2,4,0),"-") -> 0 | G166: =IFERROR(VLOOKUP(A166,YEAR2023,2,0),"-") -> 11
A167: 45981 | B167: PENSIONER DATA REQUEST | C167: 100 | D167: =IFERROR(VLOOKUP(B167,SUPPLY2,3,0),"-") -> - | E167: =IFERROR(VLOOKUP(B167,SUPPLY2,4,0),"-") -> - | G167: =IFERROR(VLOOKUP(A167,YEAR2023,2,0),"-") -> 11
A168: 45981 | B168: Bond copy paper, A4 size,70gsm 500shts/rm | C168: 1 | D168: =IFERROR(VLOOKUP(B168,SUPPLY2,3,0),"-") -> Ream | E168: =IFERROR(VLOOKUP(B168,SUPPLY2,4,0),"-") -> 2276 | F168: MSS | G168: =IFERROR(VLOOKUP(A168,YEAR2023,2,0),"-") -> 11
A169: 45982 | B169: Bond copy paper, A4 size,70gsm 500shts/rm | C169: 3 | D169: =IFERROR(VLOOKUP(B169,SUPPLY2,3,0),"-") -> Ream | E169: =IFERROR(VLOOKUP(B169,SUPPLY2,4,0),"-") -> 2276 | F169: ADMIN | G169: =IFERROR(VLOOKUP(A169,YEAR2023,2,0),"-") -> 11
A170: 45982 | B170: Alcohol, ethyl, 68%-72% (500ml) | C170: 2 | D170: =IFERROR(VLOOKUP(B170,SUPPLY2,3,0),"-") -> Bottle | E170: =IFERROR(VLOOKUP(B170,SUPPLY2,4,0),"-") -> 2618 | G170: =IFERROR(VLOOKUP(A170,YEAR2023,2,0),"-") -> 11
A171: 45985 | B171: Bond copy paper, A4 size,70gsm 500shts/rm | C171: 2 | D171: =IFERROR(VLOOKUP(B171,SUPPLY2,3,0),"-") -> Ream | E171: =IFERROR(VLOOKUP(B171,SUPPLY2,4,0),"-") -> 2276 | F171: ADMIN | G171: =IFERROR(VLOOKUP(A171,YEAR2023,2,0),"-") -> 11
A172: 45986 | B172: Bond copy paper, A4 size,70gsm 500shts/rm | C172: 1 | D172: =IFERROR(VLOOKUP(B172,SUPPLY2,3,0),"-") -> Ream | E172: =IFERROR(VLOOKUP(B172,SUPPLY2,4,0),"-") -> 2276 | F172: ADMIN | G172: =IFERROR(VLOOKUP(A172,YEAR2023,2,0),"-") -> 11
A173: 45986 | B173: Alcohol, ethyl, 68%-72% (500ml) | C173: 1 | D173: =IFERROR(VLOOKUP(B173,SUPPLY2,3,0),"-") -> Bottle | E173: =IFERROR(VLOOKUP(B173,SUPPLY2,4,0),"-") -> 2618 | F173: ADMIN | G173: =IFERROR(VLOOKUP(A173,YEAR2023,2,0),"-") -> 11
A174: 45986 | B174: Bond prem,LEGAL SIZE, 216x330mm,70gsm 500shts/rm | C174: 1 | D174: =IFERROR(VLOOKUP(B174,SUPPLY2,3,0),"-") -> Ream | E174: =IFERROR(VLOOKUP(B174,SUPPLY2,4,0),"-") -> 2067 | F174: MSS | G174: =IFERROR(VLOOKUP(A174,YEAR2023,2,0),"-") -> 11
A175: 45987 | B175: Ballpoint pen | C175: 2 | D175: =IFERROR(VLOOKUP(B175,SUPPLY2,3,0),"-") -> Piece | E175: =IFERROR(VLOOKUP(B175,SUPPLY2,4,0),"-") -> 337 | F175: mss | G175: =IFERROR(VLOOKUP(A175,YEAR2023,2,0),"-") -> 11
A176: 45987 | B176: Bond copy paper, A4 size,70gsm 500shts/rm | C176: 3 | D176: =IFERROR(VLOOKUP(B176,SUPPLY2,3,0),"-") -> Ream | E176: =IFERROR(VLOOKUP(B176,SUPPLY2,4,0),"-") -> 2276 | F176: mss | G176: =IFERROR(VLOOKUP(A176,YEAR2023,2,0),"-") -> 11
A177: 45987 | B177: Bond prem,LEGAL SIZE, 216x330mm,70gsm 500shts/rm | C177: 1 | D177: =IFERROR(VLOOKUP(B177,SUPPLY2,3,0),"-") -> Ream | E177: =IFERROR(VLOOKUP(B177,SUPPLY2,4,0),"-") -> 2067 | F177: ADMIN | G177: =IFERROR(VLOOKUP(A177,YEAR2023,2,0),"-") -> 11
A178: 45988 | B178: Alcohol, ethyl, 68%-72% (500ml) | C178: 2 | D178: =IFERROR(VLOOKUP(B178,SUPPLY2,3,0),"-") -> Bottle | E178: =IFERROR(VLOOKUP(B178,SUPPLY2,4,0),"-") -> 2618 | G178: =IFERROR(VLOOKUP(A178,YEAR2023,2,0),"-") -> 11
A179: 45988 | B179: DEATH CLAIM APPLICATION 1,2 | C179: 100 | D179: =IFERROR(VLOOKUP(B179,SUPPLY2,3,0),"-") -> - | E179: =IFERROR(VLOOKUP(B179,SUPPLY2,4,0),"-") -> - | F179: MSS-GSA | G179: =IFERROR(VLOOKUP(A179,YEAR2023,2,0),"-") -> 11
A180: 45988 | B180: MEMBER DATA CHANGE REQUEST PAGE 1&2 | C180: 100 | D180: =IFERROR(VLOOKUP(B180,SUPPLY2,3,0),"-") -> Ream | E180: =IFERROR(VLOOKUP(B180,SUPPLY2,4,0),"-") -> 0 | G180: =IFERROR(VLOOKUP(A180,YEAR2023,2,0),"-") -> 11
A181: 45989 | B181: MEMBER DATA CHANGE REQUEST PAGE 1&2 | C181: 100 | D181: =IFERROR(VLOOKUP(B181,SUPPLY2,3,0),"-") -> Ream | E181: =IFERROR(VLOOKUP(B181,SUPPLY2,4,0),"-") -> 0 | G181: =IFERROR(VLOOKUP(A181,YEAR2023,2,0),"-") -> 11
A182: 45989 | B182: ACOP- SURVIVING LEGAL SPOUSE | C182: 200 | D182: =IFERROR(VLOOKUP(B182,SUPPLY2,3,0),"-") -> Ream | E182: =IFERROR(VLOOKUP(B182,SUPPLY2,4,0),"-") -> 0 | G182: =IFERROR(VLOOKUP(A182,YEAR2023,2,0),"-") -> 11
A183: 45989 | B183: PAYMENT SLIP-CONTRIBUTION 1 | C183: 200 | D183: =IFERROR(VLOOKUP(B183,SUPPLY2,3,0),"-") -> Ream | E183: =IFERROR(VLOOKUP(B183,SUPPLY2,4,0),"-") -> 2521 | G183: =IFERROR(VLOOKUP(A183,YEAR2023,2,0),"-") -> 11
A184: 45989 | B184: Bond copy paper, A4 size,70gsm 500shts/rm | C184: 2 | D184: =IFERROR(VLOOKUP(B184,SUPPLY2,3,0),"-") -> Ream | E184: =IFERROR(VLOOKUP(B184,SUPPLY2,4,0),"-") -> 2276 | F184: ADMIN | G184: =IFERROR(VLOOKUP(A184,YEAR2023,2,0),"-") -> 11
...

Sheet SUMMARY
A1: DATE TODAY (MM/DD/YYYY) | B1: DESCRIPTION | C1: BEG BALANCE (QTY) | D1: TOTAL STOCKS RECEIVED (QTY) | E1: TOTAL STOCKS RELEASED (QTY) | F1: ENDING BALANCE (QTY) | G1: UNIT | H1: STOCK CODE | I1: MONTH | L1: ACTUAL
A2: =TODAY() -> 46223 | B2: Bond copy paper, A4 size,70gsm 500shts/rm | C2: 9 | D2: =SUMIFS('DATA ENTRY - RECEIVED'!F:F,'DATA ENTRY - RECEIVED'!E:E,"=Bond copy paper, A4 size,70gsm 500shts/rm") -> 295 | E2: =SUMIFS('DATA ENTRY - RELEASED'!C:C,'DATA ENTRY - RELEASED'!B:B,"=Bond copy paper, A4 size,70gsm 500shts/rm") -> 212 | F2: =Table26[[#This Row],[BEG BALANCE (QTY)]]+Table26[[#This Row],[TOTAL STOCKS RECEIVED (QTY)]]-Table26[[#This Row],[TOTAL STOCKS RELEASED (QTY)]] -> 92 | G2: =IFERROR(VLOOKUP(B2,SUPPLY2,3,0),"-") -> Ream | H2: =IFERROR(VLOOKUP(B2,SUPPLY2,4,0),"-") -> 2276 | I2: =IFERROR(VLOOKUP(A2,YEAR2023,2,0),"-") -> 0 | L2: 97
A3: =TODAY() -> 46223 | B3: Bond prem,LEGAL SIZE, 216x330mm,70gsm 500shts/rm | C3: 241 | D3: =SUMIFS('DATA ENTRY - RECEIVED'!F:F,'DATA ENTRY - RECEIVED'!E:E,"=Bond prem,LEGAL SIZE, 216x330mm,70gsm 500shts/rm") -> 151 | E3: =SUMIFS('DATA ENTRY - RELEASED'!C:C,'DATA ENTRY - RELEASED'!B:B,"=Bond prem,LEGAL SIZE, 216x330mm,70gsm 500shts/rm") -> 90 | F3: =Table26[[#This Row],[BEG BALANCE (QTY)]]+Table26[[#This Row],[TOTAL STOCKS RECEIVED (QTY)]]-Table26[[#This Row],[TOTAL STOCKS RELEASED (QTY)]] -> 302 | G3: =IFERROR(VLOOKUP(B3,SUPPLY2,3,0),"-") -> Ream | H3: =IFERROR(VLOOKUP(B3,SUPPLY2,4,0),"-") -> 2067 | I3: =IFERROR(VLOOKUP(A3,YEAR2023,2,0),"-") -> 0 | L3: 302
A4: =TODAY() -> 46223 | B4: Carbon film, legal | C4: 51 | D4: =SUMIFS('DATA ENTRY - RECEIVED'!F:F,'DATA ENTRY - RECEIVED'!E:E,"=Carbon film, legal") -> 0 | E4: =SUMIFS('DATA ENTRY - RELEASED'!C:C,'DATA ENTRY - RELEASED'!B:B,"=Carbon film, legal") -> 0 | F4: =Table26[[#This Row],[BEG BALANCE (QTY)]]+Table26[[#This Row],[TOTAL STOCKS RECEIVED (QTY)]]-Table26[[#This Row],[TOTAL STOCKS RELEASED (QTY)]] -> 51 | G4: =IFERROR(VLOOKUP(B4,SUPPLY2,3,0),"-") -> Box | H4: =IFERROR(VLOOKUP(B4,SUPPLY2,4,0),"-") -> 2634 | I4: =IFERROR(VLOOKUP(A4,YEAR2023,2,0),"-") -> 0 | L4: 51
A5: =TODAY() -> 46223 | B5: Cartolina - white, 22-1/2 x 28-1/2 | D5: =SUMIFS('DATA ENTRY - RECEIVED'!F:F,'DATA ENTRY - RECEIVED'!E:E,"=Cartolina - white, 22-1/2 x 28-1/2") -> 0 | E5: =SUMIFS('DATA ENTRY - RELEASED'!C:C,'DATA ENTRY - RELEASED'!B:B,"=Cartolina - white, 22-1/2 x 28-1/2") -> 0 | F5: =Table26[[#This Row],[BEG BALANCE (QTY)]]+Table26[[#This Row],[TOTAL STOCKS RECEIVED (QTY)]]-Table26[[#This Row],[TOTAL STOCKS RELEASED (QTY)]] -> 0 | G5: =IFERROR(VLOOKUP(B5,SUPPLY2,3,0),"-") -> Piece | H5: =IFERROR(VLOOKUP(B5,SUPPLY2,4,0),"-") -> 5 | I5: =IFERROR(VLOOKUP(A5,YEAR2023,2,0),"-") -> 0
A6: =TODAY() -> 46223 | B6: Envelope - document, 10 x 15 | C6: 0 | D6: =SUMIFS('DATA ENTRY - RECEIVED'!F:F,'DATA ENTRY - RECEIVED'!E:E,"=Envelope - document, 10 x 15") -> 132 | E6: =SUMIFS('DATA ENTRY - RELEASED'!C:C,'DATA ENTRY - RELEASED'!B:B,"=Envelope - document, 10 x 15")*(0.01) -> 1.52 | F6: =Table26[[#This Row],[BEG BALANCE (QTY)]]+Table26[[#This Row],[TOTAL STOCKS RECEIVED (QTY)]]-Table26[[#This Row],[TOTAL STOCKS RELEASED (QTY)]] -> 130.48 | G6: =IFERROR(VLOOKUP(B6,SUPPLY2,3,0),"-") -> C | H6: =IFERROR(VLOOKUP(B6,SUPPLY2,4,0),"-") -> 46 | I6: =IFERROR(VLOOKUP(A6,YEAR2023,2,0),"-") -> 0 | L6: 1
A7: =TODAY() -> 46223 | B7: Envelope - expanding 11x15x 2 w/out flap | D7: =SUMIFS('DATA ENTRY - RECEIVED'!F:F,'DATA ENTRY - RECEIVED'!E:E,"=Envelope - expanding 11x15x 2 w/out flap") -> 0 | E7: =SUMIFS('DATA ENTRY - RELEASED'!C:C,'DATA ENTRY - RELEASED'!B:B,"=Envelope - expanding 11x15x 2 w/out flap") -> 4 | F7: =Table26[[#This Row],[BEG BALANCE (QTY)]]+Table26[[#This Row],[TOTAL STOCKS RECEIVED (QTY)]]-Table26[[#This Row],[TOTAL STOCKS RELEASED (QTY)]] -> -4 | G7: =IFERROR(VLOOKUP(B7,SUPPLY2,3,0),"-") -> Piece | H7: =IFERROR(VLOOKUP(B7,SUPPLY2,4,0),"-") -> 59 | I7: =IFERROR(VLOOKUP(A7,YEAR2023,2,0),"-") -> 0
A8: =TODAY() -> 46223 | B8: Envelope - window reg mailing only white (500 pcs/box) | D8: =SUMIFS('DATA ENTRY - RECEIVED'!F:F,'DATA ENTRY - RECEIVED'!E:E,"=Envelope - window reg mailing only white (500 pcs/box)") -> 0 | E8: =SUMIFS('DATA ENTRY - RELEASED'!C:C,'DATA ENTRY - RELEASED'!B:B,"=Envelope - window reg mailing only white (500 pcs/box)") -> 0 | F8: =Table26[[#This Row],[BEG BALANCE (QTY)]]+Table26[[#This Row],[TOTAL STOCKS RECEIVED (QTY)]]-Table26[[#This Row],[TOTAL STOCKS RELEASED (QTY)]] -> 0 | G8: =IFERROR(VLOOKUP(B8,SUPPLY2,3,0),"-") -> Box | H8: =IFERROR(VLOOKUP(B8,SUPPLY2,4,0),"-") -> 40 | I8: =IFERROR(VLOOKUP(A8,YEAR2023,2,0),"-") -> 0
A9: =TODAY() -> 46223 | B9: Envelope-wdw reg no add white for brnchs (500 pcs/box) | D9: =SUMIFS('DATA ENTRY - RECEIVED'!F:F,'DATA ENTRY - RECEIVED'!E:E,"=Envelope-wdw reg no add white for brnchs (500 pcs/box)") -> 0 | E9: =SUMIFS('DATA ENTRY - RELEASED'!C:C,'DATA ENTRY - RELEASED'!B:B,"=Envelope-wdw reg no add white for brnchs (500 pcs/box)") -> 0 | F9: =Table26[[#This Row],[BEG BALANCE (QTY)]]+Table26[[#This Row],[TOTAL STOCKS RECEIVED (QTY)]]-Table26[[#This Row],[TOTAL STOCKS RELEASED (QTY)]] -> 0 | G9: =IFERROR(VLOOKUP(B9,SUPPLY2,3,0),"-") -> Box | H9: =IFERROR(VLOOKUP(B9,SUPPLY2,4,0),"-") -> 1695 | I9: =IFERROR(VLOOKUP(A9,YEAR2023,2,0),"-") -> 0
A10: =TODAY() -> 46223 | B10: Envelope, expanding kraftboard for legal docs. | D10: =SUMIFS('DATA ENTRY - RECEIVED'!F:F,'DATA ENTRY - RECEIVED'!E:E,"=Envelope, expanding kraftboard for legal docs.") -> 0 | E10: =SUMIFS('DATA ENTRY - RELEASED'!C:C,'DATA ENTRY - RELEASED'!B:B,"=Envelope, expanding kraftboard for legal docs.") -> 6 | F10: =Table26[[#This Row],[BEG BALANCE (QTY)]]+Table26[[#This Row],[TOTAL STOCKS RECEIVED (QTY)]]-Table26[[#This Row],[TOTAL STOCKS RELEASED (QTY)]] -> -6 | G10: =IFERROR(VLOOKUP(B10,SUPPLY2,3,0),"-") -> Piece | H10: =IFERROR(VLOOKUP(B10,SUPPLY2,4,0),"-") -> 2366 | I10: =IFERROR(VLOOKUP(A10,YEAR2023,2,0),"-") -> 0
A11: =TODAY() -> 46223 | B11: Folder - cardboard loose lift 8-1/2x14 | D11: =SUMIFS('DATA ENTRY - RECEIVED'!F:F,'DATA ENTRY - RECEIVED'!E:E,"=Folder - cardboard loose lift 8-1/2x14") -> 0 | E11: =SUMIFS('DATA ENTRY - RELEASED'!C:C,'DATA ENTRY - RELEASED'!B:B,"=Folder - cardboard loose lift 8-1/2x14") -> 0 | F11: =Table26[[#This Row],[BEG BALANCE (QTY)]]+Table26[[#This Row],[TOTAL STOCKS RECEIVED (QTY)]]-Table26[[#This Row],[TOTAL STOCKS RELEASED (QTY)]] -> 0 | G11: =IFERROR(VLOOKUP(B11,SUPPLY2,3,0),"-") -> Set | H11: =IFERROR(VLOOKUP(B11,SUPPLY2,4,0),"-") -> 331 | I11: =IFERROR(VLOOKUP(A11,YEAR2023,2,0),"-") -> 0
A12: =TODAY() -> 46223 | B12: Folder - legal size, 36mm thick (14pts) | C12: 2 | D12: =SUMIFS('DATA ENTRY - RECEIVED'!F:F,'DATA ENTRY - RECEIVED'!E:E,"=Folder - legal size, 36mm thick (14pts)") -> 143 | E12: =SUMIFS('DATA ENTRY - RELEASED'!C:C,'DATA ENTRY - RELEASED'!B:B,"=Folder - legal size, 36mm thick (14pts)") -> 315 | F12: =Table26[[#This Row],[BEG BALANCE (QTY)]]+Table26[[#This Row],[TOTAL STOCKS RECEIVED (QTY)]]-Table26[[#This Row],[TOTAL STOCKS RELEASED (QTY)]] -> -170 | G12: =IFERROR(VLOOKUP(B12,SUPPLY2,3,0),"-") -> C | H12: =IFERROR(VLOOKUP(B12,SUPPLY2,4,0),"-") -> 330 | I12: =IFERROR(VLOOKUP(A12,YEAR2023,2,0),"-") -> 0 | L12: 1
A13: =TODAY() -> 46223 | B13: Folder - marble green, 11 x 14-7/8 | D13: =SUMIFS('DATA ENTRY - RECEIVED'!F:F,'DATA ENTRY - RECEIVED'!E:E,"=Folder - marble green, 11 x 14-7/8") -> 0 | E13: =SUMIFS('DATA ENTRY - RELEASED'!C:C,'DATA ENTRY - RELEASED'!B:B,"=Folder - marble green, 11 x 14-7/8") -> 0 | F13: =Table26[[#This Row],[BEG BALANCE (QTY)]]+Table26[[#This Row],[TOTAL STOCKS RECEIVED (QTY)]]-Table26[[#This Row],[TOTAL STOCKS RELEASED (QTY)]] -> 0 | G13: =IFERROR(VLOOKUP(B13,SUPPLY2,3,0),"-") -> Set | H13: =IFERROR(VLOOKUP(B13,SUPPLY2,4,0),"-") -> 65 | I13: =IFERROR(VLOOKUP(A13,YEAR2023,2,0),"-") -> 0
A14: =TODAY() -> 46223 | B14: Paper - adding machine tape, 2-1/4 | D14: =SUMIFS('DATA ENTRY - RECEIVED'!F:F,'DATA ENTRY - RECEIVED'!E:E,"=Paper - adding machine tape, 2-1/4") -> 0 | E14: =SUMIFS('DATA ENTRY - RELEASED'!C:C,'DATA ENTRY - RELEASED'!B:B,"=Paper - adding machine tape, 2-1/4") -> 0 | F14: =Table26[[#This Row],[BEG BALANCE (QTY)]]+Table26[[#This Row],[TOTAL STOCKS RECEIVED (QTY)]]-Table26[[#This Row],[TOTAL STOCKS RELEASED (QTY)]] -> 0 | G14: =IFERROR(VLOOKUP(B14,SUPPLY2,3,0),"-") -> Piece | H14: =IFERROR(VLOOKUP(B14,SUPPLY2,4,0),"-") -> 70 | I14: =IFERROR(VLOOKUP(A14,YEAR2023,2,0),"-") -> 0
A15: =TODAY() -> 46223 | B15: Paper-bond w/letterhead, a4 size 70gsm | D15: =SUMIFS('DATA ENTRY - RECEIVED'!F:F,'DATA ENTRY - RECEIVED'!E:E,"=Paper-bond w/letterhead, a4 size 70gsm") -> 0 | E15: =SUMIFS('DATA ENTRY - RELEASED'!C:C,'DATA ENTRY - RELEASED'!B:B,"=Paper-bond w/letterhead, a4 size 70gsm") -> 0 | F15: =Table26[[#This Row],[BEG BALANCE (QTY)]]+Table26[[#This Row],[TOTAL STOCKS RECEIVED (QTY)]]-Table26[[#This Row],[TOTAL STOCKS RELEASED (QTY)]] -> 0 | G15: =IFERROR(VLOOKUP(B15,SUPPLY2,3,0),"-") -> Ream | H15: =IFERROR(VLOOKUP(B15,SUPPLY2,4,0),"-") -> 1823 | I15: =IFERROR(VLOOKUP(A15,YEAR2023,2,0),"-") -> 0
A16: =TODAY() -> 46223 | B16: UBP QUICK CARDS - PENSION LOAN | C16: 450 | D16: =SUMIFS('DATA ENTRY - RECEIVED'!F:F,'DATA ENTRY - RECEIVED'!E:E,"=UBP QUICK CARDS - PENSION LOAN") -> 0 | E16: =SUMIFS('DATA ENTRY - RELEASED'!C:C,'DATA ENTRY - RELEASED'!B:B,"=UBP QUICK CARDS - PENSION LOAN") -> 450 | F16: =Table26[[#This Row],[BEG BALANCE (QTY)]]+Table26[[#This Row],[TOTAL STOCKS RECEIVED (QTY)]]-Table26[[#This Row],[TOTAL STOCKS RELEASED (QTY)]] -> 0 | G16: =IFERROR(VLOOKUP(B16,SUPPLY2,3,0),"-") -> pc | H16: =IFERROR(VLOOKUP(B16,SUPPLY2,4,0),"-") -> UBP | I16: =IFERROR(VLOOKUP(A16,YEAR2023,2,0),"-") -> 0
A17: =TODAY() -> 46223 | B17: ACOP-PENSIONERS REPLY P1&2 | C17: 1 | D17: =SUMIFS('DATA ENTRY - RECEIVED'!F:F,'DATA ENTRY - RECEIVED'!E:E,"=ACOP-PENSIONERS REPLY P1&2") -> 0 | E17: =SUMIFS('DATA ENTRY - RELEASED'!C:C,'DATA ENTRY - RELEASED'!B:B,"=ACOP-PENSIONERS REPLY P1&2") -> 0 | F17: =Table26[[#This Row],[BEG BALANCE (QTY)]]+Table26[[#This Row],[TOTAL STOCKS RECEIVED (QTY)]]-Table26[[#This Row],[TOTAL STOCKS RELEASED (QTY)]] -> 1 | G17: =IFERROR(VLOOKUP(B17,SUPPLY2,3,0),"-") -> - | H17: =IFERROR(VLOOKUP(B17,SUPPLY2,4,0),"-") -> - | I17: =IFERROR(VLOOKUP(A17,YEAR2023,2,0),"-") -> 0
A18: =TODAY() -> 46223 | B18: DEATH CLAIM APPLICATION PAGE 1 | D18: =SUMIFS('DATA ENTRY - RECEIVED'!F:F,'DATA ENTRY - RECEIVED'!E:E,"=DEATH CLAIM APPLICATION PAGE 1") -> 0 | E18: =SUMIFS('DATA ENTRY - RELEASED'!C:C,'DATA ENTRY - RELEASED'!B:B,"=DEATH CLAIM APPLICATION PAGE 1") -> 0 | F18: =Table26[[#This Row],[BEG BALANCE (QTY)]]+Table26[[#This Row],[TOTAL STOCKS RECEIVED (QTY)]]-Table26[[#This Row],[TOTAL STOCKS RELEASED (QTY)]] -> 0 | G18: =IFERROR(VLOOKUP(B18,SUPPLY2,3,0),"-") -> - | H18: =IFERROR(VLOOKUP(B18,SUPPLY2,4,0),"-") -> - | I18: =IFERROR(VLOOKUP(A18,YEAR2023,2,0),"-") -> 0
A19: =TODAY() -> 46223 | B19: DEATH CLAIM APPLICATION PAGE 2 | D19: =SUMIFS('DATA ENTRY - RECEIVED'!F:F,'DATA ENTRY - RECEIVED'!E:E,"=DEATH CLAIM APPLICATION PAGE 2") -> 0 | E19: =SUMIFS('DATA ENTRY - RELEASED'!C:C,'DATA ENTRY - RELEASED'!B:B,"=DEATH CLAIM APPLICATION PAGE 2") -> 0 | F19: =Table26[[#This Row],[BEG BALANCE (QTY)]]+Table26[[#This Row],[TOTAL STOCKS RECEIVED (QTY)]]-Table26[[#This Row],[TOTAL STOCKS RELEASED (QTY)]] -> 0 | G19: =IFERROR(VLOOKUP(B19,SUPPLY2,3,0),"-") -> - | H19: =IFERROR(VLOOKUP(B19,SUPPLY2,4,0),"-") -> - | I19: =IFERROR(VLOOKUP(A19,YEAR2023,2,0),"-") -> 0
A20: =TODAY() -> 46223 | B20: MEMBER DATA CHANGE REQUEST PAGE 1&2 | C20: 185 | D20: =SUMIFS('DATA ENTRY - RECEIVED'!F:F,'DATA ENTRY - RECEIVED'!E:E,"=MEMBER DATA CHANGE REQUEST PAGE 1&2") -> 25 | E20: =SUMIFS('DATA ENTRY - RELEASED'!C:C,'DATA ENTRY - RELEASED'!B:B,"=MEMBER DATA CHANGE REQUEST PAGE 1&2") -> 8808 | F20: =Table26[[#This Row],[BEG BALANCE (QTY)]]+Table26[[#This Row],[TOTAL STOCKS RECEIVED (QTY)]]-Table26[[#This Row],[TOTAL STOCKS RELEASED (QTY)]] -> -8598 | I20: =IFERROR(VLOOKUP(A20,YEAR2023,2,0),"-") -> 0
A21: =TODAY() -> 46223 | B21: E4-PAGE 1-MEMBER DATA CHANGE PAGE 1 | C21: 50 | D21: =SUMIFS('DATA ENTRY - RECEIVED'!F:F,'DATA ENTRY - RECEIVED'!E:E,"=E4-PAGE 1-MEMBER DATA CHANGE PAGE 1") -> 0 | E21: =SUMIFS('DATA ENTRY - RELEASED'!C:C,'DATA ENTRY - RELEASED'!B:B,"=E4-PAGE 1-MEMBER DATA CHANGE PAGE 1") -> 140 | F21: =Table26[[#This Row],[BEG BALANCE (QTY)]]+Table26[[#This Row],[TOTAL STOCKS RECEIVED (QTY)]]-Table26[[#This Row],[TOTAL STOCKS RELEASED (QTY)]] -> -90 | G21: =IFERROR(VLOOKUP(B21,SUPPLY2,3,0),"-") -> - | H21: =IFERROR(VLOOKUP(B21,SUPPLY2,4,0),"-") -> - | I21: =IFERROR(VLOOKUP(A21,YEAR2023,2,0),"-") -> 0
A22: =TODAY() -> 46223 | B22: E4-PAGE 2-MEMBER DATA CHANGE PAGE 2 | C22: 1 | D22: =SUMIFS('DATA ENTRY - RECEIVED'!F:F,'DATA ENTRY - RECEIVED'!E:E,"=E4-PAGE 2-MEMBER DATA CHANGE PAGE 2") -> 0 | E22: =SUMIFS('DATA ENTRY - RELEASED'!C:C,'DATA ENTRY - RELEASED'!B:B,"=E4-PAGE 2-MEMBER DATA CHANGE PAGE 2") -> 0 | F22: =Table26[[#This Row],[BEG BALANCE (QTY)]]+Table26[[#This Row],[TOTAL STOCKS RECEIVED (QTY)]]-Table26[[#This Row],[TOTAL STOCKS RELEASED (QTY)]] -> 1 | G22: =IFERROR(VLOOKUP(B22,SUPPLY2,3,0),"-") -> - | H22: =IFERROR(VLOOKUP(B22,SUPPLY2,4,0),"-") -> - | I22: =IFERROR(VLOOKUP(A22,YEAR2023,2,0),"-") -> 0
A23: =TODAY() -> 46223 | B23: FUNERAL APPLICATION | C23: 0 | D23: 51 | E23: =SUMIFS('DATA ENTRY - RELEASED'!C:C,'DATA ENTRY - RELEASED'!B:B,"=FUNERAL APPLICATION") -> 1 | F23: =Table26[[#This Row],[BEG BALANCE (QTY)]]+Table26[[#This Row],[TOTAL STOCKS RECEIVED (QTY)]]-Table26[[#This Row],[TOTAL STOCKS RELEASED (QTY)]] -> 50 | G23: =IFERROR(VLOOKUP(B23,SUPPLY2,3,0),"-") -> Ream | H23: =IFERROR(VLOOKUP(B23,SUPPLY2,4,0),"-") -> 1544 | I23: =IFERROR(VLOOKUP(A23,YEAR2023,2,0),"-") -> 0
A24: =TODAY() -> 46223 | B24: L-501-SPECIMENT SIGNATURE CARD | D24: =SUMIFS('DATA ENTRY - RECEIVED'!F:F,'DATA ENTRY - RECEIVED'!E:E,"=L-501-SPECIMENT SIGNATURE CARD") -> 200 | E24: =SUMIFS('DATA ENTRY - RELEASED'!C:C,'DATA ENTRY - RELEASED'!B:B,"=L-501-SPECIMENT SIGNATURE CARD") -> 0 | F24: =Table26[[#This Row],[BEG BALANCE (QTY)]]+Table26[[#This Row],[TOTAL STOCKS RECEIVED (QTY)]]-Table26[[#This Row],[TOTAL STOCKS RELEASED (QTY)]] -> 200 | G24: =IFERROR(VLOOKUP(B24,SUPPLY2,3,0),"-") -> PCS | H24: =IFERROR(VLOOKUP(B24,SUPPLY2,4,0),"-") -> 222 | I24: =IFERROR(VLOOKUP(A24,YEAR2023,2,0),"-") -> 0
A25: =TODAY() -> 46223 | B25: MEMBER'S/CLAIMANT'S PHOTO SIGNATURE CARD | C25: 5 | D25: =SUMIFS('DATA ENTRY - RECEIVED'!F:F,'DATA ENTRY - RECEIVED'!E:E,"=MEMBER'S/CLAIMANT'S PHOTO SIGNATURE CARD") -> 19 | E25: =SUMIFS('DATA ENTRY - RELEASED'!C:C,'DATA ENTRY - RELEASED'!B:B,"=MEMBER'S/CLAIMANT'S PHOTO SIGNATURE CARD") -> 6 | F25: =Table26[[#This Row],[BEG BALANCE (QTY)]]+Table26[[#This Row],[TOTAL STOCKS RECEIVED (QTY)]]-Table26[[#This Row],[TOTAL STOCKS RELEASED (QTY)]] -> 18 | G25: =IFERROR(VLOOKUP(B25,SUPPLY2,3,0),"-") -> Ream | H25: =IFERROR(VLOOKUP(B25,SUPPLY2,4,0),"-") -> 1976 | I25: =IFERROR(VLOOKUP(A25,YEAR2023,2,0),"-") -> 0 | L25: 5
A26: =TODAY() -> 46223 | B26: PAYMENT SLIP-CONTRIBUTION 1 | C26: 250 | D26: =SUMIFS('DATA ENTRY - RECEIVED'!F:F,'DATA ENTRY - RECEIVED'!E:E,"=PAYMENT SLIP-CONTRIBUTION 1") -> 87 | E26: =SUMIFS('DATA ENTRY - RELEASED'!C:C,'DATA ENTRY - RELEASED'!B:B,"=PAYMENT SLIP-CONTRIBUTION 1") -> 8056 | F26: =Table26[[#This Row],[BEG BALANCE (QTY)]]+Table26[[#This Row],[TOTAL STOCKS RECEIVED (QTY)]]-Table26[[#This Row],[TOTAL STOCKS RELEASED (QTY)]] -> -7719 | G26: =IFERROR(VLOOKUP(B26,SUPPLY2,3,0),"-") -> Ream | H26: =IFERROR(VLOOKUP(B26,SUPPLY2,4,0),"-") -> 2521 | I26: =IFERROR(VLOOKUP(A26,YEAR2023,2,0),"-") -> 0
A27: =TODAY() -> 46223 | B27: PAYMENT SLIP-MEMBER LOAN | D27: =SUMIFS('DATA ENTRY - RECEIVED'!F:F,'DATA ENTRY - RECEIVED'!E:E,"=PAYMENT SLIP-MEMBER LOAN") -> 13 | E27: =SUMIFS('DATA ENTRY - RELEASED'!C:C,'DATA ENTRY - RELEASED'!B:B,"=PAYMENT SLIP-MEMBER LOAN") -> 1101 | F27: =Table26[[#This Row],[BEG BALANCE (QTY)]]+Table26[[#This Row],[TOTAL STOCKS RECEIVED (QTY)]]-Table26[[#This Row],[TOTAL STOCKS RELEASED (QTY)]] -> -1088 | G27: =IFERROR(VLOOKUP(B27,SUPPLY2,3,0),"-") -> Ream | H27: =IFERROR(VLOOKUP(B27,SUPPLY2,4,0),"-") -> 2576 | I27: =IFERROR(VLOOKUP(A27,YEAR2023,2,0),"-") -> 0
A28: =TODAY() -> 46223 | B28: R-6 Misc p.r, 25shts 07'13 (carbonless) | D28: =SUMIFS('DATA ENTRY - RECEIVED'!F:F,'DATA ENTRY - RECEIVED'!E:E,"=R-6 Misc p.r, 25shts 07'13 (carbonless)") -> 0 | E28: =SUMIFS('DATA ENTRY - RELEASED'!C:C,'DATA ENTRY - RELEASED'!B:B,"=R-6 Misc p.r, 25shts 07'13 (carbonless)") -> 0 | F28: =Table26[[#This Row],[BEG BALANCE (QTY)]]+Table26[[#This Row],[TOTAL STOCKS RECEIVED (QTY)]]-Table26[[#This Row],[TOTAL STOCKS RELEASED (QTY)]] -> 0 | G28: =IFERROR(VLOOKUP(B28,SUPPLY2,3,0),"-") -> Pad | H28: =IFERROR(VLOOKUP(B28,SUPPLY2,4,0),"-") -> 2399 | I28: =IFERROR(VLOOKUP(A28,YEAR2023,2,0),"-") -> 0
A29: =TODAY() -> 46223 | B29: REGISTRY RETURN RECEIPT CARD | D29: =SUMIFS('DATA ENTRY - RECEIVED'!F:F,'DATA ENTRY - RECEIVED'!E:E,"=REGISTRY RETURN RECEIPT CARD") -> 0 | E29: =SUMIFS('DATA ENTRY - RELEASED'!C:C,'DATA ENTRY - RELEASED'!B:B,"=REGISTRY RETURN RECEIPT CARD") -> 0 | F29: =Table26[[#This Row],[BEG BALANCE (QTY)]]+Table26[[#This Row],[TOTAL STOCKS RECEIVED (QTY)]]-Table26[[#This Row],[TOTAL STOCKS RELEASED (QTY)]] -> 0 | G29: =IFERROR(VLOOKUP(B29,SUPPLY2,3,0),"-") -> PCS | H29: =IFERROR(VLOOKUP(B29,SUPPLY2,4,0),"-") -> 199 | I29: =IFERROR(VLOOKUP(A29,YEAR2023,2,0),"-") -> 0
A30: =TODAY() -> 46223 | B30: Rel-9 rep 25sets/pad 4ply (carbonless) | D30: =SUMIFS('DATA ENTRY - RECEIVED'!F:F,'DATA ENTRY - RECEIVED'!E:E,"=Rel-9 rep 25sets/pad 4ply (carbonless)") -> 0 | E30: =SUMIFS('DATA ENTRY - RELEASED'!C:C,'DATA ENTRY - RELEASED'!B:B,"=Rel-9 rep 25sets/pad 4ply (carbonless)") -> 0 | F30: =Table26[[#This Row],[BEG BALANCE (QTY)]]+Table26[[#This Row],[TOTAL STOCKS RECEIVED (QTY)]]-Table26[[#This Row],[TOTAL STOCKS RELEASED (QTY)]] -> 0 | G30: =IFERROR(VLOOKUP(B30,SUPPLY2,3,0),"-") -> Pad | H30: =IFERROR(VLOOKUP(B30,SUPPLY2,4,0),"-") -> 2386 | I30: =IFERROR(VLOOKUP(A30,YEAR2023,2,0),"-") -> 0
A31: =TODAY() -> 46223 | B31: RETIREMENT P.1 | D31: 200 | E31: =SUMIFS('DATA ENTRY - RELEASED'!C:C,'DATA ENTRY - RELEASED'!B:B,"=RETIREMENT P.1") -> 11 | F31: =Table26[[#This Row],[BEG BALANCE (QTY)]]+Table26[[#This Row],[TOTAL STOCKS RECEIVED (QTY)]]-Table26[[#This Row],[TOTAL STOCKS RELEASED (QTY)]] -> 189 | G31: =IFERROR(VLOOKUP(B31,SUPPLY2,3,0),"-") -> Ream | H31: =IFERROR(VLOOKUP(B31,SUPPLY2,4,0),"-") -> 1939 | I31: =IFERROR(VLOOKUP(A31,YEAR2023,2,0),"-") -> 0
A32: =TODAY() -> 46223 | B32: RETIREMENT P.2 | D32: =SUMIFS('DATA ENTRY - RECEIVED'!F:F,'DATA ENTRY - RECEIVED'!E:E,"=RETIREMENT P.2") -> 0 | E32: =SUMIFS('DATA ENTRY - RELEASED'!C:C,'DATA ENTRY - RELEASED'!B:B,"=RETIREMENT P.2") -> 0 | F32: =Table26[[#This Row],[BEG BALANCE (QTY)]]+Table26[[#This Row],[TOTAL STOCKS RECEIVED (QTY)]]-Table26[[#This Row],[TOTAL STOCKS RELEASED (QTY)]] -> 0 | G32: =IFERROR(VLOOKUP(B32,SUPPLY2,3,0),"-") -> Ream | H32: =IFERROR(VLOOKUP(B32,SUPPLY2,4,0),"-") -> 1950 | I32: =IFERROR(VLOOKUP(A32,YEAR2023,2,0),"-") -> 0
A33: =TODAY() -> 46223 | B33: SINUMPAANG SALAYSAY (RF) | D33: 51 | E33: =SUMIFS('DATA ENTRY - RELEASED'!C:C,'DATA ENTRY - RELEASED'!B:B,"=SINUMPAANG SALAYSAY (RF)") -> 0 | F33: =Table26[[#This Row],[BEG BALANCE (QTY)]]+Table26[[#This Row],[TOTAL STOCKS RECEIVED (QTY)]]-Table26[[#This Row],[TOTAL STOCKS RELEASED (QTY)]] -> 51 | G33: =IFERROR(VLOOKUP(B33,SUPPLY2,3,0),"-") -> Ream | H33: =IFERROR(VLOOKUP(B33,SUPPLY2,4,0),"-") -> 217 | I33: =IFERROR(VLOOKUP(A33,YEAR2023,2,0),"-") -> 0
A34: =TODAY() -> 46223 | B34: Alcohol, ethyl, 68%-72% | D34: =SUMIFS('DATA ENTRY - RECEIVED'!F:F,'DATA ENTRY - RECEIVED'!E:E,"=Alcohol, ethyl, 68%-72%") -> 40 | E34: =SUMIFS('DATA ENTRY - RELEASED'!C:C,'DATA ENTRY - RELEASED'!B:B,"=Alcohol, ethyl, 68%-72%") -> 40 | F34: =Table26[[#This Row],[BEG BALANCE (QTY)]]+Table26[[#This Row],[TOTAL STOCKS RECEIVED (QTY)]]-Table26[[#This Row],[TOTAL STOCKS RELEASED (QTY)]] -> 0 | G34: =IFERROR(VLOOKUP(B34,SUPPLY2,3,0),"-") -> Gallon | H34: =IFERROR(VLOOKUP(B34,SUPPLY2,4,0),"-") -> 2617 | I34: =IFERROR(VLOOKUP(A34,YEAR2023,2,0),"-") -> 0
A35: =TODAY() -> 46223 | B35: Alcohol, ethyl, 68%-72% (500ml) | C35: 52 | D35: =SUMIFS('DATA ENTRY - RECEIVED'!F:F,'DATA ENTRY - RECEIVED'!E:E,"=Alcohol, ethyl, 68%-72% (500ml)") -> 115 | E35: =SUMIFS('DATA ENTRY - RELEASED'!C:C,'DATA ENTRY - RELEASED'!B:B,"=Alcohol, ethyl, 68%-72% (500ml)") -> 93 | F35: =Table26[[#This Row],[BEG BALANCE (QTY)]]+Table26[[#This Row],[TOTAL STOCKS RECEIVED (QTY)]]-Table26[[#This Row],[TOTAL STOCKS RELEASED (QTY)]] -> 74 | G35: =IFERROR(VLOOKUP(B35,SUPPLY2,3,0),"-") -> Bottle | H35: =IFERROR(VLOOKUP(B35,SUPPLY2,4,0),"-") -> 2618 | I35: =IFERROR(VLOOKUP(A35,YEAR2023,2,0),"-") -> 0 | L35: 85
A36: =TODAY() -> 46223 | B36: Ballpoint pen | C36: 307 | D36: =SUMIFS('DATA ENTRY - RECEIVED'!F:F,'DATA ENTRY - RECEIVED'!E:E,"=Ballpoint pen") -> 743 | E36: =SUMIFS('DATA ENTRY - RELEASED'!C:C,'DATA ENTRY - RELEASED'!B:B,"=Ballpoint pen") -> 125 | F36: =Table26[[#This Row],[BEG BALANCE (QTY)]]+Table26[[#This Row],[TOTAL STOCKS RECEIVED (QTY)]]-Table26[[#This Row],[TOTAL STOCKS RELEASED (QTY)]] -> 925 | G36: =IFERROR(VLOOKUP(B36,SUPPLY2,3,0),"-") -> Piece | H36: =IFERROR(VLOOKUP(B36,SUPPLY2,4,0),"-") -> 337 | I36: =IFERROR(VLOOKUP(A36,YEAR2023,2,0),"-") -> 0 | L36: 400
A37: =TODAY() -> 46223 | B37: Binder clip 1 1/4” | D37: =SUMIFS('DATA ENTRY - RECEIVED'!F:F,'DATA ENTRY - RECEIVED'!E:E,"=Binder clip 1 1/4”") -> 0 | E37: =SUMIFS('DATA ENTRY - RELEASED'!C:C,'DATA ENTRY - RELEASED'!B:B,"=Binder clip 1 1/4”") -> 0 | F37: =Table26[[#This Row],[BEG BALANCE (QTY)]]+Table26[[#This Row],[TOTAL STOCKS RECEIVED (QTY)]]-Table26[[#This Row],[TOTAL STOCKS RELEASED (QTY)]] -> 0 | G37: =IFERROR(VLOOKUP(B37,SUPPLY2,3,0),"-") -> Box | H37: =IFERROR(VLOOKUP(B37,SUPPLY2,4,0),"-") -> 2551 | I37: =IFERROR(VLOOKUP(A37,YEAR2023,2,0),"-") -> 0
A38: =TODAY() -> 46223 | B38: Binder clip 1” | D38: =SUMIFS('DATA ENTRY - RECEIVED'!F:F,'DATA ENTRY - RECEIVED'!E:E,"=Binder clip 1”") -> 82 | E38: =SUMIFS('DATA ENTRY - RELEASED'!C:C,'DATA ENTRY - RELEASED'!B:B,"=Binder clip 1”") -> 0 | F38: =Table26[[#This Row],[BEG BALANCE (QTY)]]+Table26[[#This Row],[TOTAL STOCKS RECEIVED (QTY)]]-Table26[[#This Row],[TOTAL STOCKS RELEASED (QTY)]] -> 82 | G38: =IFERROR(VLOOKUP(B38,SUPPLY2,3,0),"-") -> Box | H38: =IFERROR(VLOOKUP(B38,SUPPLY2,4,0),"-") -> 2550 | I38: =IFERROR(VLOOKUP(A38,YEAR2023,2,0),"-") -> 0
A39: =TODAY() -> 46223 | B39: Binder clip 2” | D39: =SUMIFS('DATA ENTRY - RECEIVED'!F:F,'DATA ENTRY - RECEIVED'!E:E,"=Binder clip 2”") -> 5 | E39: =SUMIFS('DATA ENTRY - RELEASED'!C:C,'DATA ENTRY - RELEASED'!B:B,"=Binder clip 2”") -> 0 | F39: =Table26[[#This Row],[BEG BALANCE (QTY)]]+Table26[[#This Row],[TOTAL STOCKS RECEIVED (QTY)]]-Table26[[#This Row],[TOTAL STOCKS RELEASED (QTY)]] -> 5 | G39: =IFERROR(VLOOKUP(B39,SUPPLY2,3,0),"-") -> Box | H39: =IFERROR(VLOOKUP(B39,SUPPLY2,4,0),"-") -> 2552 | I39: =IFERROR(VLOOKUP(A39,YEAR2023,2,0),"-") -> 0
A40: =TODAY() -> 46223 | B40: Binder clip 3/4” | D40: =SUMIFS('DATA ENTRY - RECEIVED'!F:F,'DATA ENTRY - RECEIVED'!E:E,"=Binder clip 3/4”") -> 0 | E40: =SUMIFS('DATA ENTRY - RELEASED'!C:C,'DATA ENTRY - RELEASED'!B:B,"=Binder clip 3/4”") -> 0 | F40: =Table26[[#This Row],[BEG BALANCE (QTY)]]+Table26[[#This Row],[TOTAL STOCKS RECEIVED (QTY)]]-Table26[[#This Row],[TOTAL STOCKS RELEASED (QTY)]] -> 0 | G40: =IFERROR(VLOOKUP(B40,SUPPLY2,3,0),"-") -> Box | H40: =IFERROR(VLOOKUP(B40,SUPPLY2,4,0),"-") -> 2546 | I40: =IFERROR(VLOOKUP(A40,YEAR2023,2,0),"-") -> 0
A41: =TODAY() -> 46223 | B41: Correction tape | D41: =SUMIFS('DATA ENTRY - RECEIVED'!F:F,'DATA ENTRY - RECEIVED'!E:E,"=Correction tape") -> 22 | E41: =SUMIFS('DATA ENTRY - RELEASED'!C:C,'DATA ENTRY - RELEASED'!B:B,"=Correction tape") -> 0 | F41: =Table26[[#This Row],[BEG BALANCE (QTY)]]+Table26[[#This Row],[TOTAL STOCKS RECEIVED (QTY)]]-Table26[[#This Row],[TOTAL STOCKS RELEASED (QTY)]] -> 22 | G41: =IFERROR(VLOOKUP(B41,SUPPLY2,3,0),"-") -> Piece | H41: =IFERROR(VLOOKUP(B41,SUPPLY2,4,0),"-") -> 1960 | I41: =IFERROR(VLOOKUP(A41,YEAR2023,2,0),"-") -> 0
A42: =TODAY() -> 46223 | B42: Corrugated box | C42: 42 | D42: =SUMIFS('DATA ENTRY - RECEIVED'!F:F,'DATA ENTRY - RECEIVED'!E:E,"=Corrugated box") -> 0 | E42: =SUMIFS('DATA ENTRY - RELEASED'!C:C,'DATA ENTRY - RELEASED'!B:B,"=Corrugated box") -> 7 | F42: =Table26[[#This Row],[BEG BALANCE (QTY)]]+Table26[[#This Row],[TOTAL STOCKS RECEIVED (QTY)]]-Table26[[#This Row],[TOTAL STOCKS RELEASED (QTY)]] -> 35 | G42: =IFERROR(VLOOKUP(B42,SUPPLY2,3,0),"-") -> Set | H42: =IFERROR(VLOOKUP(B42,SUPPLY2,4,0),"-") -> 313 | I42: =IFERROR(VLOOKUP(A42,YEAR2023,2,0),"-") -> 0 | L42: 42
A43: =TODAY() -> 46223 | B43: File Organizer | D43: =SUMIFS('DATA ENTRY - RECEIVED'!F:F,'DATA ENTRY - RECEIVED'!E:E,"=File Organizer") -> 0 | E43: =SUMIFS('DATA ENTRY - RELEASED'!C:C,'DATA ENTRY - RELEASED'!B:B,"=File Organizer") -> 0 | F43: =Table26[[#This Row],[BEG BALANCE (QTY)]]+Table26[[#This Row],[TOTAL STOCKS RECEIVED (QTY)]]-Table26[[#This Row],[TOTAL STOCKS RELEASED (QTY)]] -> 0 | G43: =IFERROR(VLOOKUP(B43,SUPPLY2,3,0),"-") -> Piece | H43: =IFERROR(VLOOKUP(B43,SUPPLY2,4,0),"-") -> 2631 | I43: =IFERROR(VLOOKUP(A43,YEAR2023,2,0),"-") -> 0
A44: =TODAY() -> 46223 | B44: Empty cartons | D44: =SUMIFS('DATA ENTRY - RECEIVED'!F:F,'DATA ENTRY - RECEIVED'!E:E,"=Empty cartons") -> 0 | E44: =SUMIFS('DATA ENTRY - RELEASED'!C:C,'DATA ENTRY - RELEASED'!B:B,"=Empty cartons") -> 13 | F44: =Table26[[#This Row],[BEG BALANCE (QTY)]]+Table26[[#This Row],[TOTAL STOCKS RECEIVED (QTY)]]-Table26[[#This Row],[TOTAL STOCKS RELEASED (QTY)]] -> -13 | G44: =IFERROR(VLOOKUP(B44,SUPPLY2,3,0),"-") -> Piece | H44: =IFERROR(VLOOKUP(B44,SUPPLY2,4,0),"-") -> 312 | I44: =IFERROR(VLOOKUP(A44,YEAR2023,2,0),"-") -> 0
A45: =TODAY() -> 46223 | B45: Flag 3 x 6 | D45: =SUMIFS('DATA ENTRY - RECEIVED'!F:F,'DATA ENTRY - RECEIVED'!E:E,"=Flag 3 x 6") -> 0 | E45: =SUMIFS('DATA ENTRY - RELEASED'!C:C,'DATA ENTRY - RELEASED'!B:B,"=Flag 3 x 6") -> 0 | F45: =Table26[[#This Row],[BEG BALANCE (QTY)]]+Table26[[#This Row],[TOTAL STOCKS RECEIVED (QTY)]]-Table26[[#This Row],[TOTAL STOCKS RELEASED (QTY)]] -> 0 | G45: =IFERROR(VLOOKUP(B45,SUPPLY2,3,0),"-") -> Piece | H45: =IFERROR(VLOOKUP(B45,SUPPLY2,4,0),"-") -> 2536 | I45: =IFERROR(VLOOKUP(A45,YEAR2023,2,0),"-") -> 0
A46: =TODAY() -> 46223 | B46: Ink - stamp pad, violet | D46: =SUMIFS('DATA ENTRY - RECEIVED'!F:F,'DATA ENTRY - RECEIVED'!E:E,"=Ink - stamp pad, violet") -> 0 | E46: =SUMIFS('DATA ENTRY - RELEASED'!C:C,'DATA ENTRY - RELEASED'!B:B,"=Ink - stamp pad, violet") -> 0 | F46: =Table26[[#This Row],[BEG BALANCE (QTY)]]+Table26[[#This Row],[TOTAL STOCKS RECEIVED (QTY)]]-Table26[[#This Row],[TOTAL STOCKS RELEASED (QTY)]] -> 0 | G46: =IFERROR(VLOOKUP(B46,SUPPLY2,3,0),"-") -> Bottle | H46: =IFERROR(VLOOKUP(B46,SUPPLY2,4,0),"-") -> 293 | I46: =IFERROR(VLOOKUP(A46,YEAR2023,2,0),"-") -> 0
A47: =TODAY() -> 46223 | B47: Ink for trodat dater, black 28ml/bottle | D47: =SUMIFS('DATA ENTRY - RECEIVED'!F:F,'DATA ENTRY - RECEIVED'!E:E,"=Ink for trodat dater, black 28ml/bottle") -> 0 | E47: =SUMIFS('DATA ENTRY - RELEASED'!C:C,'DATA ENTRY - RELEASED'!B:B,"=Ink for trodat dater, black 28ml/bottle") -> 0 | F47: =Table26[[#This Row],[BEG BALANCE (QTY)]]+Table26[[#This Row],[TOTAL STOCKS RECEIVED (QTY)]]-Table26[[#This Row],[TOTAL STOCKS RELEASED (QTY)]] -> 0 | G47: =IFERROR(VLOOKUP(B47,SUPPLY2,3,0),"-") -> Bottle | H47: =IFERROR(VLOOKUP(B47,SUPPLY2,4,0),"-") -> 2340 | I47: =IFERROR(VLOOKUP(A47,YEAR2023,2,0),"-") -> 0
A48: =TODAY() -> 46223 | B48: Ink stamp pad, black | D48: =SUMIFS('DATA ENTRY - RECEIVED'!F:F,'DATA ENTRY - RECEIVED'!E:E,"=Ink stamp pad, black") -> 0 | E48: =SUMIFS('DATA ENTRY - RELEASED'!C:C,'DATA ENTRY - RELEASED'!B:B,"=Ink stamp pad, black") -> 1 | F48: =Table26[[#This Row],[BEG BALANCE (QTY)]]+Table26[[#This Row],[TOTAL STOCKS RECEIVED (QTY)]]-Table26[[#This Row],[TOTAL STOCKS RELEASED (QTY)]] -> -1 | G48: =IFERROR(VLOOKUP(B48,SUPPLY2,3,0),"-") -> Piece | H48: =IFERROR(VLOOKUP(B48,SUPPLY2,4,0),"-") -> 2136 | I48: =IFERROR(VLOOKUP(A48,YEAR2023,2,0),"-") -> 0
A49: =TODAY() -> 46223 | B49: Marking pen | D49: =SUMIFS('DATA ENTRY - RECEIVED'!F:F,'DATA ENTRY - RECEIVED'!E:E,"=Marking pen") -> 23 | E49: =SUMIFS('DATA ENTRY - RELEASED'!C:C,'DATA ENTRY - RELEASED'!B:B,"=Marking pen") -> 0 | F49: =Table26[[#This Row],[BEG BALANCE (QTY)]]+Table26[[#This Row],[TOTAL STOCKS RECEIVED (QTY)]]-Table26[[#This Row],[TOTAL STOCKS RELEASED (QTY)]] -> 23 | G49: =IFERROR(VLOOKUP(B49,SUPPLY2,3,0),"-") -> Piece | H49: =IFERROR(VLOOKUP(B49,SUPPLY2,4,0),"-") -> 338 | I49: =IFERROR(VLOOKUP(A49,YEAR2023,2,0),"-") -> 0
A50: =TODAY() -> 46223 | B50: Marking pen - whiteboard | D50: =SUMIFS('DATA ENTRY - RECEIVED'!F:F,'DATA ENTRY - RECEIVED'!E:E,"=Marking pen - whiteboard") -> 0 | E50: =SUMIFS('DATA ENTRY - RELEASED'!C:C,'DATA ENTRY - RELEASED'!B:B,"=Marking pen - whiteboard") -> 0 | F50: =Table26[[#This Row],[BEG BALANCE (QTY)]]+Table26[[#This Row],[TOTAL STOCKS RECEIVED (QTY)]]-Table26[[#This Row],[TOTAL STOCKS RELEASED (QTY)]] -> 0 | G50: =IFERROR(VLOOKUP(B50,SUPPLY2,3,0),"-") -> Piece | H50: =IFERROR(VLOOKUP(B50,SUPPLY2,4,0),"-") -> 345 | I50: =IFERROR(VLOOKUP(A50,YEAR2023,2,0),"-") -> 0
A51: =TODAY() -> 46223 | B51: Packaging tape 2” | D51: =SUMIFS('DATA ENTRY - RECEIVED'!F:F,'DATA ENTRY - RECEIVED'!E:E,"=Packaging tape 2”") -> 41 | E51: =SUMIFS('DATA ENTRY - RELEASED'!C:C,'DATA ENTRY - RELEASED'!B:B,"=Packaging tape 2”") -> 32 | F51: =Table26[[#This Row],[BEG BALANCE (QTY)]]+Table26[[#This Row],[TOTAL STOCKS RECEIVED (QTY)]]-Table26[[#This Row],[TOTAL STOCKS RELEASED (QTY)]] -> 9 | G51: =IFERROR(VLOOKUP(B51,SUPPLY2,3,0),"-") -> Roll | H51: =IFERROR(VLOOKUP(B51,SUPPLY2,4,0),"-") -> 2537 | I51: =IFERROR(VLOOKUP(A51,YEAR2023,2,0),"-") -> 0 | L51: 10
A52: =TODAY() -> 46223 | B52: Paper – tissue | C52: 234 | D52: 22 | E52: =SUMIFS('DATA ENTRY - RELEASED'!C:C,'DATA ENTRY - RELEASED'!B:B,"=Paper – tissue") -> 180 | F52: =Table26[[#This Row],[BEG BALANCE (QTY)]]+Table26[[#This Row],[TOTAL STOCKS RECEIVED (QTY)]]-Table26[[#This Row],[TOTAL STOCKS RELEASED (QTY)]] -> 76 | G52: =IFERROR(VLOOKUP(B52,SUPPLY2,3,0),"-") -> Roll | H52: =IFERROR(VLOOKUP(B52,SUPPLY2,4,0),"-") -> 281 | I52: =IFERROR(VLOOKUP(A52,YEAR2023,2,0),"-") -> 0 | L52: 116
A53: =TODAY() -> 46223 | B53: Paper clip big | C53: 13 | D53: =SUMIFS('DATA ENTRY - RECEIVED'!F:F,'DATA ENTRY - RECEIVED'!E:E,"=Paper clip big") -> 0 | E53: =SUMIFS('DATA ENTRY - RELEASED'!C:C,'DATA ENTRY - RELEASED'!B:B,"=Paper clip big") -> 0 | F53: =Table26[[#This Row],[BEG BALANCE (QTY)]]+Table26[[#This Row],[TOTAL STOCKS RECEIVED (QTY)]]-Table26[[#This Row],[TOTAL STOCKS RELEASED (QTY)]] -> 13 | G53: =IFERROR(VLOOKUP(B53,SUPPLY2,3,0),"-") -> Box | H53: =IFERROR(VLOOKUP(B53,SUPPLY2,4,0),"-") -> 2538 | I53: =IFERROR(VLOOKUP(A53,YEAR2023,2,0),"-") -> 0
A54: =TODAY() -> 46223 | B54: Paper clip, 100 pcs | C54: 8 | D54: =SUMIFS('DATA ENTRY - RECEIVED'!F:F,'DATA ENTRY - RECEIVED'!E:E,"=Paper clip, 100 pcs") -> 5 | E54: =SUMIFS('DATA ENTRY - RELEASED'!C:C,'DATA ENTRY - RELEASED'!B:B,"=Paper clip, 100 pcs") -> 0 | F54: =Table26[[#This Row],[BEG BALANCE (QTY)]]+Table26[[#This Row],[TOTAL STOCKS RECEIVED (QTY)]]-Table26[[#This Row],[TOTAL STOCKS RELEASED (QTY)]] -> 13 | G54: =IFERROR(VLOOKUP(B54,SUPPLY2,3,0),"-") -> Box | H54: =IFERROR(VLOOKUP(B54,SUPPLY2,4,0),"-") -> 306 | I54: =IFERROR(VLOOKUP(A54,YEAR2023,2,0),"-") -> 0 | L54: 13
A55: =TODAY() -> 46223 | B55: Paper fastener, 50 pcs | C55: 7 | D55: =SUMIFS('DATA ENTRY - RECEIVED'!F:F,'DATA ENTRY - RECEIVED'!E:E,"=Paper fastener, 50 pcs") -> 0 | E55: =SUMIFS('DATA ENTRY - RELEASED'!C:C,'DATA ENTRY - RELEASED'!B:B,"=Paper fastener, 50 pcs") -> 0 | F55: =Table26[[#This Row],[BEG BALANCE (QTY)]]+Table26[[#This Row],[TOTAL STOCKS RECEIVED (QTY)]]-Table26[[#This Row],[TOTAL STOCKS RELEASED (QTY)]] -> 7 | G55: =IFERROR(VLOOKUP(B55,SUPPLY2,3,0),"-") -> Box | H55: =IFERROR(VLOOKUP(B55,SUPPLY2,4,0),"-") -> 305 | I55: =IFERROR(VLOOKUP(A55,YEAR2023,2,0),"-") -> 0 | L55: 7
A56: =TODAY() -> 46223 | B56: Paste - solid w/ waterwell and applicator | D56: =SUMIFS('DATA ENTRY - RECEIVED'!F:F,'DATA ENTRY - RECEIVED'!E:E,"=Paste - solid w/ waterwell and applicator") -> 81 | E56: =SUMIFS('DATA ENTRY - RELEASED'!C:C,'DATA ENTRY - RELEASED'!B:B,"=Paste - solid w/ waterwell and applicator") -> 0 | F56: =Table26[[#This Row],[BEG BALANCE (QTY)]]+Table26[[#This Row],[TOTAL STOCKS RECEIVED (QTY)]]-Table26[[#This Row],[TOTAL STOCKS RELEASED (QTY)]] -> 81 | G56: =IFERROR(VLOOKUP(B56,SUPPLY2,3,0),"-") -> Piece | H56: =IFERROR(VLOOKUP(B56,SUPPLY2,4,0),"-") -> 336 | I56: =IFERROR(VLOOKUP(A56,YEAR2023,2,0),"-") -> 0
A57: =TODAY() -> 46223 | B57: Plastic envelope, 10 x 15 gauge no. 5 | D57: =SUMIFS('DATA ENTRY - RECEIVED'!F:F,'DATA ENTRY - RECEIVED'!E:E,"=Plastic envelope, 10 x 15 gauge no. 5") -> 0 | E57: =SUMIFS('DATA ENTRY - RELEASED'!C:C,'DATA ENTRY - RELEASED'!B:B,"=Plastic envelope, 10 x 15 gauge no. 5") -> 0 | F57: =Table26[[#This Row],[BEG BALANCE (QTY)]]+Table26[[#This Row],[TOTAL STOCKS RECEIVED (QTY)]]-Table26[[#This Row],[TOTAL STOCKS RELEASED (QTY)]] -> 0 | G57: =IFERROR(VLOOKUP(B57,SUPPLY2,3,0),"-") -> Piece | H57: =IFERROR(VLOOKUP(B57,SUPPLY2,4,0),"-") -> 1972 | I57: =IFERROR(VLOOKUP(A57,YEAR2023,2,0),"-") -> 0
A58: =TODAY() -> 46223 | B58: Rag - camiseta | D58: =SUMIFS('DATA ENTRY - RECEIVED'!F:F,'DATA ENTRY - RECEIVED'!E:E,"=Rag - camiseta") -> 0 | E58: =SUMIFS('DATA ENTRY - RELEASED'!C:C,'DATA ENTRY - RELEASED'!B:B,"=Rag - camiseta") -> 0 | F58: =Table26[[#This Row],[BEG BALANCE (QTY)]]+Table26[[#This Row],[TOTAL STOCKS RECEIVED (QTY)]]-Table26[[#This Row],[TOTAL STOCKS RELEASED (QTY)]] -> 0 | G58: =IFERROR(VLOOKUP(B58,SUPPLY2,3,0),"-") -> Kilo | H58: =IFERROR(VLOOKUP(B58,SUPPLY2,4,0),"-") -> 309 | I58: =IFERROR(VLOOKUP(A58,YEAR2023,2,0),"-") -> 0
A59: =TODAY() -> 46223 | B59: Record book, 300 pages | D59: =SUMIFS('DATA ENTRY - RECEIVED'!F:F,'DATA ENTRY - RECEIVED'!E:E,"=Record book, 300 pages") -> 0 | E59: =SUMIFS('DATA ENTRY - RELEASED'!C:C,'DATA ENTRY - RELEASED'!B:B,"=Record book, 300 pages") -> 0 | F59: =Table26[[#This Row],[BEG BALANCE (QTY)]]+Table26[[#This Row],[TOTAL STOCKS RECEIVED (QTY)]]-Table26[[#This Row],[TOTAL STOCKS RELEASED (QTY)]] -> 0 | G59: =IFERROR(VLOOKUP(B59,SUPPLY2,3,0),"-") -> Piece | H59: =IFERROR(VLOOKUP(B59,SUPPLY2,4,0),"-") -> 333 | I59: =IFERROR(VLOOKUP(A59,YEAR2023,2,0),"-") -> 0
A60: =TODAY() -> 46223 | B60: Rubber band - multicolor, 450 grams | D60: =SUMIFS('DATA ENTRY - RECEIVED'!F:F,'DATA ENTRY - RECEIVED'!E:E,"=Rubber band - multicolor, 450 grams") -> 5 | E60: =SUMIFS('DATA ENTRY - RELEASED'!C:C,'DATA ENTRY - RELEASED'!B:B,"=Rubber band - multicolor, 450 grams") -> 0 | F60: =Table26[[#This Row],[BEG BALANCE (QTY)]]+Table26[[#This Row],[TOTAL STOCKS RECEIVED (QTY)]]-Table26[[#This Row],[TOTAL STOCKS RELEASED (QTY)]] -> 5 | G60: =IFERROR(VLOOKUP(B60,SUPPLY2,3,0),"-") -> Box | H60: =IFERROR(VLOOKUP(B60,SUPPLY2,4,0),"-") -> 307 | I60: =IFERROR(VLOOKUP(A60,YEAR2023,2,0),"-") -> 0
A61: =TODAY() -> 46223 | B61: Rubber band - transparent 445 grams | D61: =SUMIFS('DATA ENTRY - RECEIVED'!F:F,'DATA ENTRY - RECEIVED'!E:E,"=Rubber band - transparent 445 grams") -> 5 | E61: =SUMIFS('DATA ENTRY - RELEASED'!C:C,'DATA ENTRY - RELEASED'!B:B,"=Rubber band - transparent 445 grams") -> 3 | F61: =Table26[[#This Row],[BEG BALANCE (QTY)]]+Table26[[#This Row],[TOTAL STOCKS RECEIVED (QTY)]]-Table26[[#This Row],[TOTAL STOCKS RELEASED (QTY)]] -> 2 | G61: =IFERROR(VLOOKUP(B61,SUPPLY2,3,0),"-") -> Bag | H61: =IFERROR(VLOOKUP(B61,SUPPLY2,4,0),"-") -> 308 | I61: =IFERROR(VLOOKUP(A61,YEAR2023,2,0),"-") -> 0
A62: =TODAY() -> 46223 | B62: Ruler - plastic | D62: =SUMIFS('DATA ENTRY - RECEIVED'!F:F,'DATA ENTRY - RECEIVED'!E:E,"=Ruler - plastic") -> 0 | E62: =SUMIFS('DATA ENTRY - RELEASED'!C:C,'DATA ENTRY - RELEASED'!B:B,"=Ruler - plastic") -> 0 | F62: =Table26[[#This Row],[BEG BALANCE (QTY)]]+Table26[[#This Row],[TOTAL STOCKS RECEIVED (QTY)]]-Table26[[#This Row],[TOTAL STOCKS RELEASED (QTY)]] -> 0 | G62: =IFERROR(VLOOKUP(B62,SUPPLY2,3,0),"-") -> Piece | H62: =IFERROR(VLOOKUP(B62,SUPPLY2,4,0),"-") -> 341 | I62: =IFERROR(VLOOKUP(A62,YEAR2023,2,0),"-") -> 0
A63: =TODAY() -> 46223 | B63: Sign pen | D63: =SUMIFS('DATA ENTRY - RECEIVED'!F:F,'DATA ENTRY - RECEIVED'!E:E,"=Sign pen") -> 2 | E63: =SUMIFS('DATA ENTRY - RELEASED'!C:C,'DATA ENTRY - RELEASED'!B:B,"=Sign pen") -> 0 | F63: =Table26[[#This Row],[BEG BALANCE (QTY)]]+Table26[[#This Row],[TOTAL STOCKS RECEIVED (QTY)]]-Table26[[#This Row],[TOTAL STOCKS RELEASED (QTY)]] -> 2 | G63: =IFERROR(VLOOKUP(B63,SUPPLY2,3,0),"-") -> Piece | H63: =IFERROR(VLOOKUP(B63,SUPPLY2,4,0),"-") -> 339 | I63: =IFERROR(VLOOKUP(A63,YEAR2023,2,0),"-") -> 0
A64: =TODAY() -> 46223 | B64: Stamp pad - big 3-7/16 x 5-5/8 | C64: 2 | D64: =SUMIFS('DATA ENTRY - RECEIVED'!F:F,'DATA ENTRY - RECEIVED'!E:E,"=Stamp pad - big 3-7/16 x 5-5/8") -> 0 | E64: =SUMIFS('DATA ENTRY - RELEASED'!C:C,'DATA ENTRY - RELEASED'!B:B,"=Stamp pad - big 3-7/16 x 5-5/8") -> 2 | F64: =Table26[[#This Row],[BEG BALANCE (QTY)]]+Table26[[#This Row],[TOTAL STOCKS RECEIVED (QTY)]]-Table26[[#This Row],[TOTAL STOCKS RELEASED (QTY)]] -> 0 | G64: =IFERROR(VLOOKUP(B64,SUPPLY2,3,0),"-") -> Piece | H64: =IFERROR(VLOOKUP(B64,SUPPLY2,4,0),"-") -> 342 | I64: =IFERROR(VLOOKUP(A64,YEAR2023,2,0),"-") -> 0
A65: =TODAY() -> 46223 | B65: Staple wire remover | D65: =SUMIFS('DATA ENTRY - RECEIVED'!F:F,'DATA ENTRY - RECEIVED'!E:E,"=Staple wire remover") -> 0 | E65: =SUMIFS('DATA ENTRY - RELEASED'!C:C,'DATA ENTRY - RELEASED'!B:B,"=Staple wire remover") -> 0 | F65: =Table26[[#This Row],[BEG BALANCE (QTY)]]+Table26[[#This Row],[TOTAL STOCKS RECEIVED (QTY)]]-Table26[[#This Row],[TOTAL STOCKS RELEASED (QTY)]] -> 0 | G65: =IFERROR(VLOOKUP(B65,SUPPLY2,3,0),"-") -> Piece | H65: =IFERROR(VLOOKUP(B65,SUPPLY2,4,0),"-") -> 343 | I65: =IFERROR(VLOOKUP(A65,YEAR2023,2,0),"-") -> 0
A66: =TODAY() -> 46223 | B66: Staple wire, 5000 pcs | C66: 24 | D66: =SUMIFS('DATA ENTRY - RECEIVED'!F:F,'DATA ENTRY - RECEIVED'!E:E,"=Staple wire, 5000 pcs") -> 359 | E66: =SUMIFS('DATA ENTRY - RELEASED'!C:C,'DATA ENTRY - RELEASED'!B:B,"=Staple wire, 5000 pcs") -> 313 | F66: =Table26[[#This Row],[BEG BALANCE (QTY)]]+Table26[[#This Row],[TOTAL STOCKS RECEIVED (QTY)]]-Table26[[#This Row],[TOTAL STOCKS RELEASED (QTY)]] -> 70 | G66: =IFERROR(VLOOKUP(B66,SUPPLY2,3,0),"-") -> Box | H66: =IFERROR(VLOOKUP(B66,SUPPLY2,4,0),"-") -> 310 | I66: =IFERROR(VLOOKUP(A66,YEAR2023,2,0),"-") -> 0 | L66: 25
A67: =TODAY() -> 46223 | B67: Steno notebook, 50 sheets per pad | D67: =SUMIFS('DATA ENTRY - RECEIVED'!F:F,'DATA ENTRY - RECEIVED'!E:E,"=Steno notebook, 50 sheets per pad") -> 0 | E67: =SUMIFS('DATA ENTRY - RELEASED'!C:C,'DATA ENTRY - RELEASED'!B:B,"=Steno notebook, 50 sheets per pad") -> 0 | F67: =Table26[[#This Row],[BEG BALANCE (QTY)]]+Table26[[#This Row],[TOTAL STOCKS RECEIVED (QTY)]]-Table26[[#This Row],[TOTAL STOCKS RELEASED (QTY)]] -> 0 | G67: =IFERROR(VLOOKUP(B67,SUPPLY2,3,0),"-") -> Piece | H67: =IFERROR(VLOOKUP(B67,SUPPLY2,4,0),"-") -> 334 | I67: =IFERROR(VLOOKUP(A67,YEAR2023,2,0),"-") -> 0
A68: =TODAY() -> 46223 | B68: Tape - masking 1 | D68: =SUMIFS('DATA ENTRY - RECEIVED'!F:F,'DATA ENTRY - RECEIVED'!E:E,"=Tape - masking 1") -> 60 | E68: =SUMIFS('DATA ENTRY - RELEASED'!C:C,'DATA ENTRY - RELEASED'!B:B,"=Tape - masking 1") -> 22 | F68: =Table26[[#This Row],[BEG BALANCE (QTY)]]+Table26[[#This Row],[TOTAL STOCKS RECEIVED (QTY)]]-Table26[[#This Row],[TOTAL STOCKS RELEASED (QTY)]] -> 38 | G68: =IFERROR(VLOOKUP(B68,SUPPLY2,3,0),"-") -> Roll | H68: =IFERROR(VLOOKUP(B68,SUPPLY2,4,0),"-") -> 300 | I68: =IFERROR(VLOOKUP(A68,YEAR2023,2,0),"-") -> 0 | L68: 15
A69: =TODAY() -> 46223 | B69: Tape - transparent 1 | D69: =SUMIFS('DATA ENTRY - RECEIVED'!F:F,'DATA ENTRY - RECEIVED'!E:E,"=Tape - transparent 1") -> 192 | E69: =SUMIFS('DATA ENTRY - RELEASED'!C:C,'DATA ENTRY - RELEASED'!B:B,"=Tape - transparent 1") -> 167 | F69: =Table26[[#This Row],[BEG BALANCE (QTY)]]+Table26[[#This Row],[TOTAL STOCKS RECEIVED (QTY)]]-Table26[[#This Row],[TOTAL STOCKS RELEASED (QTY)]] -> 25 | G69: =IFERROR(VLOOKUP(B69,SUPPLY2,3,0),"-") -> Roll | H69: =IFERROR(VLOOKUP(B69,SUPPLY2,4,0),"-") -> 301 | I69: =IFERROR(VLOOKUP(A69,YEAR2023,2,0),"-") -> 0 | L69: 5
A70: =TODAY() -> 46223 | B70: Twine - plastic | D70: =SUMIFS('DATA ENTRY - RECEIVED'!F:F,'DATA ENTRY - RECEIVED'!E:E,"=Twine - plastic") -> 0 | E70: =SUMIFS('DATA ENTRY - RELEASED'!C:C,'DATA ENTRY - RELEASED'!B:B,"=Twine - plastic") -> 0 | F70: =Table26[[#This Row],[BEG BALANCE (QTY)]]+Table26[[#This Row],[TOTAL STOCKS RECEIVED (QTY)]]-Table26[[#This Row],[TOTAL STOCKS RELEASED (QTY)]] -> 0 | G70: =IFERROR(VLOOKUP(B70,SUPPLY2,3,0),"-") -> Roll | H70: =IFERROR(VLOOKUP(B70,SUPPLY2,4,0),"-") -> 311 | I70: =IFERROR(VLOOKUP(A70,YEAR2023,2,0),"-") -> 0
A71: =TODAY() -> 46223 | B71: Waste basket | D71: =SUMIFS('DATA ENTRY - RECEIVED'!F:F,'DATA ENTRY - RECEIVED'!E:E,"=Waste basket") -> 0 | E71: =SUMIFS('DATA ENTRY - RELEASED'!C:C,'DATA ENTRY - RELEASED'!B:B,"=Waste basket") -> 0 | F71: =Table26[[#This Row],[BEG BALANCE (QTY)]]+Table26[[#This Row],[TOTAL STOCKS RECEIVED (QTY)]]-Table26[[#This Row],[TOTAL STOCKS RELEASED (QTY)]] -> 0 | G71: =IFERROR(VLOOKUP(B71,SUPPLY2,3,0),"-") -> Piece | H71: =IFERROR(VLOOKUP(B71,SUPPLY2,4,0),"-") -> 344 | I71: =IFERROR(VLOOKUP(A71,YEAR2023,2,0),"-") -> 0
A72: =TODAY() -> 46223 | B72: Drum for brother hl 5450 printer | D72: =SUMIFS('DATA ENTRY - RECEIVED'!F:F,'DATA ENTRY - RECEIVED'!E:E,"=Drum for brother hl 5450 printer") -> 0 | E72: =SUMIFS('DATA ENTRY - RELEASED'!C:C,'DATA ENTRY - RELEASED'!B:B,"=Drum for brother hl 5450 printer") -> 0 | F72: =Table26[[#This Row],[BEG BALANCE (QTY)]]+Table26[[#This Row],[TOTAL STOCKS RECEIVED (QTY)]]-Table26[[#This Row],[TOTAL STOCKS RELEASED (QTY)]] -> 0 | G72: =IFERROR(VLOOKUP(B72,SUPPLY2,3,0),"-") -> Piece | H72: =IFERROR(VLOOKUP(B72,SUPPLY2,4,0),"-") -> 2252 | I72: =IFERROR(VLOOKUP(A72,YEAR2023,2,0),"-") -> 0
A73: =TODAY() -> 46223 | B73: Kyocera laser printer tk- 5244, Cyan (new carried on stock) | D73: =SUMIFS('DATA ENTRY - RECEIVED'!F:F,'DATA ENTRY - RECEIVED'!E:E,"=Bond") -> 0 | E73: =SUMIFS('DATA ENTRY - RELEASED'!C:C,'DATA ENTRY - RELEASED'!B:B,"=Bond") -> 0 | F73: =Table26[[#This Row],[BEG BALANCE (QTY)]]+Table26[[#This Row],[TOTAL STOCKS RECEIVED (QTY)]]-Table26[[#This Row],[TOTAL STOCKS RELEASED (QTY)]] -> 0 | G73: =IFERROR(VLOOKUP(B73,SUPPLY2,3,0),"-") -> Unit | H73: =IFERROR(VLOOKUP(B73,SUPPLY2,4,0),"-") -> 2646 | I73: =IFERROR(VLOOKUP(A73,YEAR2023,2,0),"-") -> 0
A74: =TODAY() -> 46223 | B74: Kyocera laser printer tk- 5244, Black (new carried on stock) | D74: =SUMIFS('DATA ENTRY - RECEIVED'!F:F,'DATA ENTRY - RECEIVED'!E:E,"=Kyocera laser printer tk- 5244, Black (new carried on stock)") -> 0 | E74: =SUMIFS('DATA ENTRY - RELEASED'!C:C,'DATA ENTRY - RELEASED'!B:B,"=Kyocera laser printer tk- 5244, Black (new carried on stock)") -> 0 | F74: =Table26[[#This Row],[BEG BALANCE (QTY)]]+Table26[[#This Row],[TOTAL STOCKS RECEIVED (QTY)]]-Table26[[#This Row],[TOTAL STOCKS RELEASED (QTY)]] -> 0 | G74: =IFERROR(VLOOKUP(B74,SUPPLY2,3,0),"-") -> Unit | H74: =IFERROR(VLOOKUP(B74,SUPPLY2,4,0),"-") -> 2649 | I74: =IFERROR(VLOOKUP(A74,YEAR2023,2,0),"-") -> 0
A75: =TODAY() -> 46223 | B75: Kyocera laser printer tk- 5244, Magenta (new carried on stock) | D75: =SUMIFS('DATA ENTRY - RECEIVED'!F:F,'DATA ENTRY - RECEIVED'!E:E,"=Kyocera laser printer tk- 5244, Magenta (new carried on stock)") -> 0 | E75: =SUMIFS('DATA ENTRY - RELEASED'!C:C,'DATA ENTRY - RELEASED'!B:B,"=Kyocera laser printer tk- 5244, Magenta (new carried on stock)") -> 0 | F75: =Table26[[#This Row],[BEG BALANCE (QTY)]]+Table26[[#This Row],[TOTAL STOCKS RECEIVED (QTY)]]-Table26[[#This Row],[TOTAL STOCKS RELEASED (QTY)]] -> 0 | G75: =IFERROR(VLOOKUP(B75,SUPPLY2,3,0),"-") -> Unit | H75: =IFERROR(VLOOKUP(B75,SUPPLY2,4,0),"-") -> 2647 | I75: =IFERROR(VLOOKUP(A75,YEAR2023,2,0),"-") -> 0
A76: =TODAY() -> 46223 | B76: Kyocera laser printer tk- 5244, Yellow (new carried on stock) | D76: =SUMIFS('DATA ENTRY - RECEIVED'!F:F,'DATA ENTRY - RECEIVED'!E:E,"=Kyocera laser printer tk- 5244, Yellow (new carried on stock)") -> 0 | E76: =SUMIFS('DATA ENTRY - RELEASED'!C:C,'DATA ENTRY - RELEASED'!B:B,"=Kyocera laser printer tk- 5244, Yellow (new carried on stock)") -> 0 | F76: =Table26[[#This Row],[BEG BALANCE (QTY)]]+Table26[[#This Row],[TOTAL STOCKS RECEIVED (QTY)]]-Table26[[#This Row],[TOTAL STOCKS RELEASED (QTY)]] -> 0 | G76: =IFERROR(VLOOKUP(B76,SUPPLY2,3,0),"-") -> Unit | H76: =IFERROR(VLOOKUP(B76,SUPPLY2,4,0),"-") -> 2648 | I76: =IFERROR(VLOOKUP(A76,YEAR2023,2,0),"-") -> 0
A77: =TODAY() -> 46223 | B77: Lto ultrium 6, 6.25tb c/o dcod | D77: =SUMIFS('DATA ENTRY - RECEIVED'!F:F,'DATA ENTRY - RECEIVED'!E:E,"=Lto ultrium 6, 6.25tb c/o dcod") -> 0 | E77: =SUMIFS('DATA ENTRY - RELEASED'!C:C,'DATA ENTRY - RELEASED'!B:B,"=Lto ultrium 6, 6.25tb c/o dcod") -> 0 | F77: =Table26[[#This Row],[BEG BALANCE (QTY)]]+Table26[[#This Row],[TOTAL STOCKS RECEIVED (QTY)]]-Table26[[#This Row],[TOTAL STOCKS RELEASED (QTY)]] -> 0 | G77: =IFERROR(VLOOKUP(B77,SUPPLY2,3,0),"-") -> Unit | H77: =IFERROR(VLOOKUP(B77,SUPPLY2,4,0),"-") -> 2627 | I77: =IFERROR(VLOOKUP(A77,YEAR2023,2,0),"-") -> 0
A78: =TODAY() -> 46223 | B78: Lto ultrium 7, 7.15tb c/o dcod | D78: =SUMIFS('DATA ENTRY - RECEIVED'!F:F,'DATA ENTRY - RECEIVED'!E:E,"=Lto ultrium 7, 7.15tb c/o dcod") -> 0 | E78: =SUMIFS('DATA ENTRY - RELEASED'!C:C,'DATA ENTRY - RELEASED'!B:B,"=Lto ultrium 7, 7.15tb c/o dcod") -> 0 | F78: =Table26[[#This Row],[BEG BALANCE (QTY)]]+Table26[[#This Row],[TOTAL STOCKS RECEIVED (QTY)]]-Table26[[#This Row],[TOTAL STOCKS RELEASED (QTY)]] -> 0 | G78: =IFERROR(VLOOKUP(B78,SUPPLY2,3,0),"-") -> Unit | H78: =IFERROR(VLOOKUP(B78,SUPPLY2,4,0),"-") -> 2628 | I78: =IFERROR(VLOOKUP(A78,YEAR2023,2,0),"-") -> 0
A79: =TODAY() -> 46223 | B79: Ribbon – ERC-31 for TMU-950 (epson) | D79: =SUMIFS('DATA ENTRY - RECEIVED'!F:F,'DATA ENTRY - RECEIVED'!E:E,"=Ribbon – ERC-31 for TMU-950 (epson)") -> 14 | E79: =SUMIFS('DATA ENTRY - RELEASED'!C:C,'DATA ENTRY - RELEASED'!B:B,"=Ribbon – ERC-31 for TMU-950 (epson)") -> 1 | F79: =Table26[[#This Row],[BEG BALANCE (QTY)]]+Table26[[#This Row],[TOTAL STOCKS RECEIVED (QTY)]]-Table26[[#This Row],[TOTAL STOCKS RELEASED (QTY)]] -> 13 | G79: =IFERROR(VLOOKUP(B79,SUPPLY2,3,0),"-") -> Piece | H79: =IFERROR(VLOOKUP(B79,SUPPLY2,4,0),"-") -> 137 | I79: =IFERROR(VLOOKUP(A79,YEAR2023,2,0),"-") -> 0 | L79: 4
A80: =TODAY() -> 46223 | B80: Ribbon tally dascom 1330 99007 | D80: =SUMIFS('DATA ENTRY - RECEIVED'!F:F,'DATA ENTRY - RECEIVED'!E:E,"=Ribbon tally dascom 1330 99007") -> 0 | E80: =SUMIFS('DATA ENTRY - RELEASED'!C:C,'DATA ENTRY - RELEASED'!B:B,"=Ribbon tally dascom 1330 99007") -> 0 | F80: =Table26[[#This Row],[BEG BALANCE (QTY)]]+Table26[[#This Row],[TOTAL STOCKS RECEIVED (QTY)]]-Table26[[#This Row],[TOTAL STOCKS RELEASED (QTY)]] -> 0 | G80: =IFERROR(VLOOKUP(B80,SUPPLY2,3,0),"-") -> Piece | H80: =IFERROR(VLOOKUP(B80,SUPPLY2,4,0),"-") -> 2416 | I80: =IFERROR(VLOOKUP(A80,YEAR2023,2,0),"-") -> 0
A81: =TODAY() -> 46223 | B81: Thermal paper for set 80 x 30mm | D81: =SUMIFS('DATA ENTRY - RECEIVED'!F:F,'DATA ENTRY - RECEIVED'!E:E,"=Thermal paper for set 80 x 30mm") -> 300 | E81: =SUMIFS('DATA ENTRY - RELEASED'!C:C,'DATA ENTRY - RELEASED'!B:B,"=Thermal paper for set 80 x 30mm") -> 119 | F81: =Table26[[#This Row],[BEG BALANCE (QTY)]]+Table26[[#This Row],[TOTAL STOCKS RECEIVED (QTY)]]-Table26[[#This Row],[TOTAL STOCKS RELEASED (QTY)]] -> 181 | G81: =IFERROR(VLOOKUP(B81,SUPPLY2,3,0),"-") -> Roll | H81: =IFERROR(VLOOKUP(B81,SUPPLY2,4,0),"-") -> 2629 | I81: =IFERROR(VLOOKUP(A81,YEAR2023,2,0),"-") -> 0 | L81: 46
A82: =TODAY() -> 46223 | B82: Toner for Samsung M3820ND MLT-D203E (High Yield) | D82: =SUMIFS('DATA ENTRY - RECEIVED'!F:F,'DATA ENTRY - RECEIVED'!E:E,"=Toner for Samsung M3820ND MLT-D203E (High Yield)") -> 0 | E82: =SUMIFS('DATA ENTRY - RELEASED'!C:C,'DATA ENTRY - RELEASED'!B:B,"=Toner for Samsung M3820ND MLT-D203E (High Yield)") -> 1 | F82: =Table26[[#This Row],[BEG BALANCE (QTY)]]+Table26[[#This Row],[TOTAL STOCKS RECEIVED (QTY)]]-Table26[[#This Row],[TOTAL STOCKS RELEASED (QTY)]] -> -1 | G82: =IFERROR(VLOOKUP(B82,SUPPLY2,3,0),"-") -> Unit | H82: =IFERROR(VLOOKUP(B82,SUPPLY2,4,0),"-") -> 2388 | I82: =IFERROR(VLOOKUP(A82,YEAR2023,2,0),"-") -> 0
A83: =TODAY() -> 46223 | B83: Toner- for Canon LBP 6780X (Compatible) | D83: 2 | E83: =SUMIFS('DATA ENTRY - RELEASED'!C:C,'DATA ENTRY - RELEASED'!B:B,"=Toner- for Canon LBP 6780X (Compatible)") -> 0 | F83: =Table26[[#This Row],[BEG BALANCE (QTY)]]+Table26[[#This Row],[TOTAL STOCKS RECEIVED (QTY)]]-Table26[[#This Row],[TOTAL STOCKS RELEASED (QTY)]] -> 2 | G83: =IFERROR(VLOOKUP(B83,SUPPLY2,3,0),"-") -> Unit | H83: =IFERROR(VLOOKUP(B83,SUPPLY2,4,0),"-") -> 2540 | I83: =IFERROR(VLOOKUP(A83,YEAR2023,2,0),"-") -> 0
A84: =TODAY() -> 46223 | B84: TSF - 11x10-5/8 1 ply 2000 shts/box | D84: =SUMIFS('DATA ENTRY - RECEIVED'!F:F,'DATA ENTRY - RECEIVED'!E:E,"=TSF - 11x10-5/8 1 ply 2000 shts/box") -> 0 | E84: =SUMIFS('DATA ENTRY - RELEASED'!C:C,'DATA ENTRY - RELEASED'!B:B,"=TSF - 11x10-5/8 1 ply 2000 shts/box") -> 0 | F84: =Table26[[#This Row],[BEG BALANCE (QTY)]]+Table26[[#This Row],[TOTAL STOCKS RECEIVED (QTY)]]-Table26[[#This Row],[TOTAL STOCKS RELEASED (QTY)]] -> 0 | G84: =IFERROR(VLOOKUP(B84,SUPPLY2,3,0),"-") -> M | H84: =IFERROR(VLOOKUP(B84,SUPPLY2,4,0),"-") -> 84 | I84: =IFERROR(VLOOKUP(A84,YEAR2023,2,0),"-") -> 0
A85: =TODAY() -> 46223 | B85: TSF - 11x14-7/8 1 ply 2000 shts/box | D85: =SUMIFS('DATA ENTRY - RECEIVED'!F:F,'DATA ENTRY - RECEIVED'!E:E,"=TSF - 11x14-7/8 1 ply 2000 shts/box") -> 0 | E85: =SUMIFS('DATA ENTRY - RELEASED'!C:C,'DATA ENTRY - RELEASED'!B:B,"=TSF - 11x14-7/8 1 ply 2000 shts/box") -> 0 | F85: =Table26[[#This Row],[BEG BALANCE (QTY)]]+Table26[[#This Row],[TOTAL STOCKS RECEIVED (QTY)]]-Table26[[#This Row],[TOTAL STOCKS RELEASED (QTY)]] -> 0 | G85: =IFERROR(VLOOKUP(B85,SUPPLY2,3,0),"-") -> M | H85: =IFERROR(VLOOKUP(B85,SUPPLY2,4,0),"-") -> 87 | I85: =IFERROR(VLOOKUP(A85,YEAR2023,2,0),"-") -> 0
A86: =TODAY() -> 46223 | B86: TSF - 11x8-1/2 1 ply 2000 shts/box | D86: =SUMIFS('DATA ENTRY - RECEIVED'!F:F,'DATA ENTRY - RECEIVED'!E:E,"=TSF - 11x8-1/2 1 ply 2000 shts/box") -> 0 | E86: =SUMIFS('DATA ENTRY - RELEASED'!C:C,'DATA ENTRY - RELEASED'!B:B,"=TSF - 11x8-1/2 1 ply 2000 shts/box") -> 0 | F86: =Table26[[#This Row],[BEG BALANCE (QTY)]]+Table26[[#This Row],[TOTAL STOCKS RECEIVED (QTY)]]-Table26[[#This Row],[TOTAL STOCKS RELEASED (QTY)]] -> 0 | G86: =IFERROR(VLOOKUP(B86,SUPPLY2,3,0),"-") -> M | H86: =IFERROR(VLOOKUP(B86,SUPPLY2,4,0),"-") -> 81 | I86: =IFERROR(VLOOKUP(A86,YEAR2023,2,0),"-") -> 0

Sheet REQUISITION AND ISSUE SLIP
A1: REQUISITION AND ISSUE SLIP | J1: R.I.S. No.
A2: SSS Form S-101 (Revised 03/07) | H2: Fill up in 3 copies | J2: ILI-2022-010
A3: TO: PROPERTY DIVISION | D3: FROM: (Requisitioning Branch) | G3: DEPTCODE | J3: DATE
B4: PLEASE FURNISH US THE FOLLOWING SUPPLIES: | D4: ILIGAN BRANCH | G4: 121410014 | J4: 44852
B5: STOCK CODE | C5: DESCRIPTION | D5: BALANCE ON HAND | E5: UNIT OF MEASURE | G5: QUANTITY | I5: ISSUED BY | J5: UNIT COST | K5: TOTAL COST
G6: REGD | H6: ISSUED
A7: 1 | B7: =IFERROR(VLOOKUP(C7,SUPPLY2,4,0),"-") -> - | C7: Bookpaper/Offset - 8-1/2 x 13 | D7: 0 | E7: =IFERROR(VLOOKUP(C7,SUPPLY2,3,0),"-") -> - | G7: 60
A8: 2 | B8: =IFERROR(VLOOKUP(C8,SUPPLY2,4,0),"-") -> - | C8: Bookpaper/Offset – A4 | D8: 0 | E8: =IFERROR(VLOOKUP(C8,SUPPLY2,3,0),"-") -> - | G8: 100
A9: 3 | B9: =IFERROR(VLOOKUP(C9,SUPPLY2,4,0),"-") -> 330 | C9: Folder - Legal size, 36mm thick (14pts) | D9: 0 | E9: =IFERROR(VLOOKUP(C9,SUPPLY2,3,0),"-") -> C | G9: 400
A10: 4 | B10: =IFERROR(VLOOKUP(C10,SUPPLY2,4,0),"-") -> - | C10: Envelope - Wdw #10 Not Reg No Add Brwn | D10: 0 | E10: =IFERROR(VLOOKUP(C10,SUPPLY2,3,0),"-") -> - | G10: 200
E11: =IFERROR(VLOOKUP(C11,SUPPLY2,3,0),"-") -> -
E12: =IFERROR(VLOOKUP(C12,SUPPLY2,3,0),"-") -> -
E13: =IFERROR(VLOOKUP(C13,SUPPLY2,3,0),"-") -> -
E14: =IFERROR(VLOOKUP(C14,SUPPLY2,3,0),"-") -> -
E15: =IFERROR(VLOOKUP(C15,SUPPLY2,3,0),"-") -> -
B16: =IFERROR(VLOOKUP(C16,SUPPLY2,4,0),"-") -> - | D16: =IFERROR(VLOOKUP(B16,SUPPLY3,7,0),"-") -> - | E16: =IFERROR(VLOOKUP(C16,SUPPLY2,3,0),"-") -> -
A17: Signature of Requisitioning Department/Branch | G17: Approval:
A18: CHERYL V. JARIOL, M.D.
A19: Branch Head II
A20: Received the above supplies as issued: | D20: Date: | G20: Team Head, Warehouse

Sheet SUPPLIES SUMMARY
A1: Stock Code | B1: Material Description | C1: Unit of Measue | D1: Beginning Balance | E1: TOTAL IN STOCKS | F1: TOTAL OUT STOCKS | G1: Running Balance
A2: PAPER AND PAPER PRODUCTS | G2: x
A3: 27 | B3: Bookpaper/Offset - 8 1/2 x 11 | C3: ream | E3: =SUMIFS('DATA ENTRY - REQUEST'!#REF!,'DATA ENTRY - REQUEST'!E:E,"=Bookpaper/Offset - 8 1/2 x 11") -> #REF! | F3: =SUMIFS('DATA ENTRY - REQUEST'!#REF!,'DATA ENTRY - REQUEST'!E:E,"=Bookpaper/Offset - 8 1/2 x 11") -> #REF! | G3: =D3+E3-F3 -> #REF!
A4: 2067 | B4: Bookpaper/Offset - 8-1/2 x 13 | C4: ream | E4: =SUMIFS('DATA ENTRY - REQUEST'!#REF!,'DATA ENTRY - REQUEST'!E:E,"=Bookpaper/Offset - 8-1/2 x 13") -> #REF! | F4: =SUMIFS('DATA ENTRY - REQUEST'!#REF!,'DATA ENTRY - REQUEST'!E:E,"=Bookpaper/Offset - 8-1/2 x 13") -> #REF! | G4: =D4+E4-F4 -> #REF!
A5: 2376 | B5: Bookpaper/Offset – A4 | C5: ream | E5: =SUMIFS('DATA ENTRY - REQUEST'!#REF!,'DATA ENTRY - REQUEST'!E:E,"=Bookpaper/Offset – A4") -> #REF! | F5: =SUMIFS('DATA ENTRY - REQUEST'!#REF!,'DATA ENTRY - REQUEST'!E:E,"=Bookpaper/Offset – A4") -> #REF! | G5: =D5+E5-F5 -> #REF!
A6: 26 | B6: Paper – Carbon Legal Size | C6: box | G6: =D6+E6-F6 -> 0
A7: 37 | B7: Envelope - Wdw #10 Not Reg No Add Brwn | C7: pc | D7: 250 | E7: =SUMIFS('DATA ENTRY - REQUEST'!#REF!,'DATA ENTRY - REQUEST'!E:E,"=Envelope - Wdw #10 Not Reg No Add Brwn") -> #REF! | F7: =SUMIFS('DATA ENTRY - REQUEST'!#REF!,'DATA ENTRY - REQUEST'!E:E,"=Envelope - Wdw #10 Not Reg No Add Brwn") -> #REF! | G7: =D7+E7-F7 -> #REF!
A8: 40 | B8: Envelope - Window Reg Mailing Only White | C8: box | G8: =D8+E8-F8 -> 0
A9: 46 | B9: Envelope - Document, 10 x 15 | C9: C | E9: =SUMIFS('DATA ENTRY - REQUEST'!#REF!,'DATA ENTRY - REQUEST'!E:E,"=Envelope - Document, 10 x 15") -> #REF! | F9: =SUMIFS('DATA ENTRY - REQUEST'!#REF!,'DATA ENTRY - REQUEST'!E:E,"=Envelope - Document, 10 x 15") -> #REF! | G9: =D9+E9-F9 -> #REF!
A10: 49 | B10: Envelope - Exp,10x15x 2 w/out flap thick | C10: pc | G10: =D10+E10-F10 -> 0
A11: 330 | B11: Folder - Legal size, 36mm thick (14pts) | C11: C | E11: =SUMIFS('DATA ENTRY - REQUEST'!#REF!,'DATA ENTRY - REQUEST'!E:E,"=Folder - Legal size, 36mm thick (14pts)") -> #REF! | F11: =SUMIFS('DATA ENTRY - REQUEST'!#REF!,'DATA ENTRY - REQUEST'!E:E,"=Folder - Legal size, 36mm thick (14pts)") -> #REF! | G11: =D11+E11-F11 -> #REF!
A12: PRINTED FORMS | G12: x
A13: FOI | B13: FOI REQUEST FORM | C13: pc | E13: =SUMIFS('DATA ENTRY - REQUEST'!#REF!,'DATA ENTRY - REQUEST'!E:E,"=FOI REQUEST FORM") -> #REF! | F13: =SUMIFS('DATA ENTRY - REQUEST'!#REF!,'DATA ENTRY - REQUEST'!E:E,"=FOI REQUEST FORM") -> #REF! | G13: =D13+E13-F13 -> #REF!
A14: 181 | B14: Toner Laser Printer HP-P2015D Q-7553A | C14: pc | E14: =SUMIFS('DATA ENTRY - REQUEST'!#REF!,'DATA ENTRY - REQUEST'!E:E,"=Bookpaper/Offset – A4") -> #REF! | F14: =SUMIFS('DATA ENTRY - REQUEST'!#REF!,'DATA ENTRY - REQUEST'!E:E,"=Toner Laser Printer HP-P2015D Q-7553A") -> #REF! | G14: =D14+E14-F14 -> #REF!
A15: 2386 | B15: REL-9 - Real Estate Pymnt 25 shts 4 ply | C15: pad | E15: =SUMIFS('DATA ENTRY - REQUEST'!#REF!,'DATA ENTRY - REQUEST'!E:E,"=Bookpaper/Offset – A4") -> #REF! | F15: =SUMIFS('DATA ENTRY - REQUEST'!#REF!,'DATA ENTRY - REQUEST'!E:E,"=REL-9 - Real Estate Pymnt 25 shts 4 ply") -> #REF! | G15: =D15+E15-F15 -> #REF!
A16: 2399 | B16: R-6 - Misc Paymt Ret, 25 shts, 07/2013 | C16: pad | E16: =SUMIFS('DATA ENTRY - REQUEST'!#REF!,'DATA ENTRY - REQUEST'!E:E,"=Bookpaper/Offset – A4") -> #REF! | F16: =SUMIFS('DATA ENTRY - REQUEST'!#REF!,'DATA ENTRY - REQUEST'!E:E,"=R-6 - Misc Paymt Ret, 25 shts, 07/2013") -> #REF! | G16: =D16+E16-F16 -> #REF!
A17: 198 | B17: Daily time Records 14 pts.Tagboard | C17: pc | G17: =D17+E17-F17 -> 0
A18: 202 | B18: CS form No. 6, Leave Application | C18: ream | G18: =D18+E18-F18 -> 0
A19: 204 | B19: AD-528 - Permission to Leave the Office | C19: ream | E19: =SUMIFS('DATA ENTRY - REQUEST'!#REF!,'DATA ENTRY - REQUEST'!E:E,"=Bookpaper/Offset – A4") -> #REF! | F19: =SUMIFS('DATA ENTRY - REQUEST'!#REF!,'DATA ENTRY - REQUEST'!E:E,"=AD-528 - Permission to Leave the Office") -> #REF! | G19: =D19+E19-F19 -> #REF!
A20: 210 | B20: E-4 - Members Ammendment carbonless | C20: pad | G20: =D20+E20-F20 -> 0
A21: 2286 | B21: R-1 - ER' s Data Record | C21: ream | G21: =D21+E21-F21 -> 0
A22: 2287 | B22: R-1A - Report of EE Members | C22: ream | E22: =SUMIFS('DATA ENTRY - REQUEST'!#REF!,'DATA ENTRY - REQUEST'!E:E,"=R-1A - Report of EE Members") -> #REF! | F22: =SUMIFS('DATA ENTRY - REQUEST'!#REF!,'DATA ENTRY - REQUEST'!E:E,"=R-1A - Report of EE Members") -> #REF! | G22: =D22+E22-F22 -> #REF!
A23: 214 | B23: R3 Contribution Collection List | C23: ream | G23: =D23+E23-F23 -> 0
A24: 215 | B24: R-8 - ER's Data Ammendment Form | C24: ream | G24: =D24+E24-F24 -> 0
A25: 217 | B25: Sinumpaang Salaysay | C25: ream | G25: =D25+E25-F25 -> 0
A26: 218 | B26: OW-1 - Overseas Worker Records | C26: pad | G26: =D26+E26-F26 -> 0
A27: 222 | B27: L-501 - Specimen Signature Card | C27: pc | G27: =D27+E27-F27 -> 0
A28: 224 | B28: CLD 1.3A | C28: ream | E28: =SUMIFS('DATA ENTRY - REQUEST'!#REF!,'DATA ENTRY - REQUEST'!E:E,"=Bookpaper/Offset – A4") -> #REF! | F28: =SUMIFS('DATA ENTRY - REQUEST'!#REF!,'DATA ENTRY - REQUEST'!E:E,"=CLD 1.3A") -> #REF! | G28: =D28+E28-F28 -> #REF!
A29: 232 | B29: Guarantor's Form p1 | C29: ream | G29: =D29+E29-F29 -> 0
A30: 233 | B30: Guarantor's Form p2 | C30: ream | G30: =D30+E30-F30 -> 0
A31: 270 | B31: DDR-2 Pensioner's Data Change Request | C31: ream | G31: =D31+E31-F31 -> 0
A32: 2326 | B32: Revised ACOP P2 | C32: ream | G32: =D32+E32-F32 -> 0
A33: 276 | B33: Revised ACOP P1 | C33: ream | E33: =SUMIFS('DATA ENTRY - REQUEST'!#REF!,'DATA ENTRY - REQUEST'!E:E,"=Revised ACOP P1") -> #REF! | F33: =SUMIFS('DATA ENTRY - REQUEST'!#REF!,'DATA ENTRY - REQUEST'!E:E,"=Revised ACOP P1") -> #REF! | G33: =D33+E33-F33 -> #REF!
A34: 1544 | B34: Funeral Claim Application | C34: ream | E34: =SUMIFS('DATA ENTRY - REQUEST'!#REF!,'DATA ENTRY - REQUEST'!E:E,"=Funeral Claim Application") -> #REF! | F34: =SUMIFS('DATA ENTRY - REQUEST'!#REF!,'DATA ENTRY - REQUEST'!E:E,"=Funeral Claim Application") -> #REF! | G34: =D34+E34-F34 -> #REF!
A35: 1938 | B35: Death Claim Application | C35: ream | E35: =SUMIFS('DATA ENTRY - REQUEST'!#REF!,'DATA ENTRY - REQUEST'!E:E,"=Death Claim Application") -> #REF! | F35: =SUMIFS('DATA ENTRY - REQUEST'!#REF!,'DATA ENTRY - REQUEST'!E:E,"=Death Claim Application") -> #REF! | G35: =D35+E35-F35 -> #REF!
A36: 1949 | B36: Death Claim Application1 | C36: ream | G36: =D36+E36-F36 -> 0
A37: 1939 | B37: Retirement Claim Application Part I | C37: ream | E37: =SUMIFS('DATA ENTRY - REQUEST'!#REF!,'DATA ENTRY - REQUEST'!E:E,"=Retirement Claim Application Part I") -> #REF! | F37: =SUMIFS('DATA ENTRY - REQUEST'!#REF!,'DATA ENTRY - REQUEST'!E:E,"=Retirement Claim Application Part I") -> #REF! | G37: =D37+E37-F37 -> #REF!
A38: 1950 | B38: Retirement Claim Application Part II | C38: ream | E38: =SUMIFS('DATA ENTRY - REQUEST'!#REF!,'DATA ENTRY - REQUEST'!E:E,"=Bookpaper/Offset – A4") -> #REF! | F38: =SUMIFS('DATA ENTRY - REQUEST'!#REF!,'DATA ENTRY - REQUEST'!E:E,"=Retirement Claim Application Part II") -> #REF! | G38: =D38+E38-F38 -> #REF!
A39: 1667 | B39: DIsability Claim Application | C39: ream | G39: =D39+E39-F39 -> 0
A40: 1668 | B40: Medical Certificate dis. | C40: ream | G40: =D40+E40-F40 -> 0
A41: 1668 | B41: Medical Certificate (Disability Claim) | C41: ream | G41: =D41+E41-F41 -> 0
A42: 1727 | B42: R-5 - Mo Cont Payt Ret 3 ply 25 sets/pad | C42: pad | G42: =D42+E42-F42 -> 0
A43: 1856 | B43: Revised UMID | C43: ream | E43: =SUMIFS('DATA ENTRY - REQUEST'!#REF!,'DATA ENTRY - REQUEST'!E:E,"=Revised UMID") -> #REF! | F43: =SUMIFS('DATA ENTRY - REQUEST'!#REF!,'DATA ENTRY - REQUEST'!E:E,"=Revised UMID") -> #REF! | G43: =D43+E43-F43 -> #REF!
A44: 2400 | B44: TD-12 Petty CashVoucher25 sets/pad 4 ply | C44: pad | G44: =D44+E44-F44 -> 0
A45: 1976 | B45: Photo/Signature Card | C45: ream | G45: =D45+E45-F45 -> 0
A46: 2518 | B46: E-1 - Personal Data Re pre-prntd carbonl | C46: ream | G46: =D46+E46-F46 -> 0
G47: =D47+E47-F47 -> 0
A48: 2279 | B48: Sickness Notification | C48: ream | E48: =SUMIFS('DATA ENTRY - REQUEST'!#REF!,'DATA ENTRY - REQUEST'!E:E,"=Sickness Notification") -> #REF! | F48: =SUMIFS('DATA ENTRY - REQUEST'!#REF!,'DATA ENTRY - REQUEST'!E:E,"=Sickness Notification") -> #REF! | G48: x
A49: 2280 | B49: Sickness Benefit Reimbursement | C49: ream | E49: =SUMIFS('DATA ENTRY - REQUEST'!#REF!,'DATA ENTRY - REQUEST'!E:E,"=Bookpaper/Offset – A4") -> #REF! | F49: =SUMIFS('DATA ENTRY - REQUEST'!#REF!,'DATA ENTRY - REQUEST'!E:E,"=Retirement Claim Application Part II") -> #REF! | G49: =D49+E49-F49 -> #REF!
A50: 2281 | B50: Sickness Benefit Application P1 | C50: ream | E50: =SUMIFS('DATA ENTRY - REQUEST'!#REF!,'DATA ENTRY - REQUEST'!E:E,"=Bookpaper/Offset – A4") -> #REF! | F50: =SUMIFS('DATA ENTRY - REQUEST'!#REF!,'DATA ENTRY - REQUEST'!E:E,"=Retirement Claim Application Part II") -> #REF! | G50: =D50+E50-F50 -> #REF!
A51: 2291 | B51: Sickness Benefit Application P2 | C51: ream | E51: =SUMIFS('DATA ENTRY - REQUEST'!#REF!,'DATA ENTRY - REQUEST'!E:E,"=Bookpaper/Offset – A4") -> #REF! | F51: =SUMIFS('DATA ENTRY - REQUEST'!#REF!,'DATA ENTRY - REQUEST'!E:E,"=Retirement Claim Application Part II") -> #REF! | G51: =D51+E51-F51 -> #REF!
A52: 2282 | B52: Maternity Notification | C52: ream | G52: =D52+E52-F52 -> 0
A53: 2283 | B53: Maternity Reimbursement MAT2 pg. 1 | C53: ream | E53: =SUMIFS('DATA ENTRY - REQUEST'!#REF!,'DATA ENTRY - REQUEST'!E:E,"=Bookpaper/Offset – A4") -> #REF! | F53: =SUMIFS('DATA ENTRY - REQUEST'!#REF!,'DATA ENTRY - REQUEST'!E:E,"=Retirement Claim Application Part II") -> #REF! | G53: =D53+E53-F53 -> #REF!
A54: 2292 | B54: Maternity Reimbursement MAT2 pg. 2 | C54: ream | E54: =SUMIFS('DATA ENTRY - REQUEST'!#REF!,'DATA ENTRY - REQUEST'!E:E,"=Bookpaper/Offset – A4") -> #REF! | F54: =SUMIFS('DATA ENTRY - REQUEST'!#REF!,'DATA ENTRY - REQUEST'!E:E,"=Retirement Claim Application Part II") -> #REF! | G54: =D54+E54-F54 -> #REF!
A55: 2284 | B55: Maternity Benefit Application P1 | C55: ream | E55: =SUMIFS('DATA ENTRY - REQUEST'!#REF!,'DATA ENTRY - REQUEST'!E:E,"=Bookpaper/Offset – A4") -> #REF! | F55: =SUMIFS('DATA ENTRY - REQUEST'!#REF!,'DATA ENTRY - REQUEST'!E:E,"=Retirement Claim Application Part II") -> #REF! | G55: =D55+E55-F55 -> #REF!
A56: 2293 | B56: Maternity Benefit Application P2 | C56: ream | E56: =SUMIFS('DATA ENTRY - REQUEST'!#REF!,'DATA ENTRY - REQUEST'!E:E,"=Bookpaper/Offset – A4") -> #REF! | F56: =SUMIFS('DATA ENTRY - REQUEST'!#REF!,'DATA ENTRY - REQUEST'!E:E,"=Retirement Claim Application Part II") -> #REF! | G56: =D56+E56-F56 -> #REF!
A57: 2077 | B57: ESLD-1 - Salary Loan Application pg. 2 | C57: ream | G57: =D57+E57-F57 -> 0
A58: 2013 | B58: ESLD-1 - Salary Loan Application pg. 1 | C58: ream | G58: =D58+E58-F58 -> 0
B59: Complete OB History | C59: ream | G59: =D59+E59-F59 -> 0
A60: 2517 | B60: Request Verification Form | C60: ream | E60: =SUMIFS('DATA ENTRY - REQUEST'!#REF!,'DATA ENTRY - REQUEST'!E:E,"=Request Verification Form") -> #REF! | F60: =SUMIFS('DATA ENTRY - REQUEST'!#REF!,'DATA ENTRY - REQUEST'!E:E,"=Request Verification Form") -> #REF! | G60: =D60+E60-F60 -> #REF!
A61: 2519 | B61: E4 Member Data Change Request pg. 1 | C61: ream | E61: =SUMIFS('DATA ENTRY - REQUEST'!#REF!,'DATA ENTRY - REQUEST'!E:E,"=E4 Member Data Change Request pg. 1") -> #REF! | F61: =SUMIFS('DATA ENTRY - REQUEST'!#REF!,'DATA ENTRY - REQUEST'!E:E,"=E4 Member Data Change Request pg. 1") -> #REF! | G61: =D61+E61-F61 -> #REF!
A62: 2520 | B62: E4 Member Data Change Request pg. 2 | C62: ream | G62: =D62+E62-F62 -> 0
A63: 226 | B63: CLD 1.3 pg.1 | C63: ream | G63: =D63+E63-F63 -> 0
A64: 225 | B64: CLD 1.3 pg.2 | C64: ream | E64: =SUMIFS('DATA ENTRY - REQUEST'!#REF!,'DATA ENTRY - REQUEST'!E:E,"=Bookpaper/Offset – A4") -> #REF! | F64: =SUMIFS('DATA ENTRY - REQUEST'!#REF!,'DATA ENTRY - REQUEST'!E:E,"=Retirement Claim Application Part II") -> #REF! | G64: =D64+E64-F64 -> #REF!
A65: 227 | B65: CLD 1.3 pg.3 | C65: ream | E65: =SUMIFS('DATA ENTRY - REQUEST'!#REF!,'DATA ENTRY - REQUEST'!E:E,"=Bookpaper/Offset – A4") -> #REF! | F65: =SUMIFS('DATA ENTRY - REQUEST'!#REF!,'DATA ENTRY - REQUEST'!E:E,"=Retirement Claim Application Part II") -> #REF! | G65: =D65+E65-F65 -> #REF!
A66: 242 | B66: CLD 15 (Appointment as Representative) pag. 1 | C66: ream | G66: =D66+E66-F66 -> 0
A67: 243 | B67: CLD 15 (Appointment as Representative) pag. 2 | C67: ream | G67: =D67+E67-F67 -> 0
B68: Documentary Retirement Checklist | C68: ream | G68: =D68+E68-F68 -> 0
B69: Supplementary Retirement Checklist page 1 & 2 | C69: ream | G69: =D69+E69-F69 -> 0
B70: Supplementary Retirement Checklist page 3 | C70: ream | G70: =D70+E70-F70 -> 0
A71: 103 | B71: Funeral Check | C71: M | G71: =D71+E71-F71 -> 0
A72: 1551 | B72: Checklist – Death Claim Part 1 | C72: ream | G72: =D72+E72-F72 -> 0
A73: 1552 | B73: Checklist – Death Claim Part 2 | C73: ream | G73: =D73+E73-F73 -> 0
B74: Checklist – Funeral claim | C74: ream | G74: =D74+E74-F74 -> 0
B75: DDR Savings Account Form | C75: ream | G75: =D75+E75-F75 -> 0
B76: Affidavit of Separation from employment/ cessation of self-employments w/ undertaking | C76: ream | G76: =D76+E76-F76 -> 0
B77: Letter of Introduction | C77: ream | E77: =SUMIFS('DATA ENTRY - REQUEST'!#REF!,'DATA ENTRY - REQUEST'!E:E,"=Letter of Introduction") -> #REF! | F77: =SUMIFS('DATA ENTRY - REQUEST'!#REF!,'DATA ENTRY - REQUEST'!E:E,"=Letter of Introduction") -> #REF! | G77: =D77+E77-F77 -> #REF!
B78: Affidavit of Dependent Parents | C78: ream | G78: =D78+E78-F78 -> 0
B79: Checklist – Death Claim Revised | C79: ream | G79: =D79+E79-F79 -> 0
A80: 2377 | B80: Pre-printed form special paper for Employer Certificate of registration | C80: pc | E80: =SUMIFS('DATA ENTRY - REQUEST'!#REF!,'DATA ENTRY - REQUEST'!E:E,"=Pre-printed form special paper for Employer Certificate of registration") -> #REF! | F80: =SUMIFS('DATA ENTRY - REQUEST'!#REF!,'DATA ENTRY - REQUEST'!E:E,"=Pre-printed form special paper for Employer Certificate of registration") -> #REF! | G80: =D80+E80-F80 -> #REF!
A81: 252 | B81: Report of Death Form (BPN-105) | C81: ream | G81: =D81+E81-F81 -> 0
A82: 232 | B82: BPN-107 (Guarantor's Form) page 1 | C82: ream | G82: =D82+E82-F82 -> 0
A83: 233 | B83: BPN-107 (Guarantor's Form) page 2 | C83: ream | G83: =D83+E83-F83 -> 0
B84: Sickness and Maternity Benefits Payment Thru the Bank Form | C84: ream | G84: =D84+E84-F84 -> 0
B85: PESO Fund Payment Form | C85: ream | G85: =D85+E85-F85 -> 0
B86: DDR-2 (Flexi-fund Program) | C86: ream | G86: =D86+E86-F86 -> 0
A87: 241 | B87: Medical Report (Form MD-15) | C87: ream | G87: =D87+E87-F87 -> 0
A88: 2521 | B88: Contribution Payment Slip | C88: ream | G88: =D88+E88-F88 -> 0
B89: Member's Web Registration | C89: ream | G89: =D89+E89-F89 -> 0
B90: Eployer Web Registration | C90: ream | G90: =D90+E90-F90 -> 0
A91: 2508 | B91: Updated Terms & Conditions sheet – PLP | C91: ream | G91: =D91+E91-F91 -> 0
B92: EC Medical Reimbursement Form | C92: ream | G92: =D92+E92-F92 -> 0
A94: 2157 | B94: Toner Samsung M3820ND | C94: pc | D94: 3 | E94: =SUMIFS('DATA ENTRY - REQUEST'!#REF!,'DATA ENTRY - REQUEST'!E:E,"=Toner Samsung M3820ND") -> #REF! | F94: =SUMIFS('DATA ENTRY - REQUEST'!#REF!,'DATA ENTRY - REQUEST'!E:E,"=Toner Samsung M3820ND") -> #REF! | G94: =D94+E94-F94 -> #REF!
A95: 2201 | B95: Toner for Brother HL-5450DN | C95: pc | D95: 5 | E95: =SUMIFS('DATA ENTRY - REQUEST'!#REF!,'DATA ENTRY - REQUEST'!E:E,"=Toner for Brother HL-5450DN") -> #REF! | F95: =SUMIFS('DATA ENTRY - REQUEST'!#REF!,'DATA ENTRY - REQUEST'!E:E,"=Toner for Brother HL-5450DN") -> #REF! | G95: =D95+E95-F95 -> #REF!
A96: UBP | B96: UBP QUICK CARDS - PENSION LOAN | C96: pc | D96: 0 | E96: =SUMIFS('DATA ENTRY - REQUEST'!#REF!,'DATA ENTRY - REQUEST'!E:E,"=UBP QUICK CARDS - PENSION LOAN") -> #REF! | F96: =SUMIFS('DATA ENTRY - REQUEST'!#REF!,'DATA ENTRY - REQUEST'!E:E,"=UBP QUICK CARDS - PENSION LOAN") -> #REF! | G96: =D96+E96-F96 -> #REF!
A103: SUPPLIES OTHERS | G103: x
A104: 300 | B104: Tape – Masking | C104: roll | E104: =SUMIFS('DATA ENTRY - REQUEST'!#REF!,'DATA ENTRY - REQUEST'!E:E,"=Tape – Masking") -> #REF! | F104: =SUMIFS('DATA ENTRY - REQUEST'!#REF!,'DATA ENTRY - REQUEST'!E:E,"=Tape - Transparent 1") -> #REF! | G104: =D104+E104-F104 -> #REF!
A105: 301 | B105: Tape - Transparent 1 | C105: pc | E105: =SUMIFS('DATA ENTRY - REQUEST'!#REF!,'DATA ENTRY - REQUEST'!E:E,"=Tape - Transparent 1") -> #REF! | F105: =SUMIFS('DATA ENTRY - REQUEST'!#REF!,'DATA ENTRY - REQUEST'!E:E,"=Tape - Transparent 1") -> #REF! | G105: =D105+E105-F105 -> #REF!
A106: 305 | B106: Paper Fastener, 50 pcs | C106: box | G106: =D106+E106-F106 -> 0
A107: 307 | B107: Rubber Band – Multicolor | C107: box | G107: =D107+E107-F107 -> 0
...

Sheet RIS FORM V112022
D1: Republic of the Philippines | BF1: 2026-007
D2: SOCIAL SECURITY SYSTEM
D3: Office Services Department
D4: REQUISITION AND ISSUE SLIP
D6: REQUESTING UNIT | AD6: COST CENTER | AQ6: RIS NO.
D7: ILIGAN BRANCH | AD7: 121410014 | AQ7: ILI- | AV7: =BF1 -> 2026-007
D8: REQUISITION | AQ8: ISSUE
F9: STOCK CODE | J9: UNIT OF MEASUREMENT | Q9: DESCRIPTION | AJ9: QUANTITY | AQ9: STATUS/ REMARKS | AZ9: QUANTITY
A10: 1 | B10: =CONCATENATE(BF$1,A10) -> 2026-0071 | C10: =IFERROR(VLOOKUP(B10,REQUEST1,3,0),"-") -> Bond copy paper, A4 size,70gsm 500shts/rm | D10: 1 | F10: =IFERROR(VLOOKUP(Q10,SUPPLY2,4,0),"-") -> 2276 | J10: =IFERROR(VLOOKUP(Q10,SUPPLY2,3,0),"-") -> Ream | Q10: =C10 -> Bond copy paper, A4 size,70gsm 500shts/rm | AJ10: =IFERROR(VLOOKUP(B10,REQUEST2,4,0),"-") -> 50
A11: 2 | B11: =CONCATENATE(BF$1,A11) -> 2026-0072 | C11: =IFERROR(VLOOKUP(B11,REQUEST1,3,0),"-") -> Bond prem,LEGAL SIZE, 216x330mm,70gsm 500shts/rm | D11: 2 | F11: =IFERROR(VLOOKUP(Q11,SUPPLY2,4,0),"-") -> 2067 | J11: =IFERROR(VLOOKUP(Q11,SUPPLY2,3,0),"-") -> Ream | Q11: =C11 -> Bond prem,LEGAL SIZE, 216x330mm,70gsm 500shts/rm | AJ11: =IFERROR(VLOOKUP(B11,REQUEST2,4,0),"-") -> 30
A12: 3 | B12: =CONCATENATE(BF$1,A12) -> 2026-0073 | C12: =IFERROR(VLOOKUP(B12,REQUEST1,3,0),"-") -> MEMBER DATA CHANGE REQUEST PAGE 1&2 | D12: 3 | F12: =IFERROR(VLOOKUP(Q12,SUPPLY2,4,0),"-") -> 0 | J12: =IFERROR(VLOOKUP(Q12,SUPPLY2,3,0),"-") -> Ream | Q12: =C12 -> MEMBER DATA CHANGE REQUEST PAGE 1&2 | AJ12: =IFERROR(VLOOKUP(B12,REQUEST2,4,0),"-") -> 50
A13: 4 | B13: =CONCATENATE(BF$1,A13) -> 2026-0074 | C13: =IFERROR(VLOOKUP(B13,REQUEST1,3,0),"-") -> ACOP- SURVIVING LEGAL SPOUSE | D13: 4 | F13: =IFERROR(VLOOKUP(Q13,SUPPLY2,4,0),"-") -> 0 | J13: =IFERROR(VLOOKUP(Q13,SUPPLY2,3,0),"-") -> Ream | Q13: =C13 -> ACOP- SURVIVING LEGAL SPOUSE | AJ13: =IFERROR(VLOOKUP(B13,REQUEST2,4,0),"-") -> 10
A14: 5 | B14: =CONCATENATE(BF$1,A14) -> 2026-0075 | C14: =IFERROR(VLOOKUP(B14,REQUEST1,3,0),"-") -> Envelope - document, 10 x 15 | D14: 5 | F14: =IFERROR(VLOOKUP(Q14,SUPPLY2,4,0),"-") -> 46 | J14: =IFERROR(VLOOKUP(Q14,SUPPLY2,3,0),"-") -> C | Q14: =C14 -> Envelope - document, 10 x 15 | AJ14: =IFERROR(VLOOKUP(B14,REQUEST2,4,0),"-") -> 10
A15: 6 | B15: =CONCATENATE(BF$1,A15) -> 2026-0076 | C15: =IFERROR(VLOOKUP(B15,REQUEST1,3,0),"-") -> Folder - legal size, 36mm thick (14pts) | D15: 6 | F15: =IFERROR(VLOOKUP(Q15,SUPPLY2,4,0),"-") -> 330 | J15: =IFERROR(VLOOKUP(Q15,SUPPLY2,3,0),"-") -> C | Q15: =C15 -> Folder - legal size, 36mm thick (14pts) | AJ15: =IFERROR(VLOOKUP(B15,REQUEST2,4,0),"-") -> 10
A16: 7 | B16: =CONCATENATE(BF$1,A16) -> 2026-0077 | C16: =IFERROR(VLOOKUP(B16,REQUEST1,3,0),"-") -> Tape - transparent 1 | D16: 7 | F16: =IFERROR(VLOOKUP(Q16,SUPPLY2,4,0),"-") -> 301 | J16: =IFERROR(VLOOKUP(Q16,SUPPLY2,3,0),"-") -> Roll | Q16: =C16 -> Tape - transparent 1 | AJ16: =IFERROR(VLOOKUP(B16,REQUEST2,4,0),"-") -> 20
A17: 8 | B17: =CONCATENATE(BF$1,A17) -> 2026-0078 | C17: =IFERROR(VLOOKUP(B17,REQUEST1,3,0),"-") -> Alcohol, ethyl, 68%-72% (500ml) | D17: 8 | F17: =IFERROR(VLOOKUP(Q17,SUPPLY2,4,0),"-") -> 2618 | J17: =IFERROR(VLOOKUP(Q17,SUPPLY2,3,0),"-") -> Bottle | Q17: =C17 -> Alcohol, ethyl, 68%-72% (500ml) | AJ17: =IFERROR(VLOOKUP(B17,REQUEST2,4,0),"-") -> 50
A18: 9 | B18: =CONCATENATE(BF$1,A18) -> 2026-0079 | C18: =IFERROR(VLOOKUP(B18,REQUEST1,3,0),"-") -> PAYMENT SLIP-CONTRIBUTION 1 | D18: 9 | F18: =IFERROR(VLOOKUP(Q18,SUPPLY2,4,0),"-") -> 2521 | J18: =IFERROR(VLOOKUP(Q18,SUPPLY2,3,0),"-") -> Ream | Q18: =C18 -> PAYMENT SLIP-CONTRIBUTION 1 | AJ18: =IFERROR(VLOOKUP(B18,REQUEST2,4,0),"-") -> 50
A19: 10 | B19: =CONCATENATE(BF$1,A19) -> 2026-00710 | C19: =IFERROR(VLOOKUP(B19,REQUEST1,3,0),"-") -> Staple wire, 5000 pcs | D19: 10 | F19: =IFERROR(VLOOKUP(Q19,SUPPLY2,4,0),"-") -> 310 | J19: =IFERROR(VLOOKUP(Q19,SUPPLY2,3,0),"-") -> Box | Q19: =C19 -> Staple wire, 5000 pcs | AJ19: =IFERROR(VLOOKUP(B19,REQUEST2,4,0),"-") -> 50
A20: 11 | B20: =CONCATENATE(BF$1,A20) -> 2026-00711 | C20: =IFERROR(VLOOKUP(B20,REQUEST1,3,0),"-") -> Ballpoint pen | D20: 11 | F20: =IFERROR(VLOOKUP(Q20,SUPPLY2,4,0),"-") -> 337 | J20: =IFERROR(VLOOKUP(Q20,SUPPLY2,3,0),"-") -> Piece | Q20: =C20 -> Ballpoint pen | AJ20: =IFERROR(VLOOKUP(B20,REQUEST2,4,0),"-") -> 100
A21: 12 | B21: =CONCATENATE(BF$1,A21) -> 2026-00712 | C21: =IFERROR(VLOOKUP(B21,REQUEST1,3,0),"-") -> ACOP- REPRESENTATIVE PAYEE OF DEPENDENT | D21: 12 | F21: =IFERROR(VLOOKUP(Q21,SUPPLY2,4,0),"-") -> 0 | J21: =IFERROR(VLOOKUP(Q21,SUPPLY2,3,0),"-") -> Ream | Q21: =C21 -> ACOP- REPRESENTATIVE PAYEE OF DEPENDENT | AJ21: =IFERROR(VLOOKUP(B21,REQUEST2,4,0),"-") -> 10
... A54: 46 | B54: =CONCATENATE(BF$1,A54) -> 2026-00746 | C54: =IFERROR(VLOOKUP(B54,REQUEST1,3,0),"-") -> - | D54: 46 | F54: =IFERROR(VLOOKUP(Q54,SUPPLY2,4,0),"-") -> - | J54: =IFERROR(VLOOKUP(Q54,SUPPLY2,3,0),"-") -> - | Q54: =C54 -> - | AJ54: =IFERROR(VLOOKUP(B54,REQUEST2,4,0),"-") -> -
D55: REQUESTED BY
F56: ARNEL Y. BALISTOY | AB56: CEO I- Admin Head | AT56: 46216
F57: SIGNATURE OVER PRINTED NAME | AB57: POSITION TITLE | AT57: DATE AND TIME
D58: SCREENED AND ISSUED BY
F60: SIGNATURE OVER PRINTED NAME | AB60: POSITION TITLE | AT60: DATE AND TIME
D61: APPROVED FOR ISSUANCE BY
F62: MARIBETH D. VALDE | AB62: Acting Head, AGAS, MND
F63: SIGNATURE OVER PRINTED NAME | AB63: POSITION TITLE | AT63: DATE AND TIME
D64: RECEIVED FOR SHIPMENT BY
F66: SIGNATURE OVER PRINTED NAME | AB66: POSITION TITLE | AT66: DATE AND TIME
D67: ACKNOWLEDGEMENT OF RECEIPT BY BRANCH OFFICE/UNIT
D68: This is to certify that I have received the above stated supplies and materials as issued.
F70: SIGNATURE OVER PRINTED NAME | AB70: POSITION TITLE | AT70: DATE AND TIME

Sheet ENDING BAL
A1: DESCRIPTION | B1: # OF STOCKS | C1: DATE

Sheet 082023
A1: MONTHLY INVENTORY OF SUPPLIES AND MATERIALS FOR C.Y. 2023
A2: DEPARTMENT/BRANCH NAME: ILIGAN BRANCH
A3: Mat Code | B3: Material description | C3: B. UOM | D3: AUGUST 2023
A4: Paper & Paper Products | D4: CONSUMPTION (including purchase thru CBA) | E4: STOCK ON HAND
A5: 2276 | B5: Bond copy paper, a4 size,70gsm 500shts/rm | C5: Ream | D5: 34 | E5: 0
A6: 2067 | B6: Bond prem,ls, 216x330mm,70gsm 500shts/rm | C6: Ream | D6: 17 | E6: 0
A7: 2634 | B7: Carbon film, legal | C7: Box | D7: 0 | E7: 0
A8: 5 | B8: Cartolina - white, 22-1/2 x 28-1/2 | C8: Piece | D8: 0 | E8: 0
A9: 46 | B9: Envelope - document, 10 x 15 | C9: C | D9: 55 | E9: 0
A10: 59 | B10: Envelope - expanding 11x15x 2 w/out flap | C10: Piece | D10: 0 | E10: 0
A11: 40 | B11: Envelope - window reg mailing only white (500 pcs/box) | C11: Box | D11: 0 | E11: 0
A12: 1695 | B12: Envelope-wdw reg no add white for brnchs (500 pcs/box) | C12: Box | D12: 0 | E12: 0
A13: 2366 | B13: Envelope, expanding kraftboard for legal docs. | C13: Piece | D13: 0 | E13: 0
A14: 331 | B14: Folder - cardboard loose lift 8-1/2x14 | C14: Set | D14: 0 | E14: 0
A15: 330 | B15: Folder - legal size, 36mm thick (14pts) | C15: C | D15: 200 | E15: 0
A16: 65 | B16: Folder - marble green, 11 x 14-7/8 | C16: Set | D16: 0 | E16: 0
... A18: 1823 | B18: Paper-bond w/letterhead, a4 size 70gsm | C18: Ream | D18: 0 | E18: 0
A20: Mat Code | B20: Material description | C20: B. UOM | D20: =D3 -> AUGUST 2023
A21: IT Supplies | D21: CONSUMPTION (including purchase thru CBA) | E21: STOCK ON HAND
A22: 2252 | B22: Drum for brother hl 5450 printer | C22: Piece | D22: 0 | E22: 0
A23: 2646 | B23: Kyocera laser printer tk- 5244, Cyan (new carried on stock) | C23: Unit | D23: 0 | E23: 0
A24: 2649 | B24: Kyocera laser printer tk- 5244, Black (new carried on stock) | C24: Unit | D24: 0 | E24: 0
A25: 2647 | B25: Kyocera laser printer tk- 5244, Magenta (new carried on stock) | C25: Unit | D25: 0 | E25: 0
A26: 2648 | B26: Kyocera laser printer tk- 5244, Yellow (new carried on stock) | C26: Unit | D26: 0 | E26: 0
A27: 2627 | B27: Lto ultrium 6, 6.25tb c/o dcod | C27: Unit | D27: 0 | E27: 0
A28: 2628 | B28: Lto ultrium 7, 7.15tb c/o dcod | C28: Unit | D28: 0 | E28: 0
A29: 137 | B29: Ribbon – ERC-31 for TMU-950 (epson) | C29: Piece | D29: 0 | E29: 0
A30: 2416 | B30: Ribbon tally dascom 1330 99007 | C30: Piece | D30: 0 | E30: 0
A31: 2629 | B31: Thermal paper for set 80 x 30mm | C31: Roll | D31: 0 | E31: 0
A32: 2388 | B32: Toner for Samsung M3820ND MLT-D203E (High Yield) | C32: Unit | D32: 0 | E32: 0
A33: 2540 | B33: Toner- for Canon LBP 6780X (Compatible) | C33: Unit | D33: 1 | E33: 0
... A36: 81 | B36: TSF - 11x8-1/2 1 ply 2000 shts/box | C36: M | D36: 0 | E36: 0
A38: Mat Code | B38: Material description | C38: B. UOM | D38: =D20 -> AUGUST 2023
A39: Printed Forms | D39: CONSUMPTION (including purchase thru CBA) | E39: STOCK ON HAND
A40: 276 | B40: ACOP-PENSIONERS REPLY P1&2 | C40: Ream | D40: 0 | E40: 0
A41: 1938 | B41: DEATH CLAIM APPLICATION PAGE 1 | C41: Ream | D41: 3 | E41: 0
A42: 1949 | B42: DEATH CLAIM APPLICATION PAGE 2 | C42: Ream | D42: 3 | E42: 0
A43: 2519 | B43: E4-PAGE 1-MEMBER DATA CHANGE PAGE 1 | C43: Ream | D43: 0 | E43: 0
A44: 2520 | B44: E4-PAGE 2-MEMBER DATA CHANGE PAGE 2 | C44: Ream | D44: 0 | E44: 0
A45: 222 | B45: L-501-SPECIMENT SIGNATURE CARD | C45: PC | D45: 0 | E45: 0
A46: 1976 | B46: MEMBER'S/CLAIMANT'S PHOTO SIGNATURE CARD | C46: Ream | D46: 0 | E46: 0
A47: 2521 | B47: PAYMENT SLIP-CONTRIBUTION | C47: Ream | D47: 0 | E47: 0
A48: 2576 | B48: PAYMENT SLIP-MEMBER LOAN | C48: Ream | D48: 0 | E48: 0
A49: 2399 | B49: R-6 Misc p.r, 25shts 07'13 (carbonless) | C49: Pad | D49: 3 | E49: 0
A50: 199 | B50: REGISTRY RETURN RECEIPT CARD | C50: PC | D50: 0 | E50: 0
A51: 2386 | B51: Rel-9 rep 25sets/pad 4ply (carbonless) | C51: Pad | D51: 0 | E51: 0
... A53: 1950 | B53: RETIREMENT P.2 | C53: Ream | D53: 2 | E53: 0
A55: Mat Code | B55: Material description | C55: B. UOM | D55: =D38 -> AUGUST 2023
A56: Supplies – Others | D56: CONSUMPTION (including purchase thru CBA) | E56: STOCK ON HAND
A57: 2617 | B57: Alcohol, ethyl, 68%-72% | C57: Gallon | D57: 0 | E57: 0
A58: 2618 | B58: Alcohol, ethyl, 68%-72% (500ml) | C58: Bottle | D58: 15 | E58: 15
A59: 337 | B59: Ballpoint pen | C59: Piece | D59: 0 | E59: 0
A60: 2551 | B60: Binder clip 1 1/4” | C60: Box | D60: 0 | E60: 0
A61: 2550 | B61: Binder clip 1” | C61: Box | D61: 0 | E61: 0
A62: 2552 | B62: Binder clip 2” | C62: Box | D62: 0 | E62: 0
A63: 2546 | B63: Binder clip 3/4” | C63: Box | D63: 0 | E63: 0
A64: 1960 | B64: Correction tape | C64: Piece | D64: 0 | E64: 0
A65: 313 | B65: Corrugated box | C65: Set | D65: 0 | E65: 0
A66: 2631 | B66: File Organizer | C66: Piece | D66: 0 | E66: 0
A67: 312 | B67: Empty cartons | C67: Piece | D67: 0 | E67: 0
A68: 2536 | B68: Flag 3 x 6 | C68: Piece | D68: 0 | E68: 0
... A94: 344 | B94: Waste basket | C94: Piece | D94: 0 | E94: 0

Sheet new INVENTORY
A1: MONTHLY INVENTORY OF SUPPLIES AND MATERIALS FOR C.Y. 2022
A2: DEPARTMENT/BRANCH NAME:
A3: Mat Code | B3: Material description | C3: B. UOM | D3: NOVEMBER 2022 | F3: DECEMBER 2022 | H3: AUGUST 2022 | J3: SEPTEMBER 2022 | L3: 44927
A4: Paper & Paper Products | D4: CONSUMPTION (including purchase thru CBA) | E4: STOCK ON HAND | F4: CONSUMPTION (including purchase thru CBA) | G4: STOCK ON HAND | H4: CONSUMPTION (including purchase thru CBA) | I4: STOCK ON HAND | J4: CONSUMPTION (including purchase thru CBA) | K4: STOCK ON HAND | L4: CONSUMPTION (including purchase thru CBA) | M4: STOCK ON HAND
A5: 2276 | B5: Bond copy paper, a4 size,70gsm 500shts/rm | C5: Ream | D5: 34 | E5: 26 | F5: 26 | G5: 0 | H5: 20 | I5: 0 | K5: 0
A6: 2067 | B6: Bond prem,ls, 216x330mm,70gsm 500shts/rm | C6: Ream | D6: 17 | E6: 3 | F6: 3 | G6: 0 | I6: 0 | K6: 0
A7: 2634 | B7: Carbon film, legal | C7: Box | D7: 0 | E7: 0 | F7: 0 | G7: 0 | I7: 0 | K7: 0
A8: 5 | B8: Cartolina - white, 22-1/2 x 28-1/2 | C8: Piece | D8: 0 | E8: 0 | F8: 0 | G8: 0 | I8: 0 | K8: 0
A9: 46 | B9: Envelope - document, 10 x 15 | C9: C | D9: 55 | E9: 145 | F9: 50 | G9: 95 | I9: 50 | K9: 25
A10: 59 | B10: Envelope - expanding 11x15x 2 w/out flap | C10: Piece | D10: 0 | E10: 0 | F10: 0 | G10: 0 | I10: 0 | K10: 0
A11: 40 | B11: Envelope - window reg mailing only white (500 pcs/box) | C11: Box | D11: 0 | E11: 0 | F11: 0 | G11: 0 | I11: 0 | K11: 0
A12: 1695 | B12: Envelope-wdw reg no add white for brnchs (500 pcs/box) | C12: Box | D12: 0 | E12: 0 | F12: 0 | G12: 0 | I12: 0 | K12: 0
A13: 2366 | B13: Envelope, expanding kraftboard for legal docs. | C13: Piece | D13: 0 | E13: 0 | F13: 0 | G13: 0 | I13: 0 | K13: 0
A14: 331 | B14: Folder - cardboard loose lift 8-1/2x14 | C14: Set | D14: 0 | E14: 0 | F14: 0 | G14: 0 | I14: 0 | K14: 0
A15: 330 | B15: Folder - legal size, 36mm thick (14pts) | C15: C | D15: 200 | E15: 0 | F15: 0 | G15: 0 | I15: 0 | K15: 0
A16: 65 | B16: Folder - marble green, 11 x 14-7/8 | C16: Set | D16: 0 | E16: 0 | F16: 0 | G16: 0 | I16: 0 | K16: 0
A17: 70 | B17: Paper - adding machine tape, 2-1/4 | C17: Piece | D17: 0 | E17: 0 | F17: 0 | G17: 0 | I17: 0 | K17: 0
A18: 1823 | B18: Paper-bond w/letterhead, a4 size 70gsm | C18: Ream | D18: 0 | E18: 0 | F18: 0 | G18: 0 | I18: 0 | K18: 0
D21: NOVEMBER 2022 | F21: DECEMBER 2022 | H21: AUGUST 2022 | J21: SEPTEMBER 2022 | L21: OCOTBER 2022
A22: IT Supplies | D22: CONSUMPTION (including purchase thru CBA) | E22: STOCK ON HAND | F22: CONSUMPTION (including purchase thru CBA) | G22: STOCK ON HAND | H22: CONSUMPTION (including purchase thru CBA) | I22: STOCK ON HAND | J22: CONSUMPTION (including purchase thru CBA) | K22: STOCK ON HAND | L22: CONSUMPTION (including purchase thru CBA) | M22: STOCK ON HAND
A23: 2252 | B23: Drum for brother hl 5450 printer | C23: Piece | D23: 0 | E23: 9 | F23: 1 | G23: 8 | H23: 0 | I23: 10 | J23: 0 | K23: 10
A24: 2646 | B24: Kyocera laser printer tk- 5244, Cyan (new carried on stock) | C24: Unit | D24: 0 | E24: 0 | F24: 0 | G24: 0 | H24: 0 | I24: 0 | J24: 0 | K24: 0
A25: 2649 | B25: Kyocera laser printer tk- 5244, Black (new carried on stock) | C25: Unit | D25: 0 | E25: 0 | F25: 0 | G25: 0 | H25: 0 | I25: 0 | J25: 0 | K25: 0
A26: 2647 | B26: Kyocera laser printer tk- 5244, Magenta (new carried on stock) | C26: Unit | D26: 0 | E26: 0 | F26: 0 | G26: 0 | H26: 0 | I26: 0 | J26: 0 | K26: 0
A27: 2648 | B27: Kyocera laser printer tk- 5244, Yellow (new carried on stock) | C27: Unit | D27: 0 | E27: 0 | F27: 0 | G27: 0 | H27: 0 | I27: 0 | J27: 0 | K27: 0
A28: 2627 | B28: Lto ultrium 6, 6.25tb c/o dcod | C28: Unit | D28: 0 | E28: 0 | F28: 0 | G28: 0 | H28: 0 | I28: 0 | J28: 0 | K28: 0
A29: 2628 | B29: Lto ultrium 7, 7.15tb c/o dcod | C29: Unit | D29: 0 | E29: 0 | F29: 0 | G29: 0 | H29: 0 | I29: 0 | J29: 0 | K29: 0
A30: 137 | B30: Ribbon – ERC-31 for TMU-950 (epson) | C30: Piece | D30: 0 | E30: 0 | F30: 0 | G30: 0 | H30: 0 | I30: 10 | J30: 0 | K30: 10
A31: 2416 | B31: Ribbon tally dascom 1330 99007 | C31: Piece | D31: 0 | E31: 0 | F31: 0 | G31: 0 | H31: 0 | I31: 0 | J31: 0 | K31: 0
A32: 2629 | B32: Thermal paper for set 80 x 30mm | C32: Roll | D32: 0 | E32: 20 | F32: 0 | G32: 20 | H32: 0 | I32: 20 | J32: 0 | K32: 20
A33: 2388 | B33: Toner for Samsung M3820ND MLT-D203E (High Yield) | C33: Unit | D33: 0 | E33: 3 | F33: 0 | G33: 3 | H33: 0 | I33: 3 | J33: 0 | K33: 3
A34: 2540 | B34: Toner- for Canon LBP 6780X (Compatible) | C34: Unit | D34: 1 | E34: 12 | F34: 1 | G34: 12 | H34: 1 | I34: 13 | J34: 0 | K34: 13
... A37: 81 | B37: TSF - 11x8-1/2 1 ply 2000 shts/box | C37: M | D37: 0 | E37: 0 | F37: 0 | G37: 0 | H37: 0 | I37: 0 | J37: 0 | K37: 0
D40: NOVEMBER 2022 | F40: DECEMBER 2022 | H40: AUGUST 2022 | J40: SEPTEMBER 2022 | L40: OCOTBER 2022
A41: Printed Forms | D41: CONSUMPTION (including purchase thru CBA) | E41: STOCK ON HAND | F41: CONSUMPTION (including purchase thru CBA) | G41: STOCK ON HAND | H41: CONSUMPTION (including purchase thru CBA) | I41: STOCK ON HAND | J41: CONSUMPTION (including purchase thru CBA) | K41: STOCK ON HAND | L41: CONSUMPTION (including purchase thru CBA) | M41: STOCK ON HAND
A42: 276 | B42: ACOP-PENSIONERS REPLY P1&2 | C42: Ream | D42: 0 | E42: 0 | F42: 0 | G42: 0 | H42: 0 | I42: 0 | J42: 0 | K42: 0
